Workbook
Name A: [1]MRD!$A$1:$BB$1866
Name A: [1]MRD!$A$1:$BB$1866
Name MRD: [2]MRD!$A$1:$BB$2983
Name MRD: [3]MRD!$A$1:$BB$2167

Sheet Requisiciones
A1: Número Requisicion | B1: Empresa | C1: Unidad | D1: Fecha Recepción | E1: Fecha de aprobación Requisición | F1: Regional | G1: Ciudad | H1: Tipo Servicio | I1: Cargo Solicitado | J1: Tipo Cargo Solicitado | K1: Psicologo Responsable | L1: # Personas Solicitadas | M1: Estado Requisición | N1: Fecha Afinamiento Perfil | O1: # hojas de vida presentadas al cliente | P1: ¿Pertenece a la Primera Terna? | Q1: Fecha entrega hoja de vida al cliente | R1: Fecha de aprobación de HV por el cliente | S1: Número de hojas de vida aprobadas por el cliente | T1: Fecha de envio del perfil | U1: Fecha Publicación de Concurso | V1: Fecha entrega matriz de inscritos | W1: Fecha Notificación quienes continúan a prueba técnica | X1: Fecha aplicación Prueba técnica | Y1: Fecha envío prueba técnica al cliente | Z1: Fecha Notificación quienes continúan a proceso de selección | AA1: Número de personas evaluadas | AB1: Número de informes entregados | AC1: Número de referencias | AD1: Fecha de entrega de informe al cliente | AE1: Fecha de notificación del cliente persona seleccionada | AF1: Fecha de solicitud contratacion | AG1: Fecha Firma Contrato o Cierre de requisición | AH1: Fecha de Ingreso | AI1: Mes | AJ1: Candidato(s) contratado(s): | AK1: Observacion | AL1: Efectividad reclutamiento | AM1: Oportunidad en el proceso de reclutamiento | AN1: Oportunidad en proceso de Selección | AO1: Dias a Descontar Selección | AP1: Oportunidad Selección | AQ1: Oportunidad en proceso de Contratación | AR1: Dias a Descontar Contratación | AS1: Oportunidad Contratacion | AT1: Tiempo Total Proceso | AU1: Oportunidad SyC | AV1: Fuente de Reclutamiento | AW1: Ultima empresa donde trabajó | AX1: Candidato 1 | AY1: Candidato 2 | AZ1: Candidato 3 | BA1: Candidato 4 | BB1: Candidato 5
A2: 14104 | B2: FUNDACION COOMEVA | C2: FUNDACION COOMEVA | D2: 45909 | E2: 45797 | F2: Medellin | G2: MEDELLIN | H2: VACANTE DESDE RECLUTAMIENTO | I2: SUPERNUMERARIO/A | J2: CARGO COMERCIAL | K2: Fredy Alejandro Villada Posada | L2: 1 | M2: Finalizado - Llego hasta contratacion | N2: 0000-00-00 | O2: 18 | P2: No | Q2: 46027 | R2: 46027 | S2: 15 | T2: 0000-00-00 | U2: 0000-00-00 | V2: 0000-00-00 | W2: 0000-00-00 | X2: 0000-00-00 | Y2: 0000-00-00 | Z2: 0000-00-00 | AA2: 5 | AB2: 5 | AC2: 0 | AD2: 46031 | AE2: 46037 | AF2: 46037 | AG2: 46048 | AH2: 46048 | AI2: =MONTH(AH2) -> 1 | AJ2: Juan Camilo Cuartas Echeverri | AK2: 20250520: GH solicita reclutamiento, se le solicita a GH el aval del corporativo para continuar. 20250521: Se detiene vacante hasta tener aval del corporativo. 20250618: Se reanuda proceso por cargo en estructura de la empresa, pdte enviar reclutamiento. 20250624: Se envian 3 HV (Tatiana, Isabella, Cristian), pdte retro GH. 20250701: gh solicita realizar prueba tecnica de Isabella Gonzales y Cristian Amaguaña. 20250702: se adjunta prueba tecnica. pte retro por gh. 20250704: solicitan evaluar a isabella para Analista Reg Microcredito FUN y Cristian no avanza prueba tecnica. Se activa reclutamiento. 20250707: Se envia 2 hv. pte retro por gh. 20250715: gh envia retro y solicita avanzar a prueba tecnica con Juan Carlos Roman. 20250717: se envia prueba tecnica de Juan Roman. Pte retro por gh. 20250724: gh solicita reasignar requi a la Ciudad de Medellin por cambio de la pocision. 20250724: GH notifica el cambio de RQ para la ciudad de Medellin, se informa que se tendrá en cuenta los candidatos en back de la vacante como Analista de Microcredito. 20250728: se hace el ofrecimiento a la candidata Luby Dayana Guisao quien acepta, sin embargo, se hace validacion con JI para valorar la disponibilidad de viajar. 20250801: candidata se presenta a entrevista, sin embargo, por solicitud de JI se solicita buscar nuevos candidatos considerando que la candidata podría no cumplir con los requisitos para la disponibilidad de viaje. 20250805: se comparte 1 HV a la espera de disponibilidad para entrevista. 20250806: se programa entrevista para el viernes 8 de ago. 20250811: Gh indica que no fue posible conectarse al espacio. 20250812: JI solicita programar la entrevista para el miércoles 13 y se comparten 2 HV (Marlon Pacheco) adicionales. 20250813: se presenta el candidato Marlon Pacheco y continua proceso para aplicar PS. 20250819: se comparte retroliamentacion con concepto aprobado de Marlon Pacheco 20250822: se solicita retroalimentacion a GH y JI. 20250825: JI manfiesta la intención de que el candidato sea contratado en la RQ 14772 para Analista Regional. 20250826: se continua reclutamiento. 20250827: JI mangiiesta que el candidato Marlon Pacheco desea continuar el proceso para supernumerario, sin embargo, el candidato no responde los mensajes 20250829: se comparten 2 HV para entrevista el 2 de sep. 20250902: se presetan dos candidatos, pero no aprueban proceso de entrevista. 20250908: se envían 3 HV para entrevista el 9 de sep. 20250909: se presentan dos candidatos, uno aprueba el proceso pero será tenido en cuenta para la RQ 14772 Ana de Microcrédito. 20250911: se comparte 1 HV adicional (Felipe Guerra) 20250916: se comparte otra HV (Brayan Baron) y se programa entrevista para el día de hoy. Se presentan los dos candidatos, sin embargo, no aprueban proceso de entrevista iniguno de los dos. 20250922: se comparte 1 HV para considerar y se continua reclutamiento. 20250930: se programa entrevista para el 1 de oct solo con GH por falta de disponibilidad de JI y se comparte 1 HV más 20251001: se presenta 1 candidato, pero no aprueba proceso, se programa otra entrevista para el 2 de octubre y se comparte 1 Hv adicional. 20251002: se presenta 1 candidato y no aprueba proceso 20251006: se continua con reclutamiento. 20251014: se continua proceso reclutamiento ya que no hay candidatos que cumplan con el perfil.20251020: se comparte 1 HV, sin embargo, se hace validación previa ya que requiere excepción en el perfil académico y GH informa que debe cumplir con el perfil requerido 20251023: se comparte 1 HV y se programa entrevista para el 24 de oct. 20251024: se presenta el candidato pero no aprueba entrevista. 20251028: se continua reclutamiento 20251030: se continua reclutamiento 20251104: se comparte 1 HV. 20251107: candidata de la HV pendiente indica que no tiene aún disponibilidad para iniciar el proceso 20251111: candidata inidica que cuenta con disponibilidad para el 12 de nov 20251112: se presenta la candidata, pero no aprueba proceso de entrevista 20251118: se continua reclutamiento 20251124: continua reclutamiento. 20251127: se comparte 1 HV adicional para entrevista el 1 de dic. 20251201: el candidato programado no se conecta al espacio de entrevista. 20251209: se continua reclutamiento 20251212: se comparte 1 HV para ser tenida en cuenta. 20251229: Se compartio una hoja de vida pendiente de la retroalimentacion de GH 20260105: se comparte 1 HV para entrevista el 6 de enero. 20260106: se presenta Juan Camilo Cuartas y aprueba entrevista con GH, solicita programar evaluacion.20260109: se comparte retroalimentacion con concepto aprobado 20250114: se valida con GH e indican que están aun a la espera de confirmar la posibilidad de dar continuidad al candidato 20250115: GH solicita el envio a contratacion de Juan Camilo Cuartas. Se envia OC 20260119: candidato registra con novedad en ES, sin embargo, se gestiona excepcion con GH. 20260121: candidato se encuentra en apertura de cuenta y EM 20260122: candidato presenta novedad con apertura de cuenta y GH brinda autorizacion para el pago por cheque 20260123: contratacion confirma ingreso de Juan Camilo Cuartas con fecha de inicio 26 de ene | AL2: =IFERROR(S2/O2,"N/A") -> 0.83333333 | AM2: =IFERROR(NETWORKDAYS(D2,Q2,Hoja1!$A$1:$A$29),"N/A") -> 79 | AN2: =IFERROR(NETWORKDAYS(D2,AE2,Hoja1!$A$1:$A$29),"N/A") -> 86 | AO2: 10 | AP2: =AN2-AO2 -> 76 | AQ2: =IFERROR(NETWORKDAYS(AF2,AG2,Hoja1!$A$1:$A$29),"N/A") -> 8 | AR2: 3 | AS2: =AQ2-AR2 -> 5 | AT2: =IFERROR(NETWORKDAYS(D2,AG2,Hoja1!$A$1:$A$29),"N/A") -> 93 | AU2: =AT2-AO2-AR2 -> 80 | AV2: Computrabajo | AW2: Cooperativa Afroamericano | AX2: Desiste
A3: 14454 | B3: CLUB LOS ANDES | C3: CLUB LOS ANDES | D3: 45953 | E3: 45847 | F3: Cali | G3: SANTANDER DE QUILICHAO | H3: VACANTE DESDE RECLUTAMIENTO | I3: JEFE COMERCIAL | J3: JEFE/DIRECTOR/GERENTE | K3: Susan Bermeo Saenz | L3: 1 | M3: Finalizado - Llego hasta contratacion | N3: 0000-00-00 | O3: 6 | P3: No | Q3: 45968 | R3: 45968 | S3: 6 | T3: 0000-00-00 | U3: 0000-00-00 | V3: 0000-00-00 | W3: 0000-00-00 | X3: 0000-00-00 | Y3: 0000-00-00 | Z3: 0000-00-00 | AA3: 6 | AB3: 3 | AC3: 0 | AD3: 46010 | AE3: 46036 | AF3: 46036 | AG3: 46042 | AH3: 46044 | AI3: =MONTH(AH3) -> 1 | AJ3: Ricardo Carrillo Higuita | AK3: 20250709: GH solicita evaluacion de Anny Stephany Moreno Ruiz. 20250711: Anny ha realizado unicamente una prueba, solicita tiempo adicional para culminar las demas. 20250714: Se informa que la candidata tiene pendiente 2 pruebas. Se compromete a realizarlas ese mismo dia. Se agenda entrevistas para el 15 de julio. (3) 20250717: se informa a GH que la candidata no cumple perfil academico. 20250718: GH solicita no continuar y activar reclutamiento. 20250728: se envian 5 hv. 20250813: Se solicito retroaliementación del proceso. 20250815:El cliente informa que aún se encuentran revisando los perfiles. 20250820:Se solicito nuevamente retroalimentacion del proceso. 20250821:EL cliente informa que estan a la espera de la aprobacion del jefe para continuar con el proceso.(19) 20250827:El cliente envio a contratar a Anny candidata que ya estaba evaluada por Leidy Checa. Se envio a la candidata a contratación con excepción por formación academica. 20250902: La candidata no paso ES y se solicito mas hojas de vida. 20250903:Se solicita retroalimentación de las 5 hojas de vida enviadas el 28 de Julio. (22) 20250904: El cliente informa que ya reviso las HV, sin embargo pidio mas reclutamiento. (10) 20250910: Se enviaron 6 hojas de vida mas sin filtro tefonico. 20250919: Se solito retroalimentación de las hojas de vida enviadas. 20250926: Se volvio a solicitar retroalimentacion. El cliente informa que esta en entrevistas y el Lunes me da avances. (12) 20250930:El cliente envio a evaluar a Andres Tovar y David Barreros, se enviaron pruebas y se citaran a entrevista para 1 de Octubre. Andres Felipe Tovar no contesta. 20251003:Se cito a entrevista a Andres para el dia 6 de Octubre y se enviaron pruebas. (4) 20251008:David Barrios aun no ha terminado las pruebas Bluesite. (3)20251010:Se subio informe y se le informo al cliente. 20251016:El cliente entrevistara por ultima vez a David para tomar una decision. (4) 20251017:El cliente envio a contratar a David. 20251020: El candidato no ha enviado los documentos. (3) 20251022:Se envio a contratacion con FI Nov 4 20251023: El candidato salio con anotaciones y no se continuara proceso de contratacion. 20251027: Se le solicito al cliente retroalimentacion del proceso. (8) 20251031: GH solicita reclutamiento.20251107: Se enviaron 3 hojas de vida (Lili Nieto, Jessica Armero y Sandra Angulo) (19) 20251209:El cliente envio a evaluar a 3 personas (Leidy Pedrosa, Ricardo Carrillo, Luis Medallo). 20251210:Se enviaron 3 hojas de vida(Jose Fernando Villaquiran, Yesika Robles y Alvaro Solarte) 20251211:GH solicito pruebas para Leidy Pedrosa, Ricardo Carrillo y Luis Medolla. 20251212:Los candidatos aun no han realizado pruebas y tampoco han enviado documentos para enviarlos a estudios de seguridad. 20251215:Los candidato enviaron los documentos y fueron enviados a ES. Pendiente resultados. 20251217:El cliente envio a evlauar a los 3 candidatos. 20251219:Se envio novedad al cliente de resultados de ES. 20251222:Se reunio con el cliente para retroalimentacion de dos de los 3 canddiatos. Lady no se ha podido presentar a entrevista y se volvio a reprogramar para el 23. (6) 20251224: Se evaluo a la candidata y se le dio retroalimentación al cliente. 20251230:Se solicito retroalimentacion. 20260107: Se solicito retroaimentacion y el cliente informa que el dia de mañana tomara una decision. 20260109:El envio evaluar Jose Fernando Villaquiran. 20260114:El cliente envio a contratar a Ricardo con FI 22 Ene. | AL3: =IFERROR(S3/O3,"N/A") -> 1 | AM3: =IFERROR(NETWORKDAYS(D3,Q3,Hoja1!$A$1:$A$29),"N/A") -> 11 | AN3: =IFERROR(NETWORKDAYS(D3,AE3,Hoja1!$A$1:$A$29),"N/A") -> 54 | AO3: 30 | AP3: =AN3-AO3 -> 24 | AQ3: =IFERROR(NETWORKDAYS(AF3,AG3,Hoja1!$A$1:$A$29),"N/A") -> 5 | AR3: 0 | AS3: =AQ3-AR3 -> 5 | AT3: =IFERROR(NETWORKDAYS(D3,AG3,Hoja1!$A$1:$A$29),"N/A") -> 58 | AU3: =AT3-AO3-AR3 -> 28 | AV3: Computrabajo | AW3: GI Group (INSSA) | AX3: Estudio de seguridad | AY3: Estudio de seguridad
A4: 14619 | B4: COOMEVA | C4: EYD | D4: 45972 | E4: 45873 | F4: Cali | G4: DIRECCION NACIONAL | H4: VACANTE DESDE RECLUTAMIENTO | I4: APRENDIZ SENA | J4: ESTUDIANTE/APRENDIZ | K4: Alba Lucy Alape | L4: 1 | M4: Finalizado - Llego hasta contratacion | N4: 0000-00-00 | O4: 10 | P4: No | Q4: 45996 | R4: 46006 | S4: 10 | T4: 0000-00-00 | U4: 0000-00-00 | V4: 0000-00-00 | W4: 0000-00-00 | X4: 0000-00-00 | Y4: 0000-00-00 | Z4: 0000-00-00 | AA4: 2 | AB4: 2 | AC4: 0 | AD4: 46030 | AE4: 46030 | AF4: 46031 | AG4: 46043 | AH4: 46044 | AI4: =MONTH(AH4) -> 1 | AJ4: Valery Palechor Acosta | AK4: 20250808: El cliente solicito reclutamiento. 20250813: Se enviaron 2 hojas de vida (Jhohan y Jhon Sebastian). 20250820:Se solicito retroalimentación 20250821:El cliente informa que realizaran entrevistas el dia Martes 26 de Agosto. 20250827:El cliente informo que el candidato citado no se presento a entrevista por tal razón solicito mas hojas de vida. 20250827:Se enviaron 2 hojas de vida (Jaider y Daniela) 20250902:Se solicito retroalimentación al cliente. 20250903: El cliente informo que esta solicitando espacio para entrevista. 20250915: Pte retro por gh. 20250924: gh envia retro, los candidatos ya no estan disponibles. Se activa reclutamiento. 20251006: Se envian 2 hv. Pte retro por gh. 20251015: gh envia retro, se solicita activar reclutamiento. 20251023: Se envian 2 hv. Pte retro por gh. 20251030: gh envia retro de hv y refiere que se programa a franci para entrevista y se solicita activar reclutamiento. 20251106: Gh solicita evaluar a franci, sin embargo solicita mas reclutamiento. 20251111: se informa a gh que la candidata Franci desiste del proceso. 20251114: Se envian 3 hv. Pte retro por gh. 20251121: gh envia retro y se activa reclutamiento. 20251124: se envian 2 hv. pte retro por gh. 20251125: gh solicita evaluar a contratar a Angela Natalia Ruales . Se programan pruebas. 20251128: Se envia OC FI 10 Dic. 20251204: se notifica a gh que se cancela proceso ya que la institucion no nos envia carta de presentacion. Se activa reclutamiento. 20251205: se envian 3 hv. Pte retro por gh. 20251215: pte retro por gh. 20251226: Pte retro por gh. 20250106: Pte retro por gh. (8) 20260106:gh solicita evaluar a Valery Palechor y solicita activar mas reclutamiento. 20260108: gh solicita avanzar contratacion con Valery Palechor. 20250109: Se envia OC FI 22 Enero. | AL4: =IFERROR(S4/O4,"N/A") -> 1 | AM4: =IFERROR(NETWORKDAYS(D4,Q4,Hoja1!$A$1:$A$29),"N/A") -> 18 | AN4: =IFERROR(NETWORKDAYS(D4,AE4,Hoja1!$A$1:$A$29),"N/A") -> 39 | AO4: 12 | AP4: =AN4-AO4 -> 27 | AQ4: =IFERROR(NETWORKDAYS(AF4,AG4,Hoja1!$A$1:$A$29),"N/A") -> 8 | AR4: 3 | AS4: =AQ4-AR4 -> 5 | AT4: =IFERROR(NETWORKDAYS(D4,AG4,Hoja1!$A$1:$A$29),"N/A") -> 47 | AU4: =AT4-AO4-AR4 -> 32 | AV4: Bolsa de empleo Ins. Educativa | AW4: NA | AX4: Candidato desiste | AY4: Candidato desiste
A5: 14738 | B5: MP | C5: MP | D5: 45986 | E5: 45987 | F5: Cali | G5: CALI | H5: VACANTE DESDE RECLUTAMIENTO | I5: APRENDIZ SENA | J5: ESTUDIANTE/APRENDIZ | K5: Susan Bermeo Saenz | L5: 1 | M5: Finalizado - Llego hasta contratacion | N5: 0000-00-00 | O5: 22 | P5: No | Q5: 45987 | R5: 45987 | S5: 22 | T5: 0000-00-00 | U5: 0000-00-00 | V5: 0000-00-00 | W5: 0000-00-00 | X5: 0000-00-00 | Y5: 0000-00-00 | Z5: 0000-00-00 | AA5: 5 | AB5: 5 | AC5: 0 | AD5: 46009 | AE5: 46010 | AF5: 46010 | AG5: 46024 | AH5: 46027 | AI5: =MONTH(AH5) -> 1 | AJ5: Maria Isabel Epia Perdomo | AK5: 20251125: Se activa reclutamiento. 20251126: Se envian 2 hv pte retro por gh. 20251205: Pte retro por gh. 20251216: pte retro por gh. 20251219:El cliente envio a contratar Maria Isabel Epia con FI Ene 5 | AL5: =IFERROR(S5/O5,"N/A") -> 1 | AM5: =IFERROR(NETWORKDAYS(D5,Q5,Hoja1!$A$1:$A$29),"N/A") -> 2 | AN5: =IFERROR(NETWORKDAYS(D5,AE5,Hoja1!$A$1:$A$29),"N/A") -> 18 | AO5: 3 | AP5: =AN5-AO5 -> 15 | AQ5: =IFERROR(NETWORKDAYS(AF5,AG5,Hoja1!$A$1:$A$29),"N/A") -> 9 | AR5: 3 | AS5: =AQ5-AR5 -> 6 | AT5: =IFERROR(NETWORKDAYS(D5,AG5,Hoja1!$A$1:$A$29),"N/A") -> 26 | AU5: =AT5-AO5-AR5 -> 20 | AV5: Bolsa de empleo Ins. Educativa | AW5: N/A
A6: 14746 | B6: MP | C6: MP | D6: 45891 | E6: 45891 | F6: Cali | G6: CALI | H6: VACANTE DESDE RECLUTAMIENTO | I6: APRENDIZ SENA | J6: ESTUDIANTE/APRENDIZ | K6: Alba Lucy Alape | L6: 1 | M6: Finalizado - Llego hasta contratacion | N6: 0000-00-00 | O6: 8 | P6: No | Q6: 45894 | R6: 45919 | S6: 8 | T6: 0000-00-00 | U6: 0000-00-00 | V6: 0000-00-00 | W6: 0000-00-00 | X6: 0000-00-00 | Y6: 0000-00-00 | Z6: 0000-00-00 | AA6: 1 | AB6: 1 | AC6: 0 | AD6: 45919 | AE6: 46001 | AF6: 46001 | AG6: 46042 | AH6: 46044 | AI6: =MONTH(AH6) -> 1 | AJ6: Saida Tatiana Preciado Dominguez | AK6: 20250822: Se activa reclutamiento. 20250825: Se envian 8 hv para 5 vacantes. Pte retro por gh. 20250902: gh envia retroalimentacion. Se activa reclutamiento. 20250910: Se envian 5 hv. 20250912: Se envian 3 hv pte retro por gh. 20250915: Gh solicita evaluar a Saida Preciado. Se programan pruebas. 20250919: gh solicita avanzar contratacion de Saida Preciado. pte culminar pruebas blusite para enviar OC. 20250925: Se informa a gh por instruccion de juridico que se suspenden las contrataciones de aprendices menores de edad.(52) 20250926: gh solicita activar el proceso con Saida teniendo en cuenta que es referida de Manuel Issa. Se solicita a la candidata realizar tramite para permiso de trabajo para poder enviar a contratacion. 20251209: gh informa que se contratara a Saisa para la segunda fecha de contratacion de Enero. 20251210: Se envia proceso a estudio de seguridad. (8)20251215: gh confirma estudio de seguridad. pte de gh para avanzar proceso. 20251226: Pte retro por gh. 20250106: Pte retro por gh para avanzar contratacion de Saida. 20260114: GH envia aprobacion ministerio, se continua con contratacion para ingreso 22 ene.Se descuentan 22 dias de contratacion, saida estaba realizando proceso de solicitud de permiso de trabajo. | AL6: =IFERROR(S6/O6,"N/A") -> 1 | AM6: =IFERROR(NETWORKDAYS(D6,Q6,Hoja1!$A$1:$A$29),"N/A") -> 2 | AN6: =IFERROR(NETWORKDAYS(D6,AE6,Hoja1!$A$1:$A$29),"N/A") -> 75 | AO6: 60 | AP6: =AN6-AO6 -> 15 | AQ6: =IFERROR(NETWORKDAYS(AF6,AG6,Hoja1!$A$1:$A$29),"N/A") -> 27 | AR6: 22 | AS6: =AQ6-AR6 -> 5 | AT6: =IFERROR(NETWORKDAYS(D6,AG6,Hoja1!$A$1:$A$29),"N/A") -> 101 | AU6: =AT6-AO6-AR6 -> 19 | AV6: Bolsa de empleo Ins. Educativa | AW6: NA
A7: 14875 | B7: BANCOOMEVA | C7: BANCOOMEVA | D7: 45939 | E7: 45911 | F7: Cali | G7: DIRECCION NACIONAL | H7: VACANTE DESDE RECLUTAMIENTO | I7: APRENDIZ SENA | J7: ESTUDIANTE/APRENDIZ | K7: Carolina Cordoba Betancourt | L7: 1 | M7: Finalizado - Llego hasta contratacion | N7: 0000-00-00 | O7: 19 | P7: No | Q7: 46013 | R7: 46013 | S7: 19 | T7: 0000-00-00 | U7: 0000-00-00 | V7: 0000-00-00 | W7: 0000-00-00 | X7: 0000-00-00 | Y7: 0000-00-00 | Z7: 0000-00-00 | AA7: 5 | AB7: 1 | AC7: 0 | AD7: 46031 | AE7: 46035 | AF7: 46035 | AG7: 46043 | AH7: 46044 | AI7: =MONTH(AH7) -> 1 | AJ7: Daniela Murillo Rios | AK7: 20250911: GH solicita reclutamiento perfil contable. 20250916: Se envian 2 HV Katherine, Laura. 20250922: GH solicita evaluar y contratar a Katherine FI 14/10. 20250926: Se informa disponibilidad de informe - Enviar con pruebas completas, GH solicita enviar a contratación cuando complete pruebas. 20251003: Se envia OC FI 14/10. 20251009: Se cancela proceso de contratación de Katherine Rodriguez por novedad en SECAP / Solicita evaluar y contratar a Laura Camila Mosquera FI 22/10 - Se informa a GH que la candidata no se encuentra disponible - Se reinicia reclutamiento. 20251010: Se envian 2 HV Ricardo, Luisa. 20251016: GH informa que los candidatos no se presentan a entrevista programada 15/10 / Se solicita reclutamiento. 20251017: Se envian 2 HV Katherin, Yina. 20251027: Se solicita retroalimentación. 20251028: GH informa que solo se cito a una candidata y no pasa entrevista, se retoma reclutamiento.20251105: se enviaron 3cv a GH.20251114: se realiza seguimiento.20251114: GH informa continaur con candidato Diego Angulo. 20251118: GH informa no continuar con diego Angulo, se activa reclutamiento. 20251124: se envian 2cv a GH.20251202: GH informa dos personas enviadas no se presentaron a entrevista, solicita reclutamiento. 20251204: se envian 2cv a GH Diego, Margi 20251204: candidatos no se ajsutan, deben ser formacion contable. 20251209: se envian 3cv con formacion contable Franyer, cristian, julian 20251216: entrevista lider 15 Dic pdt retro.20251218: GH solicita continuar en evaluacion con Julian Salazar. 20251219: Julian no aprobo veritas, los otros dos estudiantes no aprobaron entrevista, GH solicita reclutamiento. 20251222: se envian 3 cv a GH.20260105: se realiza seguimiento,20260106: GH informa evaluar a Daniela Murillo.20260109: evaluada, 20260113: se envia O.C con F.I 22 Enero. | AL7: =IFERROR(S7/O7,"N/A") -> 1 | AM7: =IFERROR(NETWORKDAYS(D7,Q7,Hoja1!$A$1:$A$29),"N/A") -> 49 | AN7: =IFERROR(NETWORKDAYS(D7,AE7,Hoja1!$A$1:$A$29),"N/A") -> 62 | AO7: 30 | AP7: =AN7-AO7 -> 32 | AQ7: =IFERROR(NETWORKDAYS(AF7,AG7,Hoja1!$A$1:$A$29),"N/A") -> 7 | AR7: 2 | AS7: =AQ7-AR7 -> 5 | AT7: =IFERROR(NETWORKDAYS(D7,AG7,Hoja1!$A$1:$A$29),"N/A") -> 68 | AU7: =AT7-AO7-AR7 -> 36 | AV7: Bolsa de empleo Ins. Educativa | AW7: No aplica | AX7: Estudio de seguridad | AY7: Candidato desiste | AZ7: Prueba integridad
A8: 14883 | B8: MP | C8: MP | D8: 45986 | E8: 45979 | F8: Bogota | G8: BOGOTA | H8: VACANTE DESDE RECLUTAMIENTO | I8: EJECUTIVO/A AFILIACION | J8: CARGO COMERCIAL | K8: Andrea Katherine Angel Moreno | L8: 1 | M8: Finalizado - Llego hasta contratacion | N8: 0000-00-00 | O8: 4 | P8: No | Q8: 45994 | R8: 45994 | S8: 4 | T8: 0000-00-00 | U8: 0000-00-00 | V8: 0000-00-00 | W8: 0000-00-00 | X8: 0000-00-00 | Y8: 0000-00-00 | Z8: 0000-00-00 | AA8: 4 | AB8: 1 | AC8: 0 | AD8: 46009 | AE8: 46009 | AF8: 46009 | AG8: 46031 | AH8: 46035 | AI8: =MONTH(AH8) -> 1 | AJ8: Kevin Mauricio Bolivar Rojas | AK8: 20251020: Se programan entrevistas con JI 22Oct. 20251022: Se realizan entrevistas con JI 2 candidatos no favorables por actitud. Se programan entrevistas 31Oct: Candidatos no se presentan. Se programan entrevistas 05Nov. 20251105: Candidatas seleccionadas ORFA CASTILLO BUSTAMANTE y HELEN VERONICA VÁSQUEZ BELTRAN se solicitan documentos. 20251110: Se solicitan documentos pendientes a las candidatas.HELEN VERONICA VÁSQUEZ BELTRAN desiste del proceso. 20251111: Se solicita ES candidata ORFA CASTILLO BUSTAMANTE fecha de ingreso tentativa 24Nov. 20251112: Candidata no favorable en validación pensional. Se activa reclutamiento. 20251114: Se organizan entrevistas con JI 19Nov. 20251119: Candidata seleccionada BLANCA APONTE SOLER se solicitan documentos. 20251124: Se solicita ES candidata seleccionada fecha tentativa de ingreso 01Dic. 20251125: Candidata no favorable en ES. Se continua reclutamiento. 20251128: Se realizan entrevistas con JI candidata seleccionada INGRI VIVIANA GONZALEZ se solicitan documentos. 20251201: Se solicita ES candidata seleccionada fecha tentativa de ingreso 10Dic. 20251203: Se realizan entrevistas con JI para tener Backup candidato seleccionado Kevin Bolivar se solicitan documentos. 20251205: Candidata viviana desiste. Se continua proceso con backup Kevin a la espera de documentos. 20251209: Se le indica al candidato documentos faltantes. 20251216: Se solicita excepción de estudios a GH. 20251218: Se solicita ES candidato KEVIN BOLIVAR fecha tentativa de ingreso 05Ene. 20251231: Se congela proceso de contratación por directriz nacional. 20260105: Se recibe aval para continuar con la contratación fecha tentativa de ingreso 13Ene. | AL8: =IFERROR(S8/O8,"N/A") -> 1 | AM8: =IFERROR(NETWORKDAYS(D8,Q8,Hoja1!$A$1:$A$29),"N/A") -> 7 | AN8: =IFERROR(NETWORKDAYS(D8,AE8,Hoja1!$A$1:$A$29),"N/A") -> 17 | AO8: 2 | AP8: =AN8-AO8 -> 15 | AQ8: =IFERROR(NETWORKDAYS(AF8,AG8,Hoja1!$A$1:$A$29),"N/A") -> 15 | AR8: 10 | AS8: =AQ8-AR8 -> 5 | AT8: =IFERROR(NETWORKDAYS(D8,AG8,Hoja1!$A$1:$A$29),"N/A") -> 31 | AU8: =AT8-AO8-AR8 -> 19 | AV8: Computrabajo | AW8: Colmédica
A9: 14926 | B9: MP | C9: MP | D9: 45994 | E9: 45918 | F9: Cali | G9: DIRECCION NACIONAL | H9: VACANTE DESDE RECLUTAMIENTO | I9: ESTUDIANTE EN PRACTICA | J9: ESTUDIANTE/APRENDIZ | K9: Alba Lucy Alape | L9: 1 | M9: Finalizado - Llego hasta contratacion | N9: 0000-00-00 | O9: 9 | P9: No | Q9: 45996 | R9: 46007 | S9: 9 | T9: 0000-00-00 | U9: 0000-00-00 | V9: 0000-00-00 | W9: 0000-00-00 | X9: 0000-00-00 | Y9: 0000-00-00 | Z9: 0000-00-00 | AA9: 3 | AB9: 2 | AC9: 0 | AD9: 46013 | AE9: 46013 | AF9: 46013 | AG9: 46024 | AH9: 46027 | AI9: =MONTH(AH9) -> 1 | AJ9: Maria Paula Perez Fernandez | AK9: 20250919: Se activa reclutamiento. 20250922: Se envian 3 hv. Pte retro por gh. 20251003: gh solicita evaluar a Santiago y activar reclutamiento. 20251006: se envian 3 hv. 20251007: se notifica a gh que santiago no realiza pruebas. pte retro de las hv enviadas. 20251027: pte retro por gh. 20251105: gh envia retro y solicita activar reclutamiento. 20251111: Se envian 3 hv. Pte retro por gh. 20251113: Se envia 1 hv adicional referida por Manuel Issa. Pte retro por gh. 20251120: gh solicita evaluar a Daniela y Luisa Bastidas. Se programan pruebas. 20251127: se confirma informe. 20251128: gh aolicita avanzar contratacion con Daniela. 20251201: Se envia OC FI 10 DIC. 20251203: se cancela proceso con Daniela, por que la candidata no le brindaran carta de presentacion. Se activa reclutamiento. 20251205: se envian 3 hv pte retro por gh. 20251215: Pte retro por gh. 20251216: gh solicita evaluar a Maria Paula Perez. Se programan pruebas. 20251222: Se confirma informe y se envia OC FI 05 ENE. | AL9: =IFERROR(S9/O9,"N/A") -> 1 | AM9: =IFERROR(NETWORKDAYS(D9,Q9,Hoja1!$A$1:$A$29),"N/A") -> 3 | AN9: =IFERROR(NETWORKDAYS(D9,AE9,Hoja1!$A$1:$A$29),"N/A") -> 13 | AO9: 0 | AP9: =AN9-AO9 -> 13 | AQ9: =IFERROR(NETWORKDAYS(AF9,AG9,Hoja1!$A$1:$A$29),"N/A") -> 8 | AR9: 3 | AS9: =AQ9-AR9 -> 5 | AT9: =IFERROR(NETWORKDAYS(D9,AG9,Hoja1!$A$1:$A$29),"N/A") -> 20 | AU9: =AT9-AO9-AR9 -> 17 | AV9: Bolsa de empleo Ins. Educativa | AW9: NA | AX9: Candidato desiste | AY9: Candidato desiste
A10: 14967 | B10: COOMEVA | C10: GCGIA | D10: 45958 | E10: 45979 | F10: Caribe | G10: BARRANQUILLA | H10: EMPRESA ENVIA EL CANDIDATO | I10: GESTOR/A COOPERATIVO ESPECIALIZADO | J10: CARGO COMERCIAL | K10: Sheylin Florez Saenz | L10: 1 | M10: Finalizado - Llego hasta contratacion | N10: 0000-00-00 | O10: 1 | Q10: 0000-00-00 | R10: 0000-00-00 | S10: 1 | T10: 0000-00-00 | U10: 0000-00-00 | V10: 0000-00-00 | W10: 0000-00-00 | X10: 0000-00-00 | Y10: 0000-00-00 | Z10: 0000-00-00 | AA10: 3 | AB10: 3 | AC10: 0 | AD10: 45986 | AE10: 46003 | AF10: 46006 | AG10: 46024 | AH10: 46027 | AI10: =MONTH(AH10) -> 1 | AJ10: Vanessa Donado Aguas | AK10: 20251029: REQ preventiva. JI y GH revisan candidatos entrevistados en vacante de EC para esta oferta. 20251107: Piden evaluar candidata Melanie Cerpa Cabrera en RQ preventiva. 20251111: GH comparte candidatas de Banco a tener en cuenta en el proceso: Sandra Arteta, Ibis ortega y Vanessa Donado. 20251114: GH Solicita agendar entrevistas con las 3 candidatas de Banco y Melanie Cerpa (Externa) para el 18/Nov. 20251119: JI Solicita avanzar a pruebas con Sandra, Ibis y Vanessa. Melanie no pudo asistir y sera reprogramada. 20251125: Se comparte Informes a JI de cand Sandra Arteta, Ibis Ortega y Vanessa Donado (Melanie no continua por cirugia). 20251128: GH solicita avanzar EDS con Sandra Arteta Arteta. 20251202: Se comparte a contratacion para incio de EDS. 20251204: Se confirma EDS favorable. A espera de indicacion para inicio de contratacion. 20251212: GH confirma que candidata Sandra Artera desiste del proceso y da aval para enviar a EDS a Vanessa Donado Aguas. 20251215: Se comparte a EDS candidata Vanessa Donado Aguas con FI 5/Ene. 20260102: Contratacion confirma ingreso de Vanessa Donado Aguas con FI 05/01/2026. | AL10: =IFERROR(S10/O10,"N/A") -> 1 | AM10: =IFERROR(NETWORKDAYS(D10,Q10,Hoja1!$A$1:$A$29),"N/A") -> N/A | AN10: =IFERROR(NETWORKDAYS(D10,AE10,Hoja1!$A$1:$A$29),"N/A") -> 31 | AO10: 0 | AP10: =AN10-AO10 -> 31 | AQ10: =IFERROR(NETWORKDAYS(AF10,AG10,Hoja1!$A$1:$A$29),"N/A") -> 13 | AR10: 8 | AS10: =AQ10-AR10 -> 5 | AT10: =IFERROR(NETWORKDAYS(D10,AG10,Hoja1!$A$1:$A$29),"N/A") -> 44 | AU10: =AT10-AO10-AR10 -> 36 | AV10: Referido cliente | AW10: Bancoomeva | AX10: Candidato desiste
A11: 14987 | B11: MP | C11: MP | D11: 45957 | E11: 45931 | F11: Medellin | G11: MEDELLIN | H11: VACANTE DESDE RECLUTAMIENTO | I11: AUXILIAR ENFERMERIA | J11: SALUD/ASISTENCIAL | K11: Francy Giraldo Santos | L11: 1 | M11: Finalizado - Llego hasta contratacion | N11: 0000-00-00 | O11: 14 | P11: No | Q11: 45959 | R11: 45959 | S11: 14 | T11: 0000-00-00 | U11: 0000-00-00 | V11: 0000-00-00 | W11: 0000-00-00 | X11: 0000-00-00 | Y11: 0000-00-00 | Z11: 0000-00-00 | AA11: 4 | AB11: 4 | AC11: 0 | AD11: 45995 | AE11: 46003 | AF11: 46003 | AG11: 46013 | AH11: 46027 | AI11: =MONTH(AH11) -> 1 | AJ11: Luisa Fernanda Vasquez Care | AK11: 20251002: Se activa reclutamiento. 20251002: Se le compartieron 7 hojas de vida para la validacion del cliente. 20251006: Pendiente de retroalimentacion del cliente. 20251014: Las personas enviadas ya no estan disponibles el dia de hoy se comparten 5 hojas de vida para la validacion del cliente. 200251017: El cliente solicita avanzar proceso con Laura Gomez y con Mateo Baena. 20251020: Se esta en proceso evaluativo con los 2 candidatos mencionados. 20251022: Se evalua a Laura Gomez. para esta RQ. 20251024: Se envia a contratacion a la candidata si todo sale ok su ingreso seria el 4 de noviembre 20251027: La candidata Laura se retira del proceso por que le progamaron una cirugia. SE REACTIVA PROCESO. 20251029: Se comparten 7 hojas de vida. 20251106: Pendiente retroalimentacion del cliente. 20251110: Pendiente por retroalimentación por parte de cliente . 20251118: La rq se detiene ya que la jefe de el CM esta en capacitacion en cali . 20251128: La rq se encuentra suspendida por directriz del cliente. 20251202: Se le comparte al cliente un correo para que nos retroalimente de la rq 20251203: El cliente solicita avanzar con 2 candidatas para fase evaluativa . 20251209: El cliente da el aval para avanzar a fase final con Luisa Fernanda Vasquez para ingreso el 5 de enero . 20251215: La candidata se encuentra en EM ya que solo hasta hoy tenia disponibildiad. | AL11: =IFERROR(S11/O11,"N/A") -> 1 | AM11: =IFERROR(NETWORKDAYS(D11,Q11,Hoja1!$A$1:$A$29),"N/A") -> 3 | AN11: =IFERROR(NETWORKDAYS(D11,AE11,Hoja1!$A$1:$A$29),"N/A") -> 32 | AO11: 19 | AP11: =AN11-AO11 -> 13 | AQ11: =IFERROR(NETWORKDAYS(AF11,AG11,Hoja1!$A$1:$A$29),"N/A") -> 7 | AR11: 2 | AS11: =AQ11-AR11 -> 5 | AT11: =IFERROR(NETWORKDAYS(D11,AG11,Hoja1!$A$1:$A$29),"N/A") -> 38 | AU11: =AT11-AO11-AR11 -> 17 | AV11: Computrabajo | AW11: METROSALUD | AX11: Candidato desiste | AY11: Candidato desiste
A12: 15009 | B12: BANCOOMEVA | C12: BANCOOMEVA | D12: 45966 | E12: 45933 | F12: Bogota | G12: BOGOTA | H12: VACANTE DESDE RECLUTAMIENTO | I12: APRENDIZ SENA | J12: ESTUDIANTE/APRENDIZ | K12: Andrea Katherine Angel Moreno | L12: 1 | M12: Finalizado - Llego hasta contratacion | N12: 0000-00-00 | O12: 5 | P12: No | Q12: 45997 | R12: 45997 | S12: 5 | T12: 0000-00-00 | U12: 0000-00-00 | V12: 0000-00-00 | W12: 0000-00-00 | X12: 0000-00-00 | Y12: 0000-00-00 | Z12: 0000-00-00 | AA12: 5 | AB12: 1 | AC12: 0 | AD12: 46027 | AE12: 46027 | AF12: 46027 | AG12: 46045 | AH12: 46048 | AI12: =MONTH(AH12) -> 1 | AJ12: Eillen Tatiana Garzon Guzman | AK12: 20251006: Se activa reclutamiento. 20251009: Se organiza entrevista candidato Daniel Felipe Pancha 15oct. 20251015: Candidato preseleccionado, sin embargo tiene contrato activo con el sena que esta intentando descargar por error en la plataforma. Se continua reclutamiento. 20251021: Se realizan entrevistas con JI candidata seleccionada Maria Jose Cardenas. Se solicitan documentos. 20251024: Candidata con contrato activo en el SENA solicita cadena de formación para dar continuidad. Se continua reclutamiento. 20251028: Se realizan entrevistas con JI candidato seleccionado ESTEBAN URDANETA se solicitan documentos. 20251031: Se solicitan documentos pendientes. 20251105: Candidato desiste del proceso. Se activa reclutamiento. 20251107: Se continua reclutamiento. 20251110: Se continua reclutamiento. 20251118: Se continua reclutamiento. 20251125: Se continua reclutamiento. 20251202: Se continua en reclutamiento. 20251205: Se realiza entrevista a Jhon Marroquin y Eillen Tatiana Garzón Guzmán desde la USC se valida agenda con GH para entrevista. 20251209: Gh indica agendar entrevista en hora de la tarde 09Dic. 20251210: Se solicitan documentos a la candidata Eillen Tatiana Garzón Guzmán, candidato Jhon Marronquin desiste. 20251212: Se le indica a la candidata documentos pendientes. 20251216: Se le solicita a la candidata documentos pendientes. 20251218: Se le informa a la candidata agilizar carta de fechas. 20251222: A la espera de registro en caprendizaje para carta de fechas. 20251226: Candidata solicita a la institución cambio de documento de TI a CC. A la espera del cambio por parte de la institución. 20251231: A la espera de cambio de documento en la plataforma del sena. 20260105: Se solicita ES candidata seleccionada Eillen Tatiana Garzón Guzmán fecha tentativa de ingreso 13Ene. 20260113: Candidata no puede ingresar, pendiente de actutlización en la plataforma sena para generar la carta de fechas. 20260115: Se le solicita a la candidata agilizar el tema para posible ingreso 22Ene. 20260122: La institución genera carta de fechas. Se solicita a contratación activar ingreso 23Ene. *+Se descuentan 12 dias al proceso de selección por demoras en la carta de fechas y actualización en el sena, se descuentan 8 días al proceso de contratación por demora en la carta de fechas** | AL12: =IFERROR(S12/O12,"N/A") -> 1 | AM12: =IFERROR(NETWORKDAYS(D12,Q12,Hoja1!$A$1:$A$29),"N/A") -> 22 | AN12: =IFERROR(NETWORKDAYS(D12,AE12,Hoja1!$A$1:$A$29),"N/A") -> 40 | AO12: 11 | AP12: =AN12-AO12 -> 29 | AQ12: =IFERROR(NETWORKDAYS(AF12,AG12,Hoja1!$A$1:$A$29),"N/A") -> 14 | AR12: 9 | AS12: =AQ12-AR12 -> 5 | AT12: =IFERROR(NETWORKDAYS(D12,AG12,Hoja1!$A$1:$A$29),"N/A") -> 53 | AU12: =AT12-AO12-AR12 -> 33 | AV12: Computrabajo | AW12: Sin experiencia | AX12: Candidato desiste
A13: 15014 | B13: COOMEVA | C13: GCGIA | D13: 45936 | E13: 45936 | F13: Bogota | G13: BOGOTA | H13: VACANTE DESDE RECLUTAMIENTO | I13: ESTUDIANTE EN PRACTICA | J13: ESTUDIANTE/APRENDIZ | K13: Paola Andrea Molano Malaver | L13: 1 | M13: Finalizado - Llego hasta contratacion | N13: 0000-00-00 | O13: 3 | P13: Si | Q13: 45989 | R13: 45989 | S13: 3 | T13: 0000-00-00 | U13: 0000-00-00 | V13: 0000-00-00 | W13: 0000-00-00 | X13: 0000-00-00 | Y13: 0000-00-00 | Z13: 0000-00-00 | AA13: 4 | AB13: 1 | AC13: 0 | AD13: 45985 | AE13: 45985 | AF13: 46013 | AG13: 46024 | AH13: 46027 | AI13: =MONTH(AH13) -> 1 | AJ13: Juana Sofia Sanchez Dueñas | AK13: 20251007: se inicia reclutamiento 20251015: Se agenda entrevista con JI, candidatos no se presentan 20251016: se continúa con reclutamiento 20251022: se agenda entrevista con JI 20251105: En reclutamiento 20251113: En reclutamiento 20251119: Entrevista con JI con 4 practicantes 20251120: Se solicita documentos 20251124: Se envia a juanita Gomez a ES, Mientras la universidad nos envia la carta de aval 20251202: continuamos a la espera de la carta de aval, practicante indica que la semana del 20 la universidad le entrega la carta apenas se matriculé.Ingreso 5 de enero | AL13: =IFERROR(S13/O13,"N/A") -> 1 | AM13: =IFERROR(NETWORKDAYS(D13,Q13,Hoja1!$A$1:$A$29),"N/A") -> 37 | AN13: =IFERROR(NETWORKDAYS(D13,AE13,Hoja1!$A$1:$A$29),"N/A") -> 33 | AO13: 0 | AP13: =AN13-AO13 -> 33 | AQ13: =IFERROR(NETWORKDAYS(AF13,AG13,Hoja1!$A$1:$A$29),"N/A") -> 8 | AR13: 2 | AS13: =AQ13-AR13 -> 6 | AT13: =IFERROR(NETWORKDAYS(D13,AG13,Hoja1!$A$1:$A$29),"N/A") -> 59 | AU13: =AT13-AO13-AR13 -> 57 | AV13: Computrabajo | AW13: Sin experiencia
A14: 15053 | B14: COOMEVA | C14: BANCOOMEVA USC | D14: 45966 | E14: 45944 | F14: Cali | G14: DIRECCION NACIONAL | H14: CONCURSO MIXTO | I14: AUXILIAR DIGITALIZACIÓN | J14: AUXILIAR/OPERATIVO | K14: Susan Bermeo Saenz | L14: 1 | M14: Finalizado - Llego hasta contratacion | N14: 0000-00-00 | O14: 3 | P14: No | Q14: 45968 | R14: 45980 | S14: 3 | T14: 0000-00-00 | U14: 45968 | V14: 45979 | W14: 0000-00-00 | X14: 0000-00-00 | Y14: 0000-00-00 | Z14: 0000-00-00 | AA14: 1 | AB14: 1 | AC14: 0 | AD14: 45994 | AE14: 46008 | AF14: 46009 | AG14: 46027 | AH14: 46027 | AI14: =MONTH(AH14) -> 1 | AJ14: Adriana Morales Urbano | AK14: 20251105: El cliente solicito concurso mixto. 20251107: Se envio publicacion interna. del 13 a 18 de Nov. 20251111: Se enviaron 3 hojas de vida externas (Maria Muñoz, Carolina Gutierrez, Karol Villa) 20251118: Se solicito retroalimentacion. 20251119: El cliente cito a entrevista para el Lunes 24 de Nov. 20251126:Se solicito retroalimentacion. 20251127:El cliente solicito evaluar a Adriana Morales quien se encuentra realizando su practica en la compañia. Se enviaron pruebas y se cito a entrevista para el Martes 2 de Diciembre.20251203:Se subio informe y se le informo al cliente. 20251209:Se solicito retroalimentacion. 20251212:aun no informan como se va a proceder con el proceso. 20251215: Se solicito informacion de como proceder con el proceso. (8) 20251217: El cliente solicito contratar a Adriana 20251218:Se envio a contratar con FI Enero 5. | AL14: =IFERROR(S14/O14,"N/A") -> 1 | AM14: =IFERROR(NETWORKDAYS(D14,Q14,Hoja1!$A$1:$A$29),"N/A") -> 3 | AN14: =IFERROR(NETWORKDAYS(D14,AE14,Hoja1!$A$1:$A$29),"N/A") -> 29 | AO14: 6 | AP14: =AN14-AO14 -> 23 | AQ14: =IFERROR(NETWORKDAYS(AF14,AG14,Hoja1!$A$1:$A$29),"N/A") -> 11 | AR14: 5 | AS14: =AQ14-AR14 -> 6 | AT14: =IFERROR(NETWORKDAYS(D14,AG14,Hoja1!$A$1:$A$29),"N/A") -> 40 | AU14: =AT14-AO14-AR14 -> 29 | AV14: Referido cliente | AW14: Menzies Aviación Colombia
A15: 15059 | B15: COOMEVA | C15: USC | D15: 45946 | E15: 45946 | F15: Cali | G15: DIRECCION NACIONAL | H15: VACANTE DESDE RECLUTAMIENTO | I15: APRENDIZ SENA | J15: ESTUDIANTE/APRENDIZ | K15: Susan Bermeo Saenz | L15: 1 | M15: Finalizado - Llego hasta contratacion | N15: 0000-00-00 | O15: 5 | P15: No | Q15: 46017 | R15: 45971 | S15: 5 | T15: 0000-00-00 | U15: 0000-00-00 | V15: 0000-00-00 | W15: 0000-00-00 | X15: 0000-00-00 | Y15: 0000-00-00 | Z15: 0000-00-00 | AA15: 1 | AB15: 1 | AC15: 0 | AD15: 46027 | AE15: 46036 | AF15: 46036 | AG15: 46042 | AH15: 46044 | AI15: =MONTH(AH15) -> 1 | AJ15: Edwin Fernando Nieves Quiñonez | AK15: 20251016: El cliente solicito reclutamiento de aprendices de SST. 20251020:Se enviaron 3 hojas de vida (Meily Tumbo, Juan Carlos Luna, Isabella Gutierrez) 20251024:Se solicito retroalimentacion. 20251028: El cliente no ha dado retroalimentacion. 20251030:Se volvio a solicitar retroalimentacion. 20251104: Se solicto nuevamente retroalimentacion. 20251107:El cliente aun no da retroalimentacion, se volvio a preguntar. 20251110: GH entrevistara esta semana. 20251113:Se solicito retroalimentacion. 20251114: GH informa que esta a la espera de fecha y hora de entrevistas por parte del lider. 20251118: Se volvio a solicitar retroalimentacion. 20251119: GH informa que esta a la espera de fecha y hora de entrevistas por parte del lider. 20251121:Se volvio a solicitar retroalimentacion. 20251124: Se envio correo informando que se va a detener el proceso. 20251128: GH Informa que los candidatos ya no se estan disponibles. Se envio correo solicitando que se debe de gestionar las entrevistas mas rapido ya que los aprendices se ajustan rapido. 20251201:Se activa reclutamiento. 20251202:Se enviaron 2 hojas de vida (Maria Jose Hurtado, Giseth Rodriguez) 20251205:Se solicito retroalimentacion. 20251210:Se solicito retroalimentacion. 20251212:aun no dan retroalimentacion. 20251224:Se solicito retroalimentacion. El cliente informa que las canddiatas ya esta realizando practicas. 20251226:Se activa reclutamiento. 20251226:El cliente solicito evaluar a Edwin nieves, candidato que se habia enviado para la RQ 15283. Ya no sera perfil SST y se contratara con esta RQ. 20250105:Se subio informe y se le informo al cliente. 20260113:Se solicito nuevamente retroalimentacion de la evaluacion realizada a edwin. 20260114:El cliente envio a contratar a Edwin. Se envio a contratacion con FI 22 Ene. | AL15: =IFERROR(S15/O15,"N/A") -> 1 | AM15: =IFERROR(NETWORKDAYS(D15,Q15,Hoja1!$A$1:$A$29),"N/A") -> 48 | AN15: =IFERROR(NETWORKDAYS(D15,AE15,Hoja1!$A$1:$A$29),"N/A") -> 59 | AO15: =23+13 -> 36 | AP15: =AN15-AO15 -> 23 | AQ15: =IFERROR(NETWORKDAYS(AF15,AG15,Hoja1!$A$1:$A$29),"N/A") -> 5 | AR15: 0 | AS15: =AQ15-AR15 -> 5 | AT15: =IFERROR(NETWORKDAYS(D15,AG15,Hoja1!$A$1:$A$29),"N/A") -> 63 | AU15: =AT15-AO15-AR15 -> 27 | AV15: Bolsa de empleo Ins. Educativa | AW15: N/A
A16: 15068 | B16: COOMEVA | C16: GCGIA | D16: 45945 | E16: 45945 | F16: Caribe | G16: RIOHACHA | H16: VACANTE DESDE RECLUTAMIENTO | I16: APRENDIZ SENA | J16: ESTUDIANTE/APRENDIZ | K16: Sheylin Florez Saenz | L16: 1 | M16: Finalizado - Llego hasta contratacion | N16: 0000-00-00 | O16: 6 | P16: No | Q16: 45993 | R16: 45993 | S16: 6 | T16: 0000-00-00 | U16: 0000-00-00 | V16: 0000-00-00 | W16: 0000-00-00 | X16: 0000-00-00 | Y16: 0000-00-00 | Z16: 0000-00-00 | AA16: 1 | AB16: 1 | AC16: 0 | AD16: 46013 | AE16: 46013 | AF16: 46013 | AG16: 46038 | AH16: 46044 | AI16: =MONTH(AH16) -> 1 | AJ16: Zharick Dalais Amaya Orellano | AK16: 20251015: Crean RQ - Posiciòn ocupada hasta el 01/Nov. 20251020: Las instituciones informan que aùn no cuentan con estudiantes inscritos en productiva. 20251114: En reunion de seguimiento se solicita revisar aprendices en Riohacha con posibilidad de pasar la posicion para esa ciudad. 20251124: Sena comparte 4 aprendices. Entrevistas programadas 25/nov para posicion de Riohacha en proceso de gestion. 20251125: Candidatos no avanzan y se comparte 1 candidato : Natanael Ipuana. 20251202: Se comparten candidatos: Zharick Amaya y Ana Fuentes quienes seran entrevistados el 4/Dic.20251209: JI salio a vacaciones sin dar retroalimentacion de las entrevistas programadas. 20251215: JI confirma que no avanzan los dos aprendices. Se retoma reclutamiento. 20251222: GH confirma avanzar en evaluacion con Zharick Dalais Amaya Orellano. Pend cambio de ciudad de Sincelejo a Riohacha. 20260108: Se comparte Zharick Dalais Amaya a contratacion para inicio de EDS con FI 22/Ene. 20260115: Candidata Zharick Dalais Amaya se encuentra en aprobacion de oferta. 20260116: confirman contratacion de Zharik Dalais Amaya con FI 22/01/2026 | AL16: =IFERROR(S16/O16,"N/A") -> 1 | AM16: =IFERROR(NETWORKDAYS(D16,Q16,Hoja1!$A$1:$A$29),"N/A") -> 33 | AN16: =IFERROR(NETWORKDAYS(D16,AE16,Hoja1!$A$1:$A$29),"N/A") -> 46 | AO16: 8 | AP16: =AN16-AO16 -> 38 | AQ16: =IFERROR(NETWORKDAYS(AF16,AG16,Hoja1!$A$1:$A$29),"N/A") -> 17 | AR16: 12 | AS16: =AQ16-AR16 -> 5 | AT16: =IFERROR(NETWORKDAYS(D16,AG16,Hoja1!$A$1:$A$29),"N/A") -> 62 | AU16: =AT16-AO16-AR16 -> 42 | AV16: Busqueda directa | AW16: N/A
A17: 15074 | B17: MP | C17: MP | D17: 45946 | E17: 45946 | F17: Caribe | G17: SANTA MARTA | H17: VACANTE DESDE RECLUTAMIENTO | I17: EJECUTIVO/A AFILIACION | J17: CARGO COMERCIAL | K17: Norma Elena Achkar Mansour | L17: 1 | M17: Finalizado - Llego hasta contratacion | N17: 0000-00-00 | O17: 12 | P17: No | Q17: 46007 | R17: 46007 | S17: 12 | T17: 0000-00-00 | U17: 0000-00-00 | V17: 0000-00-00 | W17: 0000-00-00 | X17: 0000-00-00 | Y17: 0000-00-00 | Z17: 0000-00-00 | AA17: 2 | AB17: 1 | AC17: 0 | AD17: 46027 | AE17: 46027 | AF17: 46027 | AG17: 46031 | AH17: 46035 | AI17: =MONTH(AH17) -> 1 | AJ17: Katty Johanna Castillo Acosta | AK17: 20251016: Crean RQ. 20251021: Se comparten: Vianys - Karen. 20251028: Se solicita informaciòn de avance. 20251029: Solicitan evaluar a Vianys. 20251107: Candidata desiste. 20251118: Se programa con Lìder entrega de candidatos para el 18/Nov. 20251120: Se comparten 4 candidatos para cubrir 2 vacantes: Indira - Marisella - Julieth - Sayuris. 20251202: Piden evaluar a Indira en la RQ 14942 y piden ver mas candidatos para esta RQ. 20251204: Se comparten: Eduardo - Luis - Ana. 20251209: Candidato Luis en entrevista con Lìder. 20251216: se comparte terna Sebastian Muñoz, Katty Castillo y Liliana Imitola. 20251218: GH solicita avanzar proceso evaluativo con Katty Johana Castillo Acosta. 20251224: Candidata Katty Castillo tiene pendiente una prueba. 20260105: Se comparte registro evaluativo y se avanza con EDS. 20260106: Congelan contrataciones - GH tramita aval para ingreso al 13//Ene. 20260107: Candidata en EMO. 20260109: Se confirma contratación de la colaboradora Katty Johanna Castillo Acosta, con FI. 13/01/2026. | AL17: =IFERROR(S17/O17,"N/A") -> 1 | AM17: =IFERROR(NETWORKDAYS(D17,Q17,Hoja1!$A$1:$A$29),"N/A") -> 41 | AN17: =IFERROR(NETWORKDAYS(D17,AE17,Hoja1!$A$1:$A$29),"N/A") -> 53 | AO17: 11 | AP17: =AN17-AO17 -> 42 | AQ17: =IFERROR(NETWORKDAYS(AF17,AG17,Hoja1!$A$1:$A$29),"N/A") -> 5 | AR17: 0 | AS17: =AQ17-AR17 -> 5 | AT17: =IFERROR(NETWORKDAYS(D17,AG17,Hoja1!$A$1:$A$29),"N/A") -> 57 | AU17: =AT17-AO17-AR17 -> 46 | AV17: Magneto | AW17: CLARO MOVIL
A18: 15077 | B18: COOMEVA | C18: USC | D18: 45946 | E18: 45946 | F18: Cali | G18: DIRECCION NACIONAL | H18: VACANTE DESDE RECLUTAMIENTO | I18: APRENDIZ SENA | J18: ESTUDIANTE/APRENDIZ | K18: Susan Bermeo Saenz | L18: 1 | M18: Finalizado - Llego hasta contratacion | N18: 0000-00-00 | O18: 6 | P18: No | Q18: 45966 | R18: 45971 | S18: 6 | T18: 0000-00-00 | U18: 0000-00-00 | V18: 0000-00-00 | W18: 0000-00-00 | X18: 0000-00-00 | Y18: 0000-00-00 | Z18: 0000-00-00 | AA18: 2 | AB18: 1 | AC18: 0 | AD18: 46031 | AE18: 46035 | AF18: 46035 | AG18: 46044 | AH18: 46045 | AI18: =MONTH(AH18) -> 1 | AJ18: Paula Andrea Cadena Quintero | AK18: 20251016:El cliente solicito estudiantes de Call Center del insitituto PIO. 20251020:El instituto respondio que no cuentan actualmente con estudiantes en etapa practica. Se le informo al cliente y se le envio informacion de otras insitutciones que cuentan con el programa pero actualmente no tienen estudiantes disponbibles. 20251024: Se le envio al cliente correo con el estudio realizado acerca de las instituciones que ofrecen programas de Call Center y que actualmente no cuentan con estudiantes disponibles.(12) 20251030: El cliente solicito aprendices en etapa lectiva. 20251030: El cliente solicito aprendices en etapa lectiva. 20251105: Se enviaron 3 hojas de vida (Angela del Carmen Sanchez, Erika Murillo, Yuly Ordoñez) 20251110:El cliente entrevistara esta semana. 20251113:Se solicito retroalimentacion. 20251118: se solicito retroalimentacion. 20251120: Se volvio a solicitar retroalimentacion 20251124:Se envio correo solicitando retroalimentacion. (14) 20251127:El cliente envio a evaluar a Angela del Carmen. Se enviaron pruebas y se cito a entrevista para el Martes 2 de Diciembre. 20251201:Se envio una hoja de vida (Deysi Garcia) 20251202:La candidata no paso prueba veritas. 20251205:Se solicito retroalimentacion. 20251210:Se solicito retroalimentacion. 20251215:se solicito nuevamente retroalimentacion de la hv enviada el 1 de diciembre, (10) 20251217:El cliente solicito mas hojas de vida ya que la candidata no paso entrevista. 20251224: se activo Reclutamiento. 20260102:Se enviaron 3 hv Paula Andrea Cadena, Johan Manquillo, Paula Gutierrez. 20260106:El cliente envio a evaluar a Paula Cadena. Se enviaron pruebas y se cito a entrevista para el Jueves 8 Enero. 20260109:Se subio informe y se le informo al cliente. 20260113:El cliente envio a contratar a Paula Cadena. Se envio a contratacion con FI 22 ENE. | AL18: =IFERROR(S18/O18,"N/A") -> 1 | AM18: =IFERROR(NETWORKDAYS(D18,Q18,Hoja1!$A$1:$A$29),"N/A") -> 14 | AN18: =IFERROR(NETWORKDAYS(D18,AE18,Hoja1!$A$1:$A$29),"N/A") -> 58 | AO18: 36 | AP18: =AN18-AO18 -> 22 | AQ18: =IFERROR(NETWORKDAYS(AF18,AG18,Hoja1!$A$1:$A$29),"N/A") -> 8 | AR18: 3 | AS18: =AQ18-AR18 -> 5 | AT18: =IFERROR(NETWORKDAYS(D18,AG18,Hoja1!$A$1:$A$29),"N/A") -> 65 | AU18: =AT18-AO18-AR18 -> 26 | AV18: Bolsa de empleo Ins. Educativa | AW18: N/A
A19: 15095 | B19: MP | C19: MP | D19: 45951 | E19: 45951 | F19: Caribe | G19: CARTAGENA | H19: VACANTE DESDE RECLUTAMIENTO | I19: APRENDIZ SENA | J19: ESTUDIANTE/APRENDIZ | K19: Sheylin Florez Saenz | L19: 1 | M19: Finalizado - Llego hasta contratacion | N19: 0000-00-00 | O19: 7 | P19: No | Q19: 46000 | R19: 46000 | S19: 7 | T19: 0000-00-00 | U19: 0000-00-00 | V19: 0000-00-00 | W19: 0000-00-00 | X19: 0000-00-00 | Y19: 0000-00-00 | Z19: 0000-00-00 | AA19: 1 | AB19: 1 | AC19: 0 | AD19: 46009 | AE19: 46009 | AF19: 46009 | AG19: 46022 | AH19: 46027 | AI19: =MONTH(AH19) -> 1 | AJ19: Cristina Isabel Hadechini Perez | AK19: 20251021: Crean RQ. 20251023: Se comparten: Silvana - Divisai. 20251028: Se solicita informaciòn de avance. 20251111: GH pide al lìder agendar espacio para entrevista. 20251112: Se suma dupla: Lineth - Yorleidys - GH informa que las entrevistas son el 19/Nov. 20251119: Piden nuevos candidatos. 20251121: Se comparten: Yengil - Roximar. 20251125: Se solicitan informaciòn de avance. 20251201: Se solicita informaciòn de avance. 20251202: Informan que el Lìder entrevistarà despues del cierre de mes. 20251204: Descartan candidatos. 20251209: Se comparten: Nikolas - Cristina -Jesus. 20251212: Se envia a proceso evaluativo a Cristina. 20251218: Se avanza con EDS 20251231: Se confirma contratación de la estudiante Cristina Isabel Hadechini Perez, con FI. 05/01/2026. | AL19: =IFERROR(S19/O19,"N/A") -> 1 | AM19: =IFERROR(NETWORKDAYS(D19,Q19,Hoja1!$A$1:$A$29),"N/A") -> 33 | AN19: =IFERROR(NETWORKDAYS(D19,AE19,Hoja1!$A$1:$A$29),"N/A") -> 40 | AO19: 20 | AP19: =AN19-AO19 -> 20 | AQ19: =IFERROR(NETWORKDAYS(AF19,AG19,Hoja1!$A$1:$A$29),"N/A") -> 9 | AR19: 4 | AS19: =AQ19-AR19 -> 5 | AT19: =IFERROR(NETWORKDAYS(D19,AG19,Hoja1!$A$1:$A$29),"N/A") -> 48 | AU19: =AT19-AO19-AR19 -> 24 | AV19: Busqueda directa | AW19: N/A
A20: 15106 | B20: MP | C20: MP | D20: 45973 | E20: 45953 | F20: Caribe | G20: BARRANQUILLA | H20: VACANTE DESDE RECLUTAMIENTO | I20: EJECUTIVO/A AFILIACION | J20: CARGO COMERCIAL | K20: Norma Elena Achkar Mansour | L20: 1 | M20: Finalizado - Llego hasta contratacion | N20: 0000-00-00 | O20: 3 | P20: Si | Q20: 45986 | R20: 45986 | S20: 3 | T20: 0000-00-00 | U20: 0000-00-00 | V20: 0000-00-00 | W20: 0000-00-00 | X20: 0000-00-00 | Y20: 0000-00-00 | Z20: 0000-00-00 | AA20: 2 | AB20: 2 | AC20: 0 | AD20: 46003 | AE20: 46003 | AF20: 46003 | AG20: 46010 | AH20: 46027 | AI20: =MONTH(AH20) -> 1 | AJ20: Mayra Isabel Torres Bayona | AK20: 20251023: Crean RQ - Solicitan evaluar a Ellen Gonzalez quien habìa estado en proceso el 2023. 20251028: Candidata Pte por Veritas. 20251030: Se solicita aval para validar Bachiller toda vez que la candidata no cuenta con otros estudios. 20251106: Comparten exepciòn por formaciòn. 20251107: Se comparte reporte evaluativo y se avanzar con ES. 20251110: Se comparte novedad en bases - Piden ampliaciòn. 20251118: Se confima el no avance del proceso - Se comparten: Natalia - Alfredo - Freddy. 20251124: Solicitan nuevos candidatos. 20251125: Se comparten: Erick - Laura - Mayra. 20251201: Se solicita informaciòn de avance. 20251202: Informan que el lìder entrevistara despues del cierre de mes. 20251205: Solicitan evaluar a Mayra Torres. 20251212: Se comparte registro evaluativo y se avanza con EDS. 20251219: Se confirma contratación de la candidata Mayra Isabel Torres Bayona, con FI. 05/01/2026 | AL20: =IFERROR(S20/O20,"N/A") -> 1 | AM20: =IFERROR(NETWORKDAYS(D20,Q20,Hoja1!$A$1:$A$29),"N/A") -> 9 | AN20: =IFERROR(NETWORKDAYS(D20,AE20,Hoja1!$A$1:$A$29),"N/A") -> 21 | AO20: 4 | AP20: =AN20-AO20 -> 17 | AQ20: =IFERROR(NETWORKDAYS(AF20,AG20,Hoja1!$A$1:$A$29),"N/A") -> 6 | AR20: 2 | AS20: =AQ20-AR20 -> 4 | AT20: =IFERROR(NETWORKDAYS(D20,AG20,Hoja1!$A$1:$A$29),"N/A") -> 26 | AU20: =AT20-AO20-AR20 -> 20 | AV20: Computrabajo | AW20: Seguros Bolivar | AX20: Estudio de seguridad
A21: 15144 | B21: COOMEVA | C21: USC | D21: 45967 | E21: 45961 | F21: Cali | G21: DIRECCION NACIONAL | H21: CONCURSO INTERNO | I21: INGENIERO/A GESTIÓN DE LA INFORMACIÓN | J21: ANALISTA/PROFESIONAL/COORDINADOR | K21: Susan Bermeo Saenz | L21: 1 | M21: Finalizado - Llego hasta contratacion | N21: 0000-00-00 | O21: 0 | Q21: 0000-00-00 | R21: 0000-00-00 | S21: 0 | T21: 0000-00-00 | U21: 45968 | V21: 45980 | W21: 0000-00-00 | X21: 0000-00-00 | Y21: 0000-00-00 | Z21: 0000-00-00 | AA21: 3 | AB21: 3 | AC21: 0 | AD21: 46013 | AE21: 46027 | AF21: 46028 | AG21: 46045 | AH21: 46045 | AI21: =MONTH(AH21) -> 1 | AJ21: Javier Acosta Muñoz | AK21: 20251031: El cliente solicito reclutamiento. 20251106:El cliente cambio el proceso y solicito solo recltuamiento interno y publicar el concurso hasta el Viernes 14 de Noviembre. (4) 20251107:Se envio concurso interno. 20251119: Se confirmo filtro interno 20251124:Se solicito retroalimentacion. 20251201:Se solicito retroalimentación. 20251202:El cliente informa que realizaron pruebas tecnicas y apenas tengan resultados estaran citando a entrevista. 20251209:Se volvio a solicitar retroalimentacion. (13) 20251211:El cliente envio a evaluar a Javier Acosta, Santiago Gomez y Caroline Ibagos. 20251215:Santiago y Javier no han terminado pruebas. Se cito a entrevista a Caroline que ya realizo las pruebas. 20251217:Santiago Gomez y Caroline no han terminado pruebas, por tal razón no se ha podido subir los informes. (2) 20251222:Se subio informes y se le informo al cliente. (5) 20251230:Se solicito retroalimentacion. 20260105:El cliente envio a contratar a Javier Acosta. 20260106:Se envio a contratacion con FI 22 Enero | AL21: =IFERROR(S21/O21,"N/A") -> N/A | AM21: =IFERROR(NETWORKDAYS(D21,Q21,Hoja1!$A$1:$A$29),"N/A") -> N/A | AN21: =IFERROR(NETWORKDAYS(D21,AE21,Hoja1!$A$1:$A$29),"N/A") -> 39 | AO21: 16 | AP21: =AN21-AO21 -> 23 | AQ21: =IFERROR(NETWORKDAYS(AF21,AG21,Hoja1!$A$1:$A$29),"N/A") -> 13 | AR21: 8 | AS21: =AQ21-AR21 -> 5 | AT21: =IFERROR(NETWORKDAYS(D21,AG21,Hoja1!$A$1:$A$29),"N/A") -> 52 | AU21: =AT21-AO21-AR21 -> 28 | AV21: Movimiento Interno | AW21: Coomeva Cooperativa
A22: 15147 | B22: BANCOOMEVA | C22: BANCOOMEVA | D22: 45957 | E22: 45957 | F22: Cali | G22: DIRECCION NACIONAL | H22: CONCURSO INTERNO | I22: ANALISTA SERVICIOS GESTION HUMANA | J22: ANALISTA/PROFESIONAL/COORDINADOR | K22: Carolina Cordoba Betancourt | L22: 1 | M22: Finalizado - Llego hasta contratacion | N22: 0000-00-00 | O22: 0 | Q22: 0000-00-00 | R22: 0000-00-00 | S22: 0 | T22: 0000-00-00 | U22: 45958 | V22: 45968 | W22: 0000-00-00 | X22: 0000-00-00 | Y22: 0000-00-00 | Z22: 46010 | AA22: 2 | AB22: 2 | AC22: 0 | AD22: 46017 | AE22: 46024 | AF22: 46027 | AG22: 46031 | AH22: 46035 | AI22: =MONTH(AH22) -> 1 | AJ22: Juan David Duque Gutierrez | AK22: 20251022:GH solicita concurso mixto sin RQ por nuevo cargo. 20251027:Gh crea RQ y envia 5 hv para ofertar, ademas se agrega al perfil manejo de excel, por lo que se reinicia reclutamiento. 20251028: se envian links para publicar concurso del 31 oct al 5 nov. 20251029: se envian 4 hv de reclutamiento. 20251107: se confirmar candidatos internos a GH para revisión. 20251110: se enviaran candidatos de magneto el 11nov. 20251120: se realiza seguimiento.20251201: se realiza seguimiento.20251209: se realiza seguimiento.20251212: GH programa prueba tecnica.20251219: GH solicita evaluar Jessica y Juan Duque. 20251226: Se carga evaluacion en SF.20260102: GH solicita envia a contratacion Juan Duque. 20260105: se envia O.C F.I 13 Enero | AL22: =IFERROR(S22/O22,"N/A") -> N/A | AM22: =IFERROR(NETWORKDAYS(D22,Q22,Hoja1!$A$1:$A$29),"N/A") -> N/A | AN22: =IFERROR(NETWORKDAYS(D22,AE22,Hoja1!$A$1:$A$29),"N/A") -> 45 | AO22: 22 | AP22: =AN22-AO22 -> 23 | AQ22: =IFERROR(NETWORKDAYS(AF22,AG22,Hoja1!$A$1:$A$29),"N/A") -> 5 | AR22: 0 | AS22: =AQ22-AR22 -> 5 | AT22: =IFERROR(NETWORKDAYS(D22,AG22,Hoja1!$A$1:$A$29),"N/A") -> 50 | AU22: =AT22-AO22-AR22 -> 28 | AV22: Movimiento Interno | AW22: Coomeva UCO
A23: 15153 | B23: COOMEVA | C23: UTTD | D23: 45936 | E23: 46019 | F23: Cali | G23: DIRECCION NACIONAL | H23: VACANTE DESDE RECLUTAMIENTO | I23: INGENIERO/A RPA | J23: ANALISTA/PROFESIONAL/COORDINADOR | K23: Alba Lucy Alape | L23: 1 | M23: Finalizado - Llego hasta contratacion | N23: 0000-00-00 | O23: 4 | P23: Si | Q23: 45939 | R23: 45994 | S23: 4 | T23: 0000-00-00 | U23: 0000-00-00 | V23: 0000-00-00 | W23: 0000-00-00 | X23: 0000-00-00 | Y23: 0000-00-00 | Z23: 0000-00-00 | AA23: 3 | AB23: 3 | AC23: 0 | AD23: 46001 | AE23: 46007 | AF23: 46013 | AG23: 46024 | AH23: 46027 | AI23: =MONTH(AH23) -> 1 | AJ23: Cristian Fernando Vallejo Gonzalez | AK23: 20251006: GH solicita reclutamiento con nuevo salario. 20251009: Se envian 4 hv. Pte retro por gh. 20251028: Pte retro por gh. 20251110: Pte retro por gh. 20251114: Pte retro por gh. 20251118: gh envia a Nicolas Palacio para ofertar vacante. 20251120: se confirma oferta de candidato pte retro por gh. 20251202: Pte retro por gh. (33) 20251203: gh solicita evaluar a Nicolas Palacio, Cristian Villavicencio y Cristian Vallejo. Se programan pruebas. 20251210: se confirman informes. 20251215: pte retro por gh. 20251216: gh solicita avanzar contratacion con Cristian Vallejo FI 05 ENE. 20251218: pte completar documentos para enviar OC. 20251222: Se completa documentos y se envia OC FI 05 ENE. | AL23: =IFERROR(S23/O23,"N/A") -> 1 | AM23: =IFERROR(NETWORKDAYS(D23,Q23,Hoja1!$A$1:$A$29),"N/A") -> 4 | AN23: =IFERROR(NETWORKDAYS(D23,AE23,Hoja1!$A$1:$A$29),"N/A") -> 48 | AO23: 33 | AP23: =AN23-AO23 -> 15 | AQ23: =IFERROR(NETWORKDAYS(AF23,AG23,Hoja1!$A$1:$A$29),"N/A") -> 8 | AR23: 3 | AS23: =AQ23-AR23 -> 5 | AT23: =IFERROR(NETWORKDAYS(D23,AG23,Hoja1!$A$1:$A$29),"N/A") -> 59 | AU23: =AT23-AO23-AR23 -> 23 | AV23: Computrabajo | AW23: CONSTRUCTORA BOLIVAR
A24: 15166 | B24: MP | C24: MP | D24: 45960 | E24: 45960 | F24: Cali | G24: DIRECCION NACIONAL | H24: VACANTE DESDE RECLUTAMIENTO | I24: ESTUDIANTE EN PRACTICA | J24: ESTUDIANTE/APRENDIZ | K24: Alba Lucy Alape | L24: 1 | M24: Finalizado - Llego hasta contratacion | N24: 0000-00-00 | O24: 2 | P24: Si | Q24: 45972 | R24: 45981 | S24: 2 | T24: 0000-00-00 | U24: 0000-00-00 | V24: 0000-00-00 | W24: 0000-00-00 | X24: 0000-00-00 | Y24: 0000-00-00 | Z24: 0000-00-00 | AA24: 1 | AB24: 1 | AC24: 0 | AD24: 45988 | AE24: 45992 | AF24: 46007 | AG24: 46041 | AH24: 46044 | AI24: =MONTH(AH24) -> 1 | AJ24: Cristian Fabian Guaca Imbachi | AK24: 20251030: Se activa reclutamiento. 20251105: Se informa a GH que Univalle no tiene estudiantes de estadistica. 20251106: Univalle envia 5 hv, pte ofertar. 20251111: Se envian 2 hv. pte retro por gh. (2) 20251120: gh solicita evaluar a Cristian Fabian. Se programan pruebas. 20251127: se envia informe. (3) 20251201: gh solicita avanzar contratacion para primera fecha de contratacion en Enero. 20251212: pte que Cristian envie Carta de Presentacion.(1) 20251215: Candidato envia carta. 20251216: Se envia OC FI 05 Enero. 20251229: se notifica que Cristian tiene regimen de Excepcion, Se encuentra realizando tramite, pte de la actualizacion del regimen para avanzar contratacion. Se aplaza FI para 13 ENE. SE DESCUENTAN 17 dias contratacion por requimen de excepcion de estudiante. | AL24: =IFERROR(S24/O24,"N/A") -> 1 | AM24: =IFERROR(NETWORKDAYS(D24,Q24,Hoja1!$A$1:$A$29),"N/A") -> 8 | AN24: =IFERROR(NETWORKDAYS(D24,AE24,Hoja1!$A$1:$A$29),"N/A") -> 21 | AO24: 6 | AP24: =AN24-AO24 -> 15 | AQ24: =IFERROR(NETWORKDAYS(AF24,AG24,Hoja1!$A$1:$A$29),"N/A") -> 22 | AR24: 17 | AS24: =AQ24-AR24 -> 5 | AT24: =IFERROR(NETWORKDAYS(D24,AG24,Hoja1!$A$1:$A$29),"N/A") -> 52 | AU24: =AT24-AO24-AR24 -> 29 | AV24: Bolsa de empleo Ins. Educativa | AW24: NA
A25: 15183 | B25: COOMEVA | C25: USC | D25: 45965 | E25: 45965 | F25: Cali | G25: CALI | H25: VACANTE DESDE RECLUTAMIENTO | I25: AUXILIAR DIGITALIZACIÓN | J25: AUXILIAR/OPERATIVO | K25: Susan Bermeo Saenz | L25: 1 | M25: Finalizado - Llego hasta contratacion | N25: 0000-00-00 | O25: 7 | P25: No | Q25: 45968 | R25: 45974 | S25: 7 | T25: 0000-00-00 | U25: 0000-00-00 | V25: 0000-00-00 | W25: 0000-00-00 | X25: 0000-00-00 | Y25: 0000-00-00 | Z25: 0000-00-00 | AA25: 2 | AB25: 2 | AC25: 0 | AD25: 46007 | AE25: 46008 | AF25: 46009 | AG25: 46045 | AH25: 46045 | AI25: =MONTH(AH25) -> 1 | AJ25: Elizabeth Zapata Balarezo | AK25: 20251104: El cliente solicito reclutamiento. 20251107: Se enviaron 3 hojas de vida (Edwin Medina, Alejandra Caicedo y Diana Ramirez). 20251112: Se solicito retroalimentacion. 20251113:El cliente informa que las hojas de vida estan en revision por parte del lider. 20251118:Se solicito nuevamente retroalimentacion. 20251120: Se solicita retroalimentacion. El cliente informo que entrevistaran el Jueves 27 de Nov. (11) 20251128:El cliente informo que dos candidatos no cuentan con el nivel de excel solicitado y otra candidata se desconecto de la entrevista y solicito nuevamente reclutamiento. Se activa reclutamiento. 20251201:Se enviaron 4 hojas de vida (Cristian Pino, Edwin Medina, Elizabeth Zapata, Paulo Mondragon) 20251202:El cliente informa que los candidatos fueron citados a entrevista para el 9 de Diciembre. 20251210:Se solcito retroalimentacion. (4) 20251211:GH envio a evaluar a Elizabeth zapata y Cristian Pino. se enviaron pruebas y se citaron a entrevista para el 12 dic. 20251216: Se subio informe y se le informo al cliente. 20251217:El cliente envio a contratar a Elizabeth. 20251218: Se envio a contratacion con FI 5 Enero. 20260119:Aun la candidata no se ha podido contratar porque se encuentran cogeladas las contrataciones. | AL25: =IFERROR(S25/O25,"N/A") -> 1 | AM25: =IFERROR(NETWORKDAYS(D25,Q25,Hoja1!$A$1:$A$29),"N/A") -> 4 | AN25: =IFERROR(NETWORKDAYS(D25,AE25,Hoja1!$A$1:$A$29),"N/A") -> 30 | AO25: 14 | AP25: =AN25-AO25 -> 16 | AQ25: =IFERROR(NETWORKDAYS(AF25,AG25,Hoja1!$A$1:$A$29),"N/A") -> 24 | AR25: 19 | AS25: =AQ25-AR25 -> 5 | AT25: =IFERROR(NETWORKDAYS(D25,AG25,Hoja1!$A$1:$A$29),"N/A") -> 54 | AU25: =AT25-AO25-AR25 -> 21 | AV25: Computrabajo | AW25: Coworking
A26: 15204 | B26: BANCOOMEVA | C26: BANCOOMEVA | D26: 45965 | E26: 45965 | F26: Cali | G26: DIRECCION NACIONAL | H26: EMPRESA ENVIA EL CANDIDATO | I26: ESTUDIANTE EN PRACTICA | J26: ESTUDIANTE/APRENDIZ | K26: Carolina Cordoba Betancourt | L26: 1 | M26: Finalizado - Llego hasta contratacion | N26: 0000-00-00 | O26: 0 | Q26: 0000-00-00 | R26: 0000-00-00 | S26: 0 | T26: 0000-00-00 | U26: 0000-00-00 | V26: 0000-00-00 | W26: 0000-00-00 | X26: 0000-00-00 | Y26: 0000-00-00 | Z26: 0000-00-00 | AA26: 2 | AB26: 2 | AC26: 0 | AD26: 45985 | AE26: 45989 | AF26: 45992 | AG26: 46024 | AH26: 46027 | AI26: =MONTH(AH26) -> 1 | AJ26: Miguel Angel Soto Agudelo | AK26: 20251105: GH envia 5 hv para validar y ofertar.20251111: Se envia validación de candidatos enviados, interesados Manuel soto y Cristian Guaca. 20251114: se envia hv plan referido presidencia candidato Juan pablo Garcia.20251118: GH solicita evaluar a Manuel soto y Cristian Guaca.20251124: se carga evaluacion en SF, pdt definicion de cliente para continuar.20251128: cliente solicita continuar con Miguel. 20251204: se solicita carta a institucion. 20251201: se envia O.C con F.I 05 Enero. Se presentó demora en contratación porque la posición estaba ocupada. | AL26: =IFERROR(S26/O26,"N/A") -> N/A | AM26: =IFERROR(NETWORKDAYS(D26,Q26,Hoja1!$A$1:$A$29),"N/A") -> N/A | AN26: =IFERROR(NETWORKDAYS(D26,AE26,Hoja1!$A$1:$A$29),"N/A") -> 18 | AO26: 0 | AP26: =AN26-AO26 -> 18 | AQ26: =IFERROR(NETWORKDAYS(AF26,AG26,Hoja1!$A$1:$A$29),"N/A") -> 22 | AR26: 17 | AS26: =AQ26-AR26 -> 5 | AT26: =IFERROR(NETWORKDAYS(D26,AG26,Hoja1!$A$1:$A$29),"N/A") -> 40 | AU26: =AT26-AO26-AR26 -> 23 | AV26: Referido cliente | AW26: No aplica
A27: 15211 | B27: MP | C27: MP | D27: 45966 | E27: 45966 | F27: Eje Cafetero | G27: ARMENIA | H27: VACANTE DESDE RECLUTAMIENTO | I27: EJECUTIVO/A AFILIACION | J27: CARGO COMERCIAL | K27: Natalia Aristizabal Tabares | L27: 1 | M27: Finalizado - Llego hasta contratacion | N27: 0000-00-00 | O27: 6 | P27: Si | Q27: 45971 | R27: 45974 | S27: 6 | T27: 0000-00-00 | U27: 0000-00-00 | V27: 0000-00-00 | W27: 0000-00-00 | X27: 0000-00-00 | Y27: 0000-00-00 | Z27: 0000-00-00 | AA27: 2 | AB27: 2 | AC27: 0 | AD27: 45987 | AE27: 45989 | AF27: 45989 | AG27: 46002 | AH27: 46027 | AI27: =MONTH(AH27) -> 1 | AJ27: Daisy Julieth Correa Castaño | AK27: 20251110: Se envian 6 HV: Danelly Lizeth Gonzalez, Johan Stiven Ojeda, Sergio Ordoñez, Daisy Correa, Emmy Alejandra Forero, German Huertas. 20251113: Se solicia aplicar prueba de servicio e integridad a Daisy Correa y German Huertas. 20251119: Pendiente programación de assessment. 20251124: Se solicita avanzar con proceso de evaluación con Daisy Correa y German Huertas para tomar decisión final. 20251126: Se envian informes, pendiente si se define continuar con Daisy Correa, se debe autorizar continuidad con prueba de integridad con factor en riesgo 3. 20251128: Se recibe autorización de Johana Betancourt de gestión humana para continuar con Daisy Correa con el resultado de la prueba de integridad. Se solicita contratación con FI 10 de diciembre. 20251203:La candidata informa que no puede ingresar el 10 de diciembre, ya que tiene se gano un viaje por cumplimiento comercial en la empresa en la que labora actualmente. GH define que el ingreso quedaría para la primera fecha de enero. 20251211:La candidata firma contrato con FI 5 de enero/26. *Descontar 3 dias en proceso de seleccion por demora en programación de assessment. *Descontar 5 dias en proceso de contratacion, demora por parte de la candidata en definir fecha por disponibilidad para ingreso en diciembre, y demora en completar documentos, cuenta y carta laboral. | AL27: =IFERROR(S27/O27,"N/A") -> 1 | AM27: =IFERROR(NETWORKDAYS(D27,Q27,Hoja1!$A$1:$A$29),"N/A") -> 4 | AN27: =IFERROR(NETWORKDAYS(D27,AE27,Hoja1!$A$1:$A$29),"N/A") -> 17 | AO27: 3 | AP27: =AN27-AO27 -> 14 | AQ27: =IFERROR(NETWORKDAYS(AF27,AG27,Hoja1!$A$1:$A$29),"N/A") -> 9 | AR27: 4 | AS27: =AQ27-AR27 -> 5 | AT27: =IFERROR(NETWORKDAYS(D27,AG27,Hoja1!$A$1:$A$29),"N/A") -> 25 | AU27: =AT27-AO27-AR27 -> 18 | AV27: Computrabajo | AW27: American School Way
A28: 15228 | B28: COOMEVA EXPERIENCIA MEDICA | C28: COOMEVA EXPERIENCIA MEDICA | D28: 45968 | E28: 45968 | F28: Bogota | G28: BOGOTA | H28: VACANTE DESDE RECLUTAMIENTO | I28: NUTRICIONISTA CENTRAL CEM | J28: SALUD/ASISTENCIAL | K28: Francisco Javier Quintero Chacon | L28: 1 | M28: Finalizado - Llego hasta contratacion | N28: 0000-00-00 | O28: 3 | P28: Si | Q28: 45987 | R28: 45987 | S28: 3 | T28: 0000-00-00 | U28: 0000-00-00 | V28: 0000-00-00 | W28: 0000-00-00 | X28: 0000-00-00 | Y28: 0000-00-00 | Z28: 0000-00-00 | AA28: 3 | AB28: 1 | AC28: 0 | AD28: 45992 | AE28: 45992 | AF28: 45993 | AG28: 46024 | AH28: 46027 | AI28: =MONTH(AH28) -> 1 | AJ28: Karen Andrea Lancheros Molano | AK28: 20251107: Se activa reclutamiento. 20251110: Se envían hv preseleccionadas a GH para validacion, a la espera de retro. 20251112: Se programan entrevistas para el 13 de Noviembre. 20251113: Con base en el espacio de hoy candidatos aptos: Irina Chaparro, karen lancheros y Maria Paula Marichal, se solicitan documentos. 20251118: Candidatos aun en documentos. 20251120: Pendiente por confirmar candidatos para enviar a ES. 20251126: Se envía a e.s. y contratación a Maria Paula Marichal con fecha tentativa de ingreso del 1 de Diciembre, con posibilidad de cambio con base en la información recibida por parte de GH. 20251201: Con base en la información recibida por parte de GH la candidata no sigue en el proceso, se retoma back up Karen Lancheros, se solicitan documentos. 20251202: Se envía a estudio de seguridad y contratación a Karen Lancheros con fecha tentativa de ingreso del 10 de Diciembre con posibilidad de cambio segun informacion recibida por parte de GH. 20251209: Con base en la información recibida la candidata presentó una novedad de salud lo que le impide ir a los exámenes médicos por lo que se brinda un plazo adicional con autorización de GH para que su ingreso se dé la primera semana de Enero por tarde, con esto la candidata irá a exámenes médicos sobre el 18 de Diciembre segun información de GH, entre tanto la candidata adelantará los demás pendientes. 20251226: Segun informacion de contratación la candidata Karen Lancheros se encuentra en apertura de cuenta. | AL28: =IFERROR(S28/O28,"N/A") -> 1 | AM28: =IFERROR(NETWORKDAYS(D28,Q28,Hoja1!$A$1:$A$29),"N/A") -> 13 | AN28: =IFERROR(NETWORKDAYS(D28,AE28,Hoja1!$A$1:$A$29),"N/A") -> 16 | AO28: 0 | AP28: =AN28-AO28 -> 16 | AQ28: =IFERROR(NETWORKDAYS(AF28,AG28,Hoja1!$A$1:$A$29),"N/A") -> 21 | AR28: 16 | AS28: =AQ28-AR28 -> 5 | AT28: =IFERROR(NETWORKDAYS(D28,AG28,Hoja1!$A$1:$A$29),"N/A") -> 37 | AU28: =AT28-AO28-AR28 -> 21 | AV28: Computrabajo | AW28: Compensar
A29: 15253 | B29: MP | C29: MP | D29: 45992 | E29: 45970 | F29: Cali | G29: DIRECCION NACIONAL | H29: CONCURSO MIXTO | I29: ANALISTA NAL MERCADEO | J29: ANALISTA/PROFESIONAL/COORDINADOR | K29: Alba Lucy Alape | L29: 1 | M29: Finalizado - Llego hasta contratacion | N29: 0000-00-00 | O29: 6 | P29: No | Q29: 45995 | R29: 46006 | S29: 6 | T29: 45973 | U29: 46002 | V29: 45979 | W29: 0000-00-00 | X29: 0000-00-00 | Y29: 0000-00-00 | Z29: 0000-00-00 | AA29: 2 | AB29: 1 | AC29: 0 | AD29: 46010 | AE29: 46010 | AF29: 46013 | AG29: 46024 | AH29: 46027 | AI29: =MONTH(AH29) -> 1 | AJ29: Brayan Andres Obonaga Giron | AK29: 20251110: Se activa reclutamiento mixto. 20251112: se envia publicacion de concurso fecha maxima publicacion 17 Nov. 20251118: se envia filtro interno. Pte retro por gh. Ese mismo dia se envian 6 hv para 2 vacantes. Pte retro por gh. 20251120: gh envia retro y solicita activa reclutamiento. 20251125: evaluar y contratar a Hans Escobar. 20251128: se notifica novedad veritas. gh solicita programar entrevista. 20251201: candidato desiste de la vacante. Se activa reclutamiento. 20251204: Se envian 3 hv. Pte retro por gh. 20251215: gh solicita evaluar a German, Brayan e Ivana para las 2 vacantes activas. Se programan pruebas. 20251219: Se confirma informe y se solicita avanzar contratacion con Brayan Obonaga. 20251222: Se envia OC FI 05 ENE. | AL29: =IFERROR(S29/O29,"N/A") -> 1 | AM29: =IFERROR(NETWORKDAYS(D29,Q29,Hoja1!$A$1:$A$29),"N/A") -> 4 | AN29: =IFERROR(NETWORKDAYS(D29,AE29,Hoja1!$A$1:$A$29),"N/A") -> 14 | AO29: 0 | AP29: =AN29-AO29 -> 14 | AQ29: =IFERROR(NETWORKDAYS(AF29,AG29,Hoja1!$A$1:$A$29),"N/A") -> 8 | AR29: 3 | AS29: =AQ29-AR29 -> 5 | AT29: =IFERROR(NETWORKDAYS(D29,AG29,Hoja1!$A$1:$A$29),"N/A") -> 22 | AU29: =AT29-AO29-AR29 -> 19 | AV29: Computrabajo | AW29: CABLES SUPERIORES COLOMBIA S.A.S | AX29: Candidato desiste
A30: 15254 | B30: MP | C30: MP | D30: 45986 | E30: 45970 | F30: Cali | G30: DIRECCION NACIONAL | H30: CONCURSO INTERNO | I30: ANALISTA NAL MERCADEO | J30: ANALISTA/PROFESIONAL/COORDINADOR | K30: Alba Lucy Alape | L30: 1 | M30: Finalizado - Llego hasta contratacion | N30: 0000-00-00 | O30: 0 | Q30: 0000-00-00 | R30: 0000-00-00 | S30: 0 | T30: 0000-00-00 | U30: 0000-00-00 | V30: 0000-00-00 | W30: 0000-00-00 | X30: 0000-00-00 | Y30: 0000-00-00 | Z30: 0000-00-00 | AA30: 1 | AB30: 1 | AC30: 0 | AD30: 46000 | AE30: 46002 | AF30: 46009 | AG30: 46024 | AH30: 46027 | AI30: =MONTH(AH30) -> 1 | AJ30: Jhon Nicolas Hernandez Polindara | AK30: 20251011: Se activa reclutamiento mixto. 20251112: se envia publicacion de concurso fecha maxima publicacion 17 Nov. 20251118: se envia filtro interno. Pte retro por gh. Ese mismo dia se envian 6 hv para 2 vacantes. Pte retro por gh. 20251125: gh envia nuevo rol para reclutamiento. 20251126: se envian 3 hv. pte retro por gh. 20251202: gh solicita evaluar a Jhon Nicolas Hernandez. Se programan pruebas. 20251209: Se confirma informe. 20251211: gh solicita avanzar contratacion. 20251212: pte envio de excepcion por formacion academica y veritas riesgo 3 para enviar a contratacion. 20251218: se envia excepcion y se avanza al envio OC FI 05 ENE. | AL30: =IFERROR(S30/O30,"N/A") -> N/A | AM30: =IFERROR(NETWORKDAYS(D30,Q30,Hoja1!$A$1:$A$29),"N/A") -> N/A | AN30: =IFERROR(NETWORKDAYS(D30,AE30,Hoja1!$A$1:$A$29),"N/A") -> 12 | AO30: 0 | AP30: =AN30-AO30 -> 12 | AQ30: =IFERROR(NETWORKDAYS(AF30,AG30,Hoja1!$A$1:$A$29),"N/A") -> 10 | AR30: 5 | AS30: =AQ30-AR30 -> 5 | AT30: =IFERROR(NETWORKDAYS(D30,AG30,Hoja1!$A$1:$A$29),"N/A") -> 26 | AU30: =AT30-AO30-AR30 -> 21 | AV30: Movimiento Interno | AW30: Coomeva
A31: 15279 | B31: MP | C31: MP | D31: 45973 | E31: 45973 | F31: Cali | G31: CALI | H31: VACANTE DESDE RECLUTAMIENTO | I31: ENFERMERO(A) CM | J31: SALUD/ASISTENCIAL | K31: Alba Lucy Alape | L31: 1 | M31: Finalizado - Llego hasta contratacion | N31: 0000-00-00 | O31: 3 | P31: Si | Q31: 45979 | R31: 45993 | S31: 3 | T31: 0000-00-00 | U31: 0000-00-00 | V31: 0000-00-00 | W31: 0000-00-00 | X31: 0000-00-00 | Y31: 0000-00-00 | Z31: 0000-00-00 | AA31: 3 | AB31: 1 | AC31: 0 | AD31: 46001 | AE31: 46003 | AF31: 46007 | AG31: 46024 | AH31: 46027 | AI31: =MONTH(AH31) -> 1 | AJ31: Diana Carolina Marmolejo Espinosa | AK31: 20251112: Se activa reclutamiento. 20251118: Se envian 3 hv. Pte retro por gh. 20251124: pte retro por gh. (6)20251202: gh solicita evaluar a Diana Marmolejo, Leydi Marin y Diana Zuleta. Se programan pruebas. 20251210: :se confirma informes. 20251212: gh solicita avanzar con Diana Marmolejo. 20251216: Se envia OC FI 05 ENE. | AL31: =IFERROR(S31/O31,"N/A") -> 1 | AM31: =IFERROR(NETWORKDAYS(D31,Q31,Hoja1!$A$1:$A$29),"N/A") -> 4 | AN31: =IFERROR(NETWORKDAYS(D31,AE31,Hoja1!$A$1:$A$29),"N/A") -> 21 | AO31: 6 | AP31: =AN31-AO31 -> 15 | AQ31: =IFERROR(NETWORKDAYS(AF31,AG31,Hoja1!$A$1:$A$29),"N/A") -> 12 | AR31: 7 | AS31: =AQ31-AR31 -> 5 | AT31: =IFERROR(NETWORKDAYS(D31,AG31,Hoja1!$A$1:$A$29),"N/A") -> 34 | AU31: =AT31-AO31-AR31 -> 21 | AV31: Computrabajo | AW31: HOSPITAL DIVINO NIÑO GUADALAJARA DE BUGA
A32: 15308 | B32: BANCOOMEVA | C32: BANCOOMEVA | D32: 45988 | E32: 45975 | F32: Cali | G32: DIRECCION NACIONAL | H32: VACANTE DESDE RECLUTAMIENTO | I32: ANALISTA OPERACIONES CREDITO Y CARTERA | J32: ANALISTA/PROFESIONAL/COORDINADOR | K32: Carolina Cordoba Betancourt | L32: 1 | M32: Finalizado - Llego hasta contratacion | N32: 0000-00-00 | O32: 3 | P32: Si | Q32: 45994 | R32: 45994 | S32: 3 | T32: 0000-00-00 | U32: 0000-00-00 | V32: 0000-00-00 | W32: 0000-00-00 | X32: 0000-00-00 | Y32: 0000-00-00 | Z32: 0000-00-00 | AA32: 1 | AB32: 1 | AC32: 0 | AD32: 46020 | AE32: 46021 | AF32: 46024 | AG32: 46044 | AH32: 46045 | AI32: =MONTH(AH32) -> 1 | AJ32: Dora Luz Cabuyales Piñeros | AK32: 20251114:GH envia candidato, se evalua martes 18 Nov. 20251121: evalaucion cargada en SF, pdt aprobacion para continuar contratación. 20251127: GH informa no avanzar con candidato referido, solicita reclutamiento. 20251203: se envian 3cv a GH Dora, Paula, Yeimi.20251216: se realiza seguimiento. 20251226: Evaluar dora cabuyales. 20251229: se carga evaluacion en sf. 20251230: enviar a contratacion dora cabuyales. 20260102: se envia O.C F.I 13 enero.20251231: rq detenido por instruccion del corporativo.20260121: uco autorizar activar contrataciones, se define F.I 23 Enero. | AL32: =IFERROR(S32/O32,"N/A") -> 1 | AM32: =IFERROR(NETWORKDAYS(D32,Q32,Hoja1!$A$1:$A$29),"N/A") -> 5 | AN32: =IFERROR(NETWORKDAYS(D32,AE32,Hoja1!$A$1:$A$29),"N/A") -> 22 | AO32: 7 | AP32: =AN32-AO32 -> 15 | AQ32: =IFERROR(NETWORKDAYS(AF32,AG32,Hoja1!$A$1:$A$29),"N/A") -> 14 | AR32: 9 | AS32: =AQ32-AR32 -> 5 | AT32: =IFERROR(NETWORKDAYS(D32,AG32,Hoja1!$A$1:$A$29),"N/A") -> 37 | AU32: =AT32-AO32-AR32 -> 21 | AV32: Computrabajo | AW32: Cooperativa multisoluciones
A33: 15312 | B33: MP | C33: MP | D33: 45975 | E33: 45975 | F33: Eje Cafetero | G33: ARMENIA | H33: VACANTE DESDE RECLUTAMIENTO | I33: EJECUTIVO(A) AFILIACION SAO | J33: CARGO COMERCIAL | K33: Natalia Aristizabal Tabares | L33: 1 | M33: Finalizado - Llego hasta contratacion | N33: 0000-00-00 | O33: 9 | P33: No | Q33: 45980 | R33: 46001 | S33: 9 | T33: 0000-00-00 | U33: 0000-00-00 | V33: 0000-00-00 | W33: 0000-00-00 | X33: 0000-00-00 | Y33: 0000-00-00 | Z33: 0000-00-00 | AA33: 2 | AB33: 2 | AC33: 0 | AD33: 46009 | AE33: 46006 | AF33: 46009 | AG33: 46021 | AH33: 46027 | AI33: =MONTH(AH33) -> 1 | AJ33: Luz Adriana Walteros Gañan | AK33: 20251119: Se envian 4 HV: Jessica Alejandra Hurtado, Ana Maria Coronado, Adriana Montoya, Efrain Josue Noriega. 20251126: Se solicita aplicar pruebas a Jessica Alejandra Hurtado. 20251128: La candidata informa que desiste del proceso por otra oferta, pendiente realizar oferta a candidato que realizó proceso de selección para MI. 20251202: Se define avanzar con proceso de contratación con candidato German Antonio Huertas que habia presentado proceso para MI. Se envia orden de contratacion con FI 10 de diciembre. 20251204: Se reporta novedad en Estudio de seguridad con la que no se puede avanzar en el proceso, se solicita continuar con reclutamiento. 20251205: Se envian otras 5 HV: Nicolas Torres, Sandra Milena Torres, Luz Adriana Walteros, Andres Mauricio Ocampo, Geraldine Barney Chica. 20251210: Se solicita aplicar prueba de servicio e integridad a Luz Adriana Walteros. 20251215: Después de realizar assessment se solicita continuar con evaluación y contratación con Luz Adriana Walteros, se debe realizar validación pensional ya que la candidata tiene 47 años. 20251217: Se recibe resultado de validación pensional, con aprobación para continuar. 20251218: Se envia informe, se solicita contratación con ingreso 5 de enero. 20251230: La candidata firma contrato. *Descontar 8 dias en proceso de seleccion, el primer candidato seleccionado no pasa EDS, se debe iniciar nuevamente el proceso. *Descontar 4 dias en proceso de contratacion por demora por parte del proveedor en entregar resultado de emo y completar documentos por parte de la candidata. | AL33: =IFERROR(S33/O33,"N/A") -> 1 | AM33: =IFERROR(NETWORKDAYS(D33,Q33,Hoja1!$A$1:$A$29),"N/A") -> 3 | AN33: =IFERROR(NETWORKDAYS(D33,AE33,Hoja1!$A$1:$A$29),"N/A") -> 20 | AO33: 6 | AP33: =AN33-AO33 -> 14 | AQ33: =IFERROR(NETWORKDAYS(AF33,AG33,Hoja1!$A$1:$A$29),"N/A") -> 8 | AR33: 3 | AS33: =AQ33-AR33 -> 5 | AT33: =IFERROR(NETWORKDAYS(D33,AG33,Hoja1!$A$1:$A$29),"N/A") -> 30 | AU33: =AT33-AO33-AR33 -> 21 | AV33: Computrabajo | AW33: Fundación de la Mujer | AX33: Candidato desiste | AY33: Estudio de seguridad
A34: 15315 | B34: MP | C34: MP | D34: 45988 | E34: 45993 | F34: Cali | G34: DIRECCION NACIONAL | H34: VACANTE DESDE RECLUTAMIENTO | I34: APRENDIZ SENA | J34: ESTUDIANTE/APRENDIZ | K34: Susan Bermeo Saenz | L34: 1 | M34: Finalizado - Llego hasta contratacion | N34: 0000-00-00 | O34: 5 | P34: No | Q34: 45996 | R34: 45996 | S34: 5 | T34: 0000-00-00 | U34: 0000-00-00 | V34: 0000-00-00 | W34: 0000-00-00 | X34: 0000-00-00 | Y34: 0000-00-00 | Z34: 0000-00-00 | AA34: 3 | AB34: 3 | AC34: 0 | AD34: 46003 | AE34: 46003 | AF34: 46013 | AG34: 46024 | AH34: 46027 | AI34: =MONTH(AH34) -> 1 | AJ34: Joselin Flor Ordoñez | AK34: 20251202: Se reactiva reclutamento teniendo en cuenta que no se cubre la pocision con curso cerrado. ese mismo dia se envian 2 hv. Pte retro por gh. 20251205: gh envia retro y se activa reclutamiento. Ese mismo dia se envian 3 hv. Pte retro por gh. 20251212: gh solicita evaluar a Javier Rodriguez y Leidy Marquez y Joselin Flor. Se programan pruebas. 20251218:El cliente envio a contratar a Joselin Flor. 20251222:Se enviaron a contratacion con FI 5 Enero. | AL34: =IFERROR(S34/O34,"N/A") -> 1 | AM34: =IFERROR(NETWORKDAYS(D34,Q34,Hoja1!$A$1:$A$29),"N/A") -> 7 | AN34: =IFERROR(NETWORKDAYS(D34,AE34,Hoja1!$A$1:$A$29),"N/A") -> 11 | AO34: 0 | AP34: =AN34-AO34 -> 11 | AQ34: =IFERROR(NETWORKDAYS(AF34,AG34,Hoja1!$A$1:$A$29),"N/A") -> 8 | AR34: 3 | AS34: =AQ34-AR34 -> 5 | AT34: =IFERROR(NETWORKDAYS(D34,AG34,Hoja1!$A$1:$A$29),"N/A") -> 24 | AU34: =AT34-AO34-AR34 -> 21 | AV34: Busqueda directa | AW34: N/A
A35: 15317 | B35: COOMEVA | C35: USC | D35: 45993 | E35: 45994 | F35: Cali | G35: CALI | H35: EMPRESA ENVIA EL CANDIDATO | I35: AUXILIAR COMPRAS | J35: AUXILIAR/OPERATIVO | K35: Susan Bermeo Saenz | L35: 1 | M35: Finalizado - Llego hasta contratacion | N35: 0000-00-00 | O35: 0 | Q35: 0000-00-00 | R35: 0000-00-00 | S35: 0 | T35: 0000-00-00 | U35: 0000-00-00 | V35: 0000-00-00 | W35: 0000-00-00 | X35: 0000-00-00 | Y35: 0000-00-00 | Z35: 0000-00-00 | AA35: 1 | AB35: 1 | AC35: 0 | AD35: 46000 | AE35: 46002 | AF35: 46007 | AG35: 46024 | AH35: 46027 | AI35: =MONTH(AH35) -> 1 | AJ35: Breiner Steven Londoño Morales | AK35: 20251202: Se solicito reclutamiento. El cliente envio a evaluar a Breiner, se cito a entrevista para el 4 de Dic y se enviaron pruebas. 20251205:El candidato no ha terminado pruebas. 20251209:Se subio informe y se le informo al cliente. 20251211:El cliente envio a contratar a Breiner. Pendiente formato de excepcion para enviarlo a contratacion. 20251216:GH envio formato de excepcion y se envio a contratacion con FI 5 enero. | AL35: =IFERROR(S35/O35,"N/A") -> N/A | AM35: =IFERROR(NETWORKDAYS(D35,Q35,Hoja1!$A$1:$A$29),"N/A") -> N/A | AN35: =IFERROR(NETWORKDAYS(D35,AE35,Hoja1!$A$1:$A$29),"N/A") -> 7 | AO35: 0 | AP35: =AN35-AO35 -> 7 | AQ35: =IFERROR(NETWORKDAYS(AF35,AG35,Hoja1!$A$1:$A$29),"N/A") -> 12 | AR35: 7 | AS35: =AQ35-AR35 -> 5 | AT35: =IFERROR(NETWORKDAYS(D35,AG35,Hoja1!$A$1:$A$29),"N/A") -> 21 | AU35: =AT35-AO35-AR35 -> 14 | AV35: Movimiento Interno | AW35: Coomeva Cooperativa
A36: 15321 | B36: COOMEVA EXPERIENCIA MEDICA | C36: COOMEVA EXPERIENCIA MEDICA | D36: 45979 | E36: 45979 | F36: Cali | G36: DIRECCION NACIONAL | H36: EMPRESA ENVIA EL CANDIDATO | I36: ESTUDIANTE EN PRACTICA | J36: ESTUDIANTE/APRENDIZ | K36: Carolina Cordoba Betancourt | L36: 1 | M36: Finalizado - Llego hasta contratacion | N36: 0000-00-00 | O36: 0 | Q36: 0000-00-00 | R36: 0000-00-00 | S36: 0 | T36: 0000-00-00 | U36: 0000-00-00 | V36: 0000-00-00 | W36: 0000-00-00 | X36: 0000-00-00 | Y36: 0000-00-00 | Z36: 0000-00-00 | AA36: 1 | AB36: 1 | AC36: 0 | AD36: 46001 | AE36: 46002 | AF36: 46002 | AG36: 46022 | AH36: 46027 | AI36: =MONTH(AH36) -> 1 | AJ36: Salome Hurtado Garcia | AK36: 20251204: GH envia Cv para evaluar ( salome) 20251205: se envian 7cv a GH.20251210: evaluacion en SF. 20251211:GH solicita contratación. 20251211: se envia O.C con F.I 05 enero. Se presentó demora en contratación porque la posición estaba ocupada. | AL36: =IFERROR(S36/O36,"N/A") -> N/A | AM36: =IFERROR(NETWORKDAYS(D36,Q36,Hoja1!$A$1:$A$29),"N/A") -> N/A | AN36: =IFERROR(NETWORKDAYS(D36,AE36,Hoja1!$A$1:$A$29),"N/A") -> 17 | AO36: 0 | AP36: =AN36-AO36 -> 17 | AQ36: =IFERROR(NETWORKDAYS(AF36,AG36,Hoja1!$A$1:$A$29),"N/A") -> 14 | AR36: 9 | AS36: =AQ36-AR36 -> 5 | AT36: =IFERROR(NETWORKDAYS(D36,AG36,Hoja1!$A$1:$A$29),"N/A") -> 30 | AU36: =AT36-AO36-AR36 -> 21 | AV36: Referido cliente | AW36: No aplica
A37: 15322 | B37: COOMEVA EXPERIENCIA MEDICA | C37: COOMEVA EXPERIENCIA MEDICA | D37: 45979 | E37: 45979 | F37: Cali | G37: CALI | H37: VACANTE DESDE RECLUTAMIENTO | I37: ESTUDIANTE EN PRACTICA | J37: ESTUDIANTE/APRENDIZ | K37: Carolina Cordoba Betancourt | L37: 1 | M37: Finalizado - Llego hasta contratacion | N37: 0000-00-00 | O37: 15 | P37: No | Q37: 46014 | R37: 46014 | S37: 14 | T37: 0000-00-00 | U37: 0000-00-00 | V37: 0000-00-00 | W37: 0000-00-00 | X37: 0000-00-00 | Y37: 0000-00-00 | Z37: 0000-00-00 | AA37: 1 | AB37: 1 | AC37: 0 | AD37: 46027 | AE37: 46027 | AF37: 46027 | AG37: 46042 | AH37: 46044 | AI37: =MONTH(AH37) -> 1 | AJ37: Maria Jose Garcia Ruiz | AK37: 20251118: se envia reclutamiento. 20251118: GH enviada 3cv, se filtran y continua Mariana. 20251118: reclutamiento comparte dos cv. 20251911: se envian candidatos a GH 1 referida y dos de reclutamiento. 20251121: GH solicita reclutamiento, candidatos no se presentaron. 20251126: se envian a GH 4cv.20251127: GH solicita evaluar a mariana y Wilson 20251127: candidatos desisten GH solicita reclutamiento. 20251204: se comparte GH 1cv Andrea.20251209: se envia 1cv Miguel. 20251212: se realiza seguimiento.20251218: se activa reclutamiento.20251223: se envian 2cv.20251226: GH informa juan david no aprobo entrevista, pdt definir candidata Maria Jose.20251229: GH informe continuar con Maria Jose. 20260105: se carga evaluacion en sf. 20260105: se envia contratacion con F.I 22 Enero. | AL37: =IFERROR(S37/O37,"N/A") -> 0.93333333 | AM37: =IFERROR(NETWORKDAYS(D37,Q37,Hoja1!$A$1:$A$29),"N/A") -> 25 | AN37: =IFERROR(NETWORKDAYS(D37,AE37,Hoja1!$A$1:$A$29),"N/A") -> 32 | AO37: 10 | AP37: =AN37-AO37 -> 22 | AQ37: =IFERROR(NETWORKDAYS(AF37,AG37,Hoja1!$A$1:$A$29),"N/A") -> 11 | AR37: 6 | AS37: =AQ37-AR37 -> 5 | AT37: =IFERROR(NETWORKDAYS(D37,AG37,Hoja1!$A$1:$A$29),"N/A") -> 42 | AU37: =AT37-AO37-AR37 -> 26 | AV37: Bolsa de empleo Ins. Educativa | AW37: No aplica
A38: 15324 | B38: COOMEVA EXPERIENCIA MEDICA | C38: COOMEVA EXPERIENCIA MEDICA | D38: 46003 | E38: 46003 | F38: Cali | G38: DIRECCION NACIONAL | H38: VACANTE DESDE RECLUTAMIENTO | I38: APRENDIZ SENA | J38: ESTUDIANTE/APRENDIZ | K38: Carolina Cordoba Betancourt | L38: 1 | M38: Finalizado - Llego hasta contratacion | N38: 0000-00-00 | O38: 7 | P38: No | Q38: 46009 | R38: 46009 | S38: 7 | T38: 0000-00-00 | U38: 0000-00-00 | V38: 0000-00-00 | W38: 0000-00-00 | X38: 0000-00-00 | Y38: 0000-00-00 | Z38: 0000-00-00 | AA38: 1 | AB38: 1 | AC38: 0 | AD38: 46031 | AE38: 46031 | AF38: 46034 | AG38: 46043 | AH38: 46044 | AI38: =MONTH(AH38) -> 1 | AJ38: Laura Vanessa Molina Peñaranda | AK38: 20251031: Gh solicita evaluar a Juan Camilo Villegas, se realiza contacto con candidato, entrevista 5 Nov. 20251106: se genera evaluacion en successfactors.20251106: se envia a proceso de contratación, fecha tentativa de ingreso 18 de noviembre. 20251114: se confirma contratación.20251128: se reasigna RQ para reclutamiento.20251201: se envia a reclutamiento.20251203: se envia a cliente las dos CV.20251203: GH solicita evaluar a Michel Medina. 20251215: GH solicita contratar a Michel en espera de documentos se encuentra en proceso de solicitud contraseña.20251218: candidata michle informa dificultad en solicitar cedula debido a error en registro civil, se envian 2 cv a GH. 20251222: GH solicita evaluar a Franyer.20251226: Se evalua frayner. 20260102: No continua en proceso Franyer, se ectiva reclutamiento, se envian 3cv.20260105: GH solicita evaluar Laura Molina.20260109: evaluada,evaluacion en sf GH solicita enviar O.C 20260113: se envia a contratacion con F.I 22 Enero. | AL38: =IFERROR(S38/O38,"N/A") -> 1 | AM38: =IFERROR(NETWORKDAYS(D38,Q38,Hoja1!$A$1:$A$29),"N/A") -> 5 | AN38: =IFERROR(NETWORKDAYS(D38,AE38,Hoja1!$A$1:$A$29),"N/A") -> 19 | AO38: 0 | AP38: =AN38-AO38 -> 19 | AQ38: =IFERROR(NETWORKDAYS(AF38,AG38,Hoja1!$A$1:$A$29),"N/A") -> 7 | AR38: 2 | AS38: =AQ38-AR38 -> 5 | AT38: =IFERROR(NETWORKDAYS(D38,AG38,Hoja1!$A$1:$A$29),"N/A") -> 26 | AU38: =AT38-AO38-AR38 -> 24 | AV38: Bolsa de empleo Ins. Educativa | AW38: No aplica
A39: 15326 | B39: COOMEVA | C39: UCO | D39: 45980 | E39: 45979 | F39: Cali | G39: DIRECCION NACIONAL | H39: VACANTE DESDE RECLUTAMIENTO | I39: ESTUDIANTE EN PRACTICA | J39: ESTUDIANTE/APRENDIZ | K39: Alba Lucy Alape | L39: 1 | M39: Finalizado - Llego hasta contratacion | N39: 0000-00-00 | O39: 3 | P39: Si | Q39: 45985 | R39: 45993 | S39: 3 | T39: 0000-00-00 | U39: 0000-00-00 | V39: 0000-00-00 | W39: 0000-00-00 | X39: 0000-00-00 | Y39: 0000-00-00 | Z39: 0000-00-00 | AA39: 1 | AB39: 1 | AC39: 0 | AD39: 46000 | AE39: 46000 | AF39: 46007 | AG39: 46024 | AH39: 46027 | AI39: =MONTH(AH39) -> 1 | AJ39: Natalia Cortes Hernandez | AK39: 20251119: Se activa reclutamiento. 20251124: se envian 3 hv. Pte retro por gh. 20251202: gh solicita evaluar y contratar a Natalia Cortes. Se programan pruebas. 20251209: se confirma informe. Ese mismo dia gh solicita avanzar a contratacion con Natalia. Pte carta de presentacion de candidata para avanzar. 20251216: se envia OC FI 05 Enero. | AL39: =IFERROR(S39/O39,"N/A") -> 1 | AM39: =IFERROR(NETWORKDAYS(D39,Q39,Hoja1!$A$1:$A$29),"N/A") -> 4 | AN39: =IFERROR(NETWORKDAYS(D39,AE39,Hoja1!$A$1:$A$29),"N/A") -> 14 | AO39: 0 | AP39: =AN39-AO39 -> 14 | AQ39: =IFERROR(NETWORKDAYS(AF39,AG39,Hoja1!$A$1:$A$29),"N/A") -> 12 | AR39: 7 | AS39: =AQ39-AR39 -> 5 | AT39: =IFERROR(NETWORKDAYS(D39,AG39,Hoja1!$A$1:$A$29),"N/A") -> 30 | AU39: =AT39-AO39-AR39 -> 23 | AV39: Bolsa de empleo Ins. Educativa | AW39: NA
A40: 15327 | B40: COOMEVA EXPERIENCIA MEDICA | C40: COOMEVA EXPERIENCIA MEDICA | D40: 45980 | E40: 45980 | F40: Cali | G40: DIRECCION NACIONAL | H40: VACANTE DESDE RECLUTAMIENTO | I40: AUXILIAR NAL CENTRAL ASISTENCIAL | J40: SALUD/ASISTENCIAL | K40: Carolina Cordoba Betancourt | L40: 1 | M40: Finalizado - Llego hasta contratacion | N40: 0000-00-00 | O40: 4 | P40: Si | Q40: 45985 | R40: 45985 | S40: 4 | T40: 0000-00-00 | U40: 0000-00-00 | V40: 0000-00-00 | W40: 0000-00-00 | X40: 0000-00-00 | Y40: 0000-00-00 | Z40: 0000-00-00 | AA40: 1 | AB40: 1 | AC40: 0 | AD40: 45992 | AE40: 45992 | AF40: 45993 | AG40: 46017 | AH40: 46027 | AI40: =MONTH(AH40) -> 1 | AJ40: Ana Isabella Rodriguez Casas | AK40: 20251119: se inicia reclutamiento.20251124: se envian 4cv GH.20251126: GH solicita evaluar Ana Isabella.20251201: evaluada Ana, evaluacion en sf. 20251201: GH solicita contratar ana 20251202: se envia OC con F.I 10 Dic.20251210: candidato no envio documentos completos, se corre ingreso para el 5 de Enero. | AL40: =IFERROR(S40/O40,"N/A") -> 1 | AM40: =IFERROR(NETWORKDAYS(D40,Q40,Hoja1!$A$1:$A$29),"N/A") -> 4 | AN40: =IFERROR(NETWORKDAYS(D40,AE40,Hoja1!$A$1:$A$29),"N/A") -> 9 | AO40: 0 | AP40: =AN40-AO40 -> 9 | AQ40: =IFERROR(NETWORKDAYS(AF40,AG40,Hoja1!$A$1:$A$29),"N/A") -> 17 | AR40: 12 | AS40: =AQ40-AR40 -> 5 | AT40: =IFERROR(NETWORKDAYS(D40,AG40,Hoja1!$A$1:$A$29),"N/A") -> 26 | AU40: =AT40-AO40-AR40 -> 14 | AV40: Computrabajo | AW40: Centro comercial Unico
A41: 15328 | B41: COOMEVA | C41: GCGIA | D41: 45980 | E41: 45980 | F41: Eje Cafetero | G41: ARMENIA | H41: VACANTE DESDE RECLUTAMIENTO | I41: APRENDIZ SENA | J41: ESTUDIANTE/APRENDIZ | K41: Natalia Aristizabal Tabares | L41: 1 | M41: Finalizado - Llego hasta contratacion | N41: 0000-00-00 | O41: 5 | P41: Si | Q41: 45987 | R41: 46000 | S41: 5 | T41: 0000-00-00 | U41: 0000-00-00 | V41: 0000-00-00 | W41: 0000-00-00 | X41: 0000-00-00 | Y41: 0000-00-00 | Z41: 0000-00-00 | AA41: 1 | AB41: 1 | AC41: 0 | AD41: 46002 | AE41: 46000 | AF41: 46003 | AG41: 46017 | AH41: 46027 | AI41: =MONTH(AH41) -> 1 | AJ41: Jeremy Gomez Ariza | AK41: 20251126: Después de realizar gestión con las Instituciones no se encuentran estudiantes disponibles en etapa productiva, Se envian 5 HV de estudiantes disponibles del Sena en etapa lectiva para inicio de productiva en julio/2026: Jeremy Gomez, Jodie Vanesa Mondragón, Angelica Viviana Cordoba. Esteban Gonzalez, Sandra Lorena Cardona. 20251202: Pendiente programar entrevista con candidatos enviados. 20251209: Se solicita continuar con proceso de evaluación y contratación con Jeremy Gomez para ingreso el 5 de enero. 20251211: Se envia informe, se solicita contratación. 20231223: Pendiente completar documentos por parte del candidato: cuenta, certificado de pensión. 20251226: El candidato firma contrato. *Descontar 3 dias en proceso de seleccion por demora en programar entrevistas despues de envio de HV. *Descontar 6 dias en proceso de contratacion, por demora en completar documentos por parte del candidato, demora en gestionar afiliación a fondo de pensión. | AL41: =IFERROR(S41/O41,"N/A") -> 1 | AM41: =IFERROR(NETWORKDAYS(D41,Q41,Hoja1!$A$1:$A$29),"N/A") -> 6 | AN41: =IFERROR(NETWORKDAYS(D41,AE41,Hoja1!$A$1:$A$29),"N/A") -> 14 | AO41: 3 | AP41: =AN41-AO41 -> 11 | AQ41: =IFERROR(NETWORKDAYS(AF41,AG41,Hoja1!$A$1:$A$29),"N/A") -> 10 | AR41: 6 | AS41: =AQ41-AR41 -> 4 | AT41: =IFERROR(NETWORKDAYS(D41,AG41,Hoja1!$A$1:$A$29),"N/A") -> 26 | AU41: =AT41-AO41-AR41 -> 17 | AV41: Busqueda directa | AW41: N/A
A42: 15348 | B42: MP | C42: MP | D42: 45985 | E42: 45982 | F42: Cali | G42: CALI | H42: VACANTE DESDE RECLUTAMIENTO | I42: AUXILIAR ADMISIONES | J42: AUXILIAR/OPERATIVO | K42: Alba Lucy Alape | L42: 1 | M42: Finalizado - Llego hasta contratacion | N42: 0000-00-00 | O42: 4 | P42: No | Q42: 45994 | R42: 46002 | S42: 4 | T42: 0000-00-00 | U42: 0000-00-00 | V42: 0000-00-00 | W42: 0000-00-00 | X42: 0000-00-00 | Y42: 0000-00-00 | Z42: 0000-00-00 | AA42: 2 | AB42: 2 | AC42: 0 | AD42: 46009 | AE42: 46009 | AF42: 46013 | AG42: 46024 | AH42: 46027 | AI42: =MONTH(AH42) -> 1 | AJ42: Yessica Yurani Mazo Arboleda | AK42: 20251027: Se activa reclutamiento sin Requi. 20251030: se envian 4 hv pte retro por gh. 20251112: gh solicita evaluar a Mayerlin Daian Carabali. Se programan pruebas. 20251119: Se confirma informe. 20251120: Gh solicita avanzar contratacion. 20251121: Se envia OC FI 01 DIC. 20251124: Mayerli desiste del proceso teniendo en cuenta que no le interesa la oferta por 4 horas. Se activa reclutamiento. 20251203: se envia 1 hv y se continua reclutamiento 4 h. 20251209: se envian 3 hv. Pte retro por gh. 20251211: gh solicita evaluar a Yessica Maso. Se programan pruebas. 20251218: se envia informe. gh solicita avanzar. 20251222: Se envia OC FI 05 ENE. | AL42: =IFERROR(S42/O42,"N/A") -> 1 | AM42: =IFERROR(NETWORKDAYS(D42,Q42,Hoja1!$A$1:$A$29),"N/A") -> 8 | AN42: =IFERROR(NETWORKDAYS(D42,AE42,Hoja1!$A$1:$A$29),"N/A") -> 18 | AO42: 0 | AP42: =AN42-AO42 -> 18 | AQ42: =IFERROR(NETWORKDAYS(AF42,AG42,Hoja1!$A$1:$A$29),"N/A") -> 8 | AR42: 3 | AS42: =AQ42-AR42 -> 5 | AT42: =IFERROR(NETWORKDAYS(D42,AG42,Hoja1!$A$1:$A$29),"N/A") -> 27 | AU42: =AT42-AO42-AR42 -> 24 | AV42: Computrabajo | AW42: Clinica Occidente | AX42: Candidato desiste
A43: 15364 | B43: MP | C43: MP | D43: 45995 | E43: 45983 | F43: Cali | G43: DIRECCION NACIONAL | H43: CONCURSO MIXTO | I43: EJECUTIVO(A) SERVICIO AL CLIENTE | J43: AUXILIAR/OPERATIVO | K43: Alba Lucy Alape | L43: 1 | M43: Finalizado - Llego hasta contratacion | N43: 0000-00-00 | O43: 4 | P43: Si | Q43: 46000 | R43: 46024 | S43: 4 | T43: 0000-00-00 | U43: 46002 | V43: 45979 | W43: 0000-00-00 | X43: 0000-00-00 | Y43: 0000-00-00 | Z43: 0000-00-00 | AA43: 2 | AB43: 1 | AC43: 0 | AD43: 46029 | AE43: 46029 | AF43: 46029 | AG43: 46044 | AH43: 46045 | AI43: =MONTH(AH43) -> 1 | AJ43: Monica Alejandra Sanchez Hurtado | AK43: 20251124: Se activa reclutamiento mixto. Se envia publicacion hasta el 30 Dic. 20251202: Se confirma filtro interno. 20251204: se realiza afinamiento y se modifica perfil. Se reactiva requerimiento. 20251209: Se envian 4 hv. Pte retro por gh. 20251215: Pte retro por gh. (2) 20251218: gh envia retro y solicita activar reclutamiento. 20251222: se envia 2 hv. pte retro por gh. 20260102: gh solicita evaluar a Sofia y Monica. Se programan pruebas. 20260107: Se envia informe de Monica y se envia OC FI 22 ENE. 20260108: Se detiene contratacion hasta tener aval del corpotativo. 20260121: se retoma contratacion. | AL43: =IFERROR(S43/O43,"N/A") -> 1 | AM43: =IFERROR(NETWORKDAYS(D43,Q43,Hoja1!$A$1:$A$29),"N/A") -> 3 | AN43: =IFERROR(NETWORKDAYS(D43,AE43,Hoja1!$A$1:$A$29),"N/A") -> 22 | AO43: 0 | AP43: =AN43-AO43 -> 22 | AQ43: =IFERROR(NETWORKDAYS(AF43,AG43,Hoja1!$A$1:$A$29),"N/A") -> 11 | AR43: 6 | AS43: =AQ43-AR43 -> 5 | AT43: =IFERROR(NETWORKDAYS(D43,AG43,Hoja1!$A$1:$A$29),"N/A") -> 32 | AU43: =AT43-AO43-AR43 -> 26 | AV43: Computrabajo | AW43: PLUSPREVENGO
A44: 15372 | B44: COOMEVA | C44: UCO | D44: 45985 | E44: 45985 | F44: Cali | G44: DIRECCION NACIONAL | H44: CONCURSO INTERNO | I44: AUXILIAR TALENTO y LIDERAZGO | J44: AUXILIAR/OPERATIVO | K44: Alba Lucy Alape | L44: 1 | M44: Finalizado - Llego hasta contratacion | N44: 0000-00-00 | O44: 0 | Q44: 0000-00-00 | R44: 0000-00-00 | S44: 0 | T44: 0000-00-00 | U44: 45985 | V44: 45669 | W44: 0000-00-00 | X44: 0000-00-00 | Y44: 0000-00-00 | Z44: 45995 | AA44: 1 | AB44: 1 | AC44: 0 | AD44: 46010 | AE44: 46007 | AF44: 46013 | AG44: 46024 | AH44: 46027 | AI44: =MONTH(AH44) -> 1 | AJ44: Valeria Cardona Velez | AK44: 20251124: Se activa reclutamiento mixto. 20251128: Se envia 3 hv reclutamiento externo. 20251201: Se confirma filtro interno. Pte retro por gh. 20251204: gh solicita programar pruebas a (Daniela Vidarte, Valeria Cardona, Isabella Sanchez, Juliana Sanchez, Angiee Rivas). Se programan pruebas. 20251208: gh informa que queda pendiente definir quien avanzar a evaluacion. 20251215: Pte retro por gh. 20251216: gh solicita evaluar y contratar a valeria Cardona FI 05 ENE. 20251219: Se envia informe. 20251222: Se envia OC FI 05 ENE. | AL44: =IFERROR(S44/O44,"N/A") -> N/A | AM44: =IFERROR(NETWORKDAYS(D44,Q44,Hoja1!$A$1:$A$29),"N/A") -> N/A | AN44: =IFERROR(NETWORKDAYS(D44,AE44,Hoja1!$A$1:$A$29),"N/A") -> 16 | AO44: 0 | AP44: =AN44-AO44 -> 16 | AQ44: =IFERROR(NETWORKDAYS(AF44,AG44,Hoja1!$A$1:$A$29),"N/A") -> 8 | AR44: 3 | AS44: =AQ44-AR44 -> 5 | AT44: =IFERROR(NETWORKDAYS(D44,AG44,Hoja1!$A$1:$A$29),"N/A") -> 27 | AU44: =AT44-AO44-AR44 -> 24 | AV44: Movimiento Interno | AW44: Coomeva
A45: 15378 | B45: COOMEVA | C45: GCGIA | D45: 45986 | E45: 45986 | F45: Caribe | G45: VALLEDUPAR | H45: VACANTE DESDE RECLUTAMIENTO | I45: APRENDIZ SENA | J45: ESTUDIANTE/APRENDIZ | K45: Sheylin Florez Saenz | L45: 1 | M45: Finalizado - Llego hasta contratacion | N45: 0000-00-00 | O45: 3 | P45: No | Q45: 45996 | R45: 45996 | S45: 3 | T45: 0000-00-00 | U45: 0000-00-00 | V45: 0000-00-00 | W45: 0000-00-00 | X45: 0000-00-00 | Y45: 0000-00-00 | Z45: 0000-00-00 | AA45: 1 | AB45: 1 | AC45: 0 | AD45: 46006 | AE45: 46006 | AF45: 46006 | AG45: 46022 | AH45: 46027 | AI45: =MONTH(AH45) -> 1 | AJ45: Laura Daniela Barros Vasquez | AK45: 20251125: Crean RQ. 20251128: Se comparte a GH dos candidatos Michel Ospino y Alexander Ramirez, los cuales seran entrevistados el 1/Dic. 20251201: Solicitan avanzar a evaluacion con Michel Ospino. 20251202: Candidata Michel Ospino desiste del proceso. Se retoma reclutamiento. 20251205: Se camparte candidata Laura Daniela Barros Vasquez y se agenda entrevista con JI para el 6/Dic. 20251206: JI solicita avanzar proceso evaluativo con la aprendiz Laura Daniela Barros Vasquez. 20251209: Se programan pruebas a candidata seleccionada Laura Daniela Barros Vasquez. 20251215: Se confirma proceso evaluativo favorable de candidata Laura Barros y dan aval para inicar EDS. 20251215: Se comparte Laura Daniela Barros Vasquez a EDS con FI 5/ene. 202251231: Se confirma contratacion de Laura Barroz Vasquez con FI. 05/01/2025. | AL45: =IFERROR(S45/O45,"N/A") -> 1 | AM45: =IFERROR(NETWORKDAYS(D45,Q45,Hoja1!$A$1:$A$29),"N/A") -> 9 | AN45: =IFERROR(NETWORKDAYS(D45,AE45,Hoja1!$A$1:$A$29),"N/A") -> 14 | AO45: 0 | AP45: =AN45-AO45 -> 14 | AQ45: =IFERROR(NETWORKDAYS(AF45,AG45,Hoja1!$A$1:$A$29),"N/A") -> 12 | AR45: 7 | AS45: =AQ45-AR45 -> 5 | AT45: =IFERROR(NETWORKDAYS(D45,AG45,Hoja1!$A$1:$A$29),"N/A") -> 25 | AU45: =AT45-AO45-AR45 -> 18 | AV45: Busqueda directa | AW45: N/A
A46: 15382 | B46: MP | C46: MP | D46: 45986 | E46: 45986 | F46: Cali | G46: DIRECCION NACIONAL | H46: EMPRESA ENVIA EL CANDIDATO | I46: ANALISTA NAL MERCADEO | J46: ANALISTA/PROFESIONAL/COORDINADOR | K46: Alba Lucy Alape | L46: 1 | M46: Finalizado - Llego hasta contratacion | N46: 0000-00-00 | O46: 0 | Q46: 0000-00-00 | R46: 0000-00-00 | S46: 0 | T46: 0000-00-00 | U46: 0000-00-00 | V46: 0000-00-00 | W46: 0000-00-00 | X46: 0000-00-00 | Y46: 0000-00-00 | Z46: 0000-00-00 | AA46: 2 | AB46: 1 | AC46: 0 | AD46: 46010 | AE46: 46010 | AF46: 46013 | AG46: 46024 | AH46: 46027 | AI46: =MONTH(AH46) -> 1 | AJ46: Ivanna Charlotte Sanchez Gonzalez | AK46: 20251125: activa requi para evaluar y contratar a Manuel Vasquez reclutado en la requi 15253. 20251128: se notifica novedad veritas. gh solicita programar entrevista. 20251201: Se notifica a gh que el concepto no es favorable. Se activa reclutamiento. 20251204: Se envian 3 hv. Pte retro por gh. 20251215: gh solicita evaluar a German, Brayan e Ivana (referida) para las 2 vacantes activas. Se programan pruebas. 20251219: Se confirma informe y se solicita avanzar contratacion con Ivanna. 20251222: Se envia OC FI 05 ENE. | AL46: =IFERROR(S46/O46,"N/A") -> N/A | AM46: =IFERROR(NETWORKDAYS(D46,Q46,Hoja1!$A$1:$A$29),"N/A") -> N/A | AN46: =IFERROR(NETWORKDAYS(D46,AE46,Hoja1!$A$1:$A$29),"N/A") -> 18 | AO46: 0 | AP46: =AN46-AO46 -> 18 | AQ46: =IFERROR(NETWORKDAYS(AF46,AG46,Hoja1!$A$1:$A$29),"N/A") -> 8 | AR46: 3 | AS46: =AQ46-AR46 -> 5 | AT46: =IFERROR(NETWORKDAYS(D46,AG46,Hoja1!$A$1:$A$29),"N/A") -> 26 | AU46: =AT46-AO46-AR46 -> 23 | AV46: Movimiento Interno | AW46: Coomeva
A47: 15385 | B47: BANCOOMEVA | C47: BANCOOMEVA | D47: 45988 | E47: 45987 | F47: Cali | G47: DIRECCION NACIONAL | H47: VACANTE DESDE RECLUTAMIENTO | I47: APRENDIZ SENA | J47: ESTUDIANTE/APRENDIZ | K47: Carolina Cordoba Betancourt | L47: 1 | M47: Finalizado - Llego hasta contratacion | N47: 0000-00-00 | O47: 5 | P47: No | Q47: 45994 | R47: 45994 | S47: 5 | T47: 0000-00-00 | U47: 0000-00-00 | V47: 0000-00-00 | W47: 0000-00-00 | X47: 0000-00-00 | Y47: 0000-00-00 | Z47: 0000-00-00 | AA47: 3 | AB47: 1 | AC47: 0 | AD47: 46034 | AE47: 46035 | AF47: 46036 | AG47: 46044 | AH47: 46045 | AI47: =MONTH(AH47) -> 1 | AJ47: Jesus Daniel Villamizar Montoya | AK47: 20251127: se inicia reclutamiento.20251203: Se envian a GH dos cv diana y Kimberly.20251212: GH solicita evaluar Diana y Kimberly.20251215: Candidatas en proceso con otra empresa, se activa reclutamiento.20251219: Se envian 3cv. 20251223: se envian pruebas de integridad a 3 estudiantes Andrea Tautas, jesus villamizar, Daylen Bolaños. 20260105: se envian a gh.20260109: Jesus aprobo proceso, se envia a GH para su filtro.20260112: Se carga evaluacion. 20260113: GH solicita avanzar con Jesus.20260114: se envia O.C con F.I 22 Enero.20260121: F.I 23 Enero por demora en carta de presentacion. | AL47: =IFERROR(S47/O47,"N/A") -> 1 | AM47: =IFERROR(NETWORKDAYS(D47,Q47,Hoja1!$A$1:$A$29),"N/A") -> 5 | AN47: =IFERROR(NETWORKDAYS(D47,AE47,Hoja1!$A$1:$A$29),"N/A") -> 30 | AO47: 15 | AP47: =AN47-AO47 -> 15 | AQ47: =IFERROR(NETWORKDAYS(AF47,AG47,Hoja1!$A$1:$A$29),"N/A") -> 7 | AR47: 2 | AS47: =AQ47-AR47 -> 5 | AT47: =IFERROR(NETWORKDAYS(D47,AG47,Hoja1!$A$1:$A$29),"N/A") -> 37 | AU47: =AT47-AO47-AR47 -> 20 | AV47: Bolsa de empleo Ins. Educativa | AW47: No aplica
A48: 15395 | B48: COOMEVA | C48: GCGIA | D48: 45987 | E48: 45987 | F48: Cali | G48: CALI | H48: VACANTE DESDE RECLUTAMIENTO | I48: ASESOR/A INTEGRAL | J48: CARGO COMERCIAL | K48: Susan Bermeo Saenz | L48: 1 | M48: Finalizado - Llego hasta contratacion | N48: 0000-00-00 | O48: 8 | P48: No | Q48: 45993 | R48: 45994 | S48: 8 | T48: 0000-00-00 | U48: 0000-00-00 | V48: 0000-00-00 | W48: 0000-00-00 | X48: 0000-00-00 | Y48: 0000-00-00 | Z48: 0000-00-00 | AA48: 1 | AB48: 1 | AC48: 0 | AD48: 46008 | AE48: 46008 | AF48: 46009 | AG48: 46024 | AH48: 46027 | AI48: =MONTH(AH48) -> 1 | AJ48: Daniela Concha Ospina | AK48: 20251126: Se inicia reclutamiento 20251202:Se enviaron 2 hojas de vida (Leidy Bocanegra, Catalina Yanguas) 20251203:El cliente cito a entrevista para el Viernes 5 Dic. 20251209:Se activo reclutamiento: Leidy no paso entrevista y Catalina Yanguas no se presento. 20251212:Se enviaro 3 hv Daniela Ramirez, Oscar Mendoza, Jean Paul Saa. 20251215: Se enviaron 3 hv mas Daniela Concha y Nicolas Perdomo. 20251215: El cliente cito a entrevista para el Martes 16. 20251216:Paso a pruebas Daniela Concha. 20251217:El cliente envio a contratar a Daniela Concha. 20251218:Se envio a contratacion con FI 5 Enero | AL48: =IFERROR(S48/O48,"N/A") -> 1 | AM48: =IFERROR(NETWORKDAYS(D48,Q48,Hoja1!$A$1:$A$29),"N/A") -> 5 | AN48: =IFERROR(NETWORKDAYS(D48,AE48,Hoja1!$A$1:$A$29),"N/A") -> 15 | AO48: 0 | AP48: =AN48-AO48 -> 15 | AQ48: =IFERROR(NETWORKDAYS(AF48,AG48,Hoja1!$A$1:$A$29),"N/A") -> 10 | AR48: 5 | AS48: =AQ48-AR48 -> 5 | AT48: =IFERROR(NETWORKDAYS(D48,AG48,Hoja1!$A$1:$A$29),"N/A") -> 25 | AU48: =AT48-AO48-AR48 -> 20 | AV48: Computrabajo | AW48: Banco BBVA
A49: 15402 | B49: COOMEVA | C49: GCGIA | D49: 46029 | E49: 45988 | F49: Cali | G49: CALI | H49: EMPRESA ENVIA EL CANDIDATO | I49: ESTUDIANTE EN PRACTICA | J49: ESTUDIANTE/APRENDIZ | K49: Susan Bermeo Saenz | L49: 1 | M49: Finalizado - Llego hasta contratacion | N49: 0000-00-00 | O49: 13 | P49: No | Q49: 45989 | R49: 45989 | S49: 13 | T49: 0000-00-00 | U49: 0000-00-00 | V49: 0000-00-00 | W49: 0000-00-00 | X49: 0000-00-00 | Y49: 0000-00-00 | Z49: 0000-00-00 | AA49: 3 | AB49: 1 | AC49: 0 | AD49: 46031 | AE49: 46031 | AF49: 46031 | AG49: 46043 | AH49: 46044 | AI49: =MONTH(AH49) -> 1 | AJ49: Catalina Gil Bedoya | AK49: 20251128:El lciente solicito reclutamiento en carreras Administrativas, mercadeo o Ingeniera Industrial. Se enviaron dos hojas de vida (Mateo Valencia y Karen Machado). El cliente solicito mas hojas de vida. 20251203:Se enviaron 5 hojas de vida (Carolina Narvaez, Genaro Hurtado, Jhon Morales, Cristina Alban, Shirley Valencia) (2) 20251209:El cliente envio a evaluar a Jhon Edward Morales y Shrley Valencia) se enviaron pruebas y se citaron a entrevista para el Jueves 11 DIC. (2) 20251210:Jhon Morales no paso prueba de integridad y Shirley no se presento a entrevista y tampoco contesta. Se le informo al cliente y se pidio retroalimentacion de los otros 5 estudiantes enviados. (5) 20251215:El cliente dio retroalimentación de cada uno de los practicantes y solicito reclutamiento. 20251216:Se enviaron 2 hv Emilsen Zañudo, Juan Daza. (3) 20251223:El cliente solicito mas reclutamiento. 20260107:Se enviaron 4 hv Angel Bermeo, Danna Sotelo, Giovanny Figueroa y Santiago Mendoza. El cliente envio a evaluar a Catalina Gil. 20260109:Se subio informe y se le inforno al cliente. El cliente envio a contratar a Catalina. Se envio con FI 22 de Ene. | AL49: =IFERROR(S49/O49,"N/A") -> 1 | AM49: =IFERROR(NETWORKDAYS(D49,Q49,Hoja1!$A$1:$A$29),"N/A") -> -26 | AN49: =IFERROR(NETWORKDAYS(D49,AE49,Hoja1!$A$1:$A$29),"N/A") -> 3 | AO49: 0 | AP49: =AN49-AO49 -> 3 | AQ49: =IFERROR(NETWORKDAYS(AF49,AG49,Hoja1!$A$1:$A$29),"N/A") -> 8 | AR49: 3 | AS49: =AQ49-AR49 -> 5 | AT49: =IFERROR(NETWORKDAYS(D49,AG49,Hoja1!$A$1:$A$29),"N/A") -> 10 | AU49: =AT49-AO49-AR49 -> 7 | AV49: Referido cliente | AW49: N/A | AX49: Prueba de Integridad
A50: 15406 | B50: FUNDACION COOMEVA | C50: FUNDACION COOMEVA | D50: 45989 | E50: 45989 | F50: Cali | G50: CALI | H50: CONCURSO INTERNO | I50: AUXILIAR REG SERV DESARROLLO EMP | J50: AUXILIAR/OPERATIVO | K50: Carolina Cordoba Betancourt | L50: 1 | M50: Finalizado - Llego hasta contratacion | N50: 0000-00-00 | O50: 0 | Q50: 0000-00-00 | R50: 0000-00-00 | S50: 0 | T50: 0000-00-00 | U50: 45993 | V50: 46001 | W50: 0000-00-00 | X50: 0000-00-00 | Y50: 0000-00-00 | Z50: 46017 | AA50: 3 | AB50: 3 | AC50: 0 | AD50: 46027 | AE50: 46029 | AF50: 46030 | AG50: 46037 | AH50: 46044 | AI50: =MONTH(AH50) -> 1 | AJ50: Rosa Daniela Mena Betancur | AK50: 20251128: Se envia a Reclutamiento. 20251201: Se envia para publicacion interna ( 2 Dic).20251204: Se envian de reclutamiento 4cv.20251210: se confirman candidatos internos a GH.20251216: se realiza seguimiento.20251216: candidatos seran entrevistados por lider el viernes 19 Dic.20251222: GH solicita aplicar prueba tecnica, pdt el envio de la prueba por lider.20251226: GH solicita evaluar sin prueba tecnica Victoria, Rosa, Ivan.20260105: evaluaciones en sf.20260107: GH informa enviar a contratacion Rosa Daniela.20260108: Se envia O.C con F.I 22 Enero. | AL50: =IFERROR(S50/O50,"N/A") -> N/A | AM50: =IFERROR(NETWORKDAYS(D50,Q50,Hoja1!$A$1:$A$29),"N/A") -> N/A | AN50: =IFERROR(NETWORKDAYS(D50,AE50,Hoja1!$A$1:$A$29),"N/A") -> 26 | AO50: 3 | AP50: =AN50-AO50 -> 23 | AQ50: =IFERROR(NETWORKDAYS(AF50,AG50,Hoja1!$A$1:$A$29),"N/A") -> 5 | AR50: 0 | AS50: =AQ50-AR50 -> 5 | AT50: =IFERROR(NETWORKDAYS(D50,AG50,Hoja1!$A$1:$A$29),"N/A") -> 31 | AU50: =AT50-AO50-AR50 -> 28 | AV50: Movimiento Interno | AW50: Coomeva GCGIA
A51: 15407 | B51: MP | C51: MP | D51: 45989 | E51: 45989 | F51: Bogota | G51: BOGOTA | H51: VACANTE DESDE RECLUTAMIENTO | I51: EJECUTIVO/A ATENCION INTEGRAL | J51: AUXILIAR/OPERATIVO | K51: Andrea Katherine Angel Moreno | L51: 1 | M51: Finalizado - Llego hasta contratacion | N51: 0000-00-00 | O51: 5 | P51: Si | Q51: 46002 | R51: 46002 | S51: 5 | T51: 0000-00-00 | U51: 0000-00-00 | V51: 0000-00-00 | W51: 0000-00-00 | X51: 0000-00-00 | Y51: 0000-00-00 | Z51: 0000-00-00 | AA51: 5 | AB51: 2 | AC51: 0 | AD51: 46009 | AE51: 46009 | AF51: 46009 | AG51: 46031 | AH51: 46035 | AI51: =MONTH(AH51) -> 1 | AJ51: Ginna Vanessa Rodriguez Bermudez | AK51: 20251128: Se activa reclutamiento, se programan entrevistas con JI 03Dic. 20251203: Candidato no favorales en entrevista. Se continua reclutamiento. 20251205: Se programan entrevistas con JI 11Dic. 20251211: Candidata seleccionada Ginna Vanesa Rodriguez Bermudez se solicitan documentos. 20251218: Se solicita ES candidata seleccionada fecha tentativa de ingreso 05Ene. 202251231: Se congela la contratación por directriz nacional. 20260105: Se recibe autorización para ingreso fecha tentativa de ingreso 13Ene. | AL51: =IFERROR(S51/O51,"N/A") -> 1 | AM51: =IFERROR(NETWORKDAYS(D51,Q51,Hoja1!$A$1:$A$29),"N/A") -> 9 | AN51: =IFERROR(NETWORKDAYS(D51,AE51,Hoja1!$A$1:$A$29),"N/A") -> 14 | AO51: 0 | AP51: =AN51-AO51 -> 14 | AQ51: =IFERROR(NETWORKDAYS(AF51,AG51,Hoja1!$A$1:$A$29),"N/A") -> 15 | AR51: 10 | AS51: =AQ51-AR51 -> 5 | AT51: =IFERROR(NETWORKDAYS(D51,AG51,Hoja1!$A$1:$A$29),"N/A") -> 28 | AU51: =AT51-AO51-AR51 -> 18 | AV51: Computrabajo | AW51: HOMI
A52: 15409 | B52: MP | C52: MP | D52: 45989 | E52: 45989 | F52: Medellin | G52: MEDELLIN | H52: VACANTE DESDE RECLUTAMIENTO | I52: EJECUTIVO/A AFILIACION CEM MP | J52: CARGO COMERCIAL | K52: Francy Giraldo Santos | L52: 1 | M52: Finalizado - Llego hasta contratacion | N52: 0000-00-00 | O52: 6 | P52: No | Q52: 46001 | R52: 46001 | S52: 6 | T52: 0000-00-00 | U52: 0000-00-00 | V52: 0000-00-00 | W52: 0000-00-00 | X52: 0000-00-00 | Y52: 0000-00-00 | Z52: 0000-00-00 | AA52: 2 | AB52: 2 | AC52: 0 | AD52: 46006 | AE52: 46006 | AF52: 46007 | AG52: 46024 | AH52: 46027 | AI52: =MONTH(AH52) -> 1 | AJ52: Vanesa Suarez Florez | AK52: 20251128: Se activa reclutamiento . 20251202: Se tiene programado AS para el 3 de diciembre . 20251204: Asistieron 4 candidatos pero ninguno continua a la siguiente fase. 20251209: Se tiene programado AS para el 10 de diciembre. 20251211: El cliente solicita evaluar 3 candidatos del AS realizado el dia anterior. 20251212: El candidato Sebastian Gil, se retira del proceso de seleccion. Y se procede a evaluar a Vanesa Suarez y Mariana Agudelo. 20251215: El proceso de entrevista de ambas candidatas es satisfactorio, pendiente de toma de decision del cliente . 20251216: El cliente solicita avanzar con Vanesa Suarez, si todo sale satisfactorio su ingreso seria el 5 de enero. 20251222: La candidata se encuentra en EM. 20251229: La candidata esta en recoleccion de documentos para firma de contrato. 20260102: La candidata firma contrato | AL52: =IFERROR(S52/O52,"N/A") -> 1 | AM52: =IFERROR(NETWORKDAYS(D52,Q52,Hoja1!$A$1:$A$29),"N/A") -> 8 | AN52: =IFERROR(NETWORKDAYS(D52,AE52,Hoja1!$A$1:$A$29),"N/A") -> 11 | AO52: 0 | AP52: =AN52-AO52 -> 11 | AQ52: =IFERROR(NETWORKDAYS(AF52,AG52,Hoja1!$A$1:$A$29),"N/A") -> 12 | AR52: 7 | AS52: =AQ52-AR52 -> 5 | AT52: =IFERROR(NETWORKDAYS(D52,AG52,Hoja1!$A$1:$A$29),"N/A") -> 23 | AU52: =AT52-AO52-AR52 -> 16 | AV52: Computrabajo | AW52: Banco Union
A53: 15415 | B53: COOMEVA EXPERIENCIA MEDICA | C53: COOMEVA EXPERIENCIA MEDICA | D53: 45987 | E53: 45992 | F53: Cali | G53: DIRECCION NACIONAL | H53: EMPRESA ENVIA EL CANDIDATO | I53: AUXILIAR NAL CENTRAL ASISTENCIAL | J53: SALUD/ASISTENCIAL | K53: Carolina Cordoba Betancourt | L53: 1 | M53: Finalizado - Llego hasta contratacion | N53: 0000-00-00 | O53: 0 | Q53: 0000-00-00 | R53: 0000-00-00 | S53: 0 | T53: 0000-00-00 | U53: 0000-00-00 | V53: 0000-00-00 | W53: 0000-00-00 | X53: 0000-00-00 | Y53: 0000-00-00 | Z53: 0000-00-00 | AA53: 1 | AB53: 1 | AC53: 0 | AD53: 45993 | AE53: 45993 | AF53: 45993 | AG53: 46017 | AH53: 46027 | AI53: =MONTH(AH53) -> 1 | AJ53: Danny Alejandro Castillo Muñoz | AK53: 20251201: GH solicita evalación Danny Castillo.20251202: se carga evaluación en SF. 20251202: Cliente solicita enviar a contratación, se envia O.C con F.I 10 de Dic.20251210: candidato no envio documentos completos, se corre ingreso para el 5 de Enero | AL53: =IFERROR(S53/O53,"N/A") -> N/A | AM53: =IFERROR(NETWORKDAYS(D53,Q53,Hoja1!$A$1:$A$29),"N/A") -> N/A | AN53: =IFERROR(NETWORKDAYS(D53,AE53,Hoja1!$A$1:$A$29),"N/A") -> 5 | AO53: 0 | AP53: =AN53-AO53 -> 5 | AQ53: =IFERROR(NETWORKDAYS(AF53,AG53,Hoja1!$A$1:$A$29),"N/A") -> 17 | AR53: 12 | AS53: =AQ53-AR53 -> 5 | AT53: =IFERROR(NETWORKDAYS(D53,AG53,Hoja1!$A$1:$A$29),"N/A") -> 21 | AU53: =AT53-AO53-AR53 -> 9 | AV53: Referido cliente | AW53: CRUE E.S.E CENTRO
A54: 15419 | B54: COOMEVA | C54: GCGIA | D54: 45992 | E54: 45992 | F54: Medellin | G54: MEDELLIN | H54: CONCURSO MIXTO | I54: COORDINADOR REG. CANAL DE GESTORES | J54: CARGO COMERCIAL | K54: Fredy Alejandro Villada Posada | L54: 1 | M54: No requiere contratacion - Finalizado | N54: 0000-00-00 | O54: 13 | P54: Si | Q54: 46003 | R54: 46003 | S54: 13 | T54: 0000-00-00 | U54: 0000-00-00 | V54: 0000-00-00 | W54: 0000-00-00 | X54: 0000-00-00 | Y54: 0000-00-00 | Z54: 0000-00-00 | AA54: 2 | AB54: 2 | AC54: 0 | AD54: 46028 | AE54: 46031 | AF54: 0000-00-00 | AG54: 46031 | AH54: 46031 | AI54: =MONTH(AH54) -> 1 | AJ54: Jhoan Andres Gomez Herrera | AK54: 20251201: se activa reclutamiento 20251209: se continua en reclutamiento ya que la convocatoria mixta está abierta hasta el 13 de dic 20251212: se comparten 5 HV de candidatos internos y 8 HV de candidatos externos. 20251229: Se realiza AS el dia de hoy y se selecciona los siguiente candidatos Andres Gomez y Juan Camilo Castrillo para proceso evaluativo 20260105: candidatos se encuentran en proceso evaluativo 20260106: se comparte la retroalimentacion de los dos candidatos, a la espera de respuesta del cliente 20260109: GH confirma que la persona a ingresar en dicha vacantes es Jhoan Andres Gomez | AL54: =IFERROR(S54/O54,"N/A") -> 1 | AM54: =IFERROR(NETWORKDAYS(D54,Q54,Hoja1!$A$1:$A$29),"N/A") -> 9 | AN54: =IFERROR(NETWORKDAYS(D54,AE54,Hoja1!$A$1:$A$29),"N/A") -> 27 | AO54: 5 | AP54: =AN54-AO54 -> 22 | AQ54: =IFERROR(NETWORKDAYS(AF54,AG54,Hoja1!$A$1:$A$29),"N/A") -> N/A | AR54: 0 | AS54: N/A | AT54: =IFERROR(NETWORKDAYS(D54,AG54,Hoja1!$A$1:$A$29),"N/A") -> 27 | AU54: =AT54-AO54-AR54 -> 22 | AV54: Movimiento Interno | AW54: Coomeva
A55: 15424 | B55: COOMEVA | C55: USC | D55: 45996 | E55: 45993 | F55: Cali | G55: DIRECCION NACIONAL | H55: CONCURSO MIXTO | I55: GESTOR/A OPERACIONES | J55: ANALISTA/PROFESIONAL/COORDINADOR | K55: Susan Bermeo Saenz | L55: 1 | M55: Finalizado - Llego hasta contratacion | N55: 0000-00-00 | O55: 4 | P55: No | Q55: 46008 | R55: 46015 | S55: 4 | T55: 0000-00-00 | U55: 46000 | V55: 46007 | W55: 0000-00-00 | X55: 0000-00-00 | Y55: 0000-00-00 | Z55: 0000-00-00 | AA55: 2 | AB55: 1 | AC55: 0 | AD55: 46036 | AE55: 46042 | AF55: 46042 | AG55: 46045 | AH55: 46045 | AI55: =MONTH(AH55) -> 1 | AJ55: Karen Vanessa Cedeño Causil | AK55: 20251202:El cliente solicito reclutamiento. 20251203: Se solicito el perfil porque no esta en coonectados. (4) 20251205:El cliente envio el perfil y se activa reclutamiento. 20251209:Se envio publicación para concurso mixto. 20251216:Se confirmo filtro interno. 20251217:Se enviaron 4 hv Alejandra Toro, Marco Banguera, Mayra Garcia y Adriana Morena recomendada por el lider. 20251224:Se solicito retroalimentacion. 20260201:Se volvio a solicitar retroalimentacion. (9) 20260106:El cliente envio a evaluar a Karen Cedeño, Diego Angel, Islena Castro y Carolina Sarasty. 20260108:El cliente informo que solo evaluaramos a Karen ya que es la persona que se encuentra actualmente desempeñando el cargo. 20260113: no se ha podido subir el informe ya que la candidata no ha realizado prueba midot. (1) 20260114:Se subio informe y se le informo al cliente. 20250115:El cliente envio a contrarar a Karen pero no se ha podido enviar ya que no tenemos correo de autorizacion. 20250120:El cliente pidido enviar a la candidata a EST y Examenes en simultaneo a la candidata mientras enviar autorización para la contratacion. Se envio con FI 23 de Ene. | AL55: =IFERROR(S55/O55,"N/A") -> 1 | AM55: =IFERROR(NETWORKDAYS(D55,Q55,Hoja1!$A$1:$A$29),"N/A") -> 8 | AN55: =IFERROR(NETWORKDAYS(D55,AE55,Hoja1!$A$1:$A$29),"N/A") -> 29 | AO55: 6 | AP55: =AN55-AO55 -> 23 | AQ55: =IFERROR(NETWORKDAYS(AF55,AG55,Hoja1!$A$1:$A$29),"N/A") -> 4 | AR55: 0 | AS55: =AQ55-AR55 -> 4 | AT55: =IFERROR(NETWORKDAYS(D55,AG55,Hoja1!$A$1:$A$29),"N/A") -> 32 | AU55: =AT55-AO55-AR55 -> 26 | AV55: Movimiento Interno | AW55: Coomeva Cooperativa
A56: 15426 | B56: MP | C56: MP | D56: 45993 | E56: 45993 | F56: Bogota | G56: BOGOTA | H56: VACANTE DESDE RECLUTAMIENTO | I56: EJECUTIVO/A AFILIACION | J56: CARGO COMERCIAL | K56: Andrea Katherine Angel Moreno | L56: 1 | M56: Finalizado - Llego hasta contratacion | N56: 0000-00-00 | O56: 6 | P56: No | Q56: 46009 | R56: 46009 | S56: 6 | T56: 0000-00-00 | U56: 0000-00-00 | V56: 0000-00-00 | W56: 0000-00-00 | X56: 0000-00-00 | Y56: 0000-00-00 | Z56: 0000-00-00 | AA56: 6 | AB56: 1 | AC56: 0 | AD56: 46009 | AE56: 46009 | AF56: 46027 | AG56: 46031 | AH56: 46035 | AI56: =MONTH(AH56) -> 1 | AJ56: Karen Eliana Lopez Moreno | AK56: 20251202: Se activa reclutamiento. 20251205: Se programan entrevistas con JI 11Dic. 20251211: Candidatos no favorables. Se programan entrevistas 18Dic. 20251218: Candidata seleccionada Karen Eliana López Moreno se solicitan documentos. 20251219: Candidata no ha podido recolectar documentos por tiempo de su trabajo actual. 20251223: Candidata indica esta en proceso de busqueda de documentos. 20251231: Candidata envia documentos pendiente diploma. 20260105: Se solicita ES candidata seleccionada fecha tentativa de ingreso 13Ene. | AL56: =IFERROR(S56/O56,"N/A") -> 1 | AM56: =IFERROR(NETWORKDAYS(D56,Q56,Hoja1!$A$1:$A$29),"N/A") -> 12 | AN56: =IFERROR(NETWORKDAYS(D56,AE56,Hoja1!$A$1:$A$29),"N/A") -> 12 | AO56: 0 | AP56: =AN56-AO56 -> 12 | AQ56: =IFERROR(NETWORKDAYS(AF56,AG56,Hoja1!$A$1:$A$29),"N/A") -> 5 | AR56: 0 | AS56: =AQ56-AR56 -> 5 | AT56: =IFERROR(NETWORKDAYS(D56,AG56,Hoja1!$A$1:$A$29),"N/A") -> 26 | AU56: =AT56-AO56-AR56 -> 26 | AV56: Computrabajo | AW56: Seguralia
A57: 15427 | B57: MP | C57: MP | D57: 46010 | E57: 45993 | F57: Bogota | G57: BOGOTA | H57: VACANTE DESDE RECLUTAMIENTO | I57: EJECUTIVO/A AFILIACION | J57: CARGO COMERCIAL | K57: Andrea Katherine Angel Moreno | L57: 1 | M57: Finalizado - Llego hasta contratacion | N57: 0000-00-00 | O57: 3 | P57: No | Q57: 46017 | R57: 46017 | S57: 3 | T57: 0000-00-00 | U57: 0000-00-00 | V57: 0000-00-00 | W57: 0000-00-00 | X57: 0000-00-00 | Y57: 0000-00-00 | Z57: 0000-00-00 | AA57: 3 | AB57: 1 | AC57: 0 | AD57: 46027 | AE57: 46027 | AF57: 46027 | AG57: 46031 | AH57: 46035 | AI57: =MONTH(AH57) -> 1 | AJ57: Daniel Avila Ponton | AK57: 20251203: Se activa reclutamiento. 20251210: Se realizan entrevistas con JI candidata seleccionada ANGELA JANNETH RIOS VALENZUELA se solicitan documentos. 20251216: Se solicita excepción de estudios. 20251218: Se solicita ES fecha tentativa de ingreso 05Ene. 20251219: Candidata no favorable en estudio de seguridad. Se activa reclutamiento. 20251222: Se programan entrevistas 26 Dic. 20251226: Candidato seleccionado Daniel Avila Pontón. Se solicitan documentos. 20251230: Candidato informa salio de la ciudad y no tiene los documentos a la mano. 20260105: Se solicita ES candidato seleccionado fecha tentativa de ingreso 13Ene. | AL57: =IFERROR(S57/O57,"N/A") -> 1 | AM57: =IFERROR(NETWORKDAYS(D57,Q57,Hoja1!$A$1:$A$29),"N/A") -> 5 | AN57: =IFERROR(NETWORKDAYS(D57,AE57,Hoja1!$A$1:$A$29),"N/A") -> 10 | AO57: 0 | AP57: =AN57-AO57 -> 10 | AQ57: =IFERROR(NETWORKDAYS(AF57,AG57,Hoja1!$A$1:$A$29),"N/A") -> 5 | AR57: 0 | AS57: =AQ57-AR57 -> 5 | AT57: =IFERROR(NETWORKDAYS(D57,AG57,Hoja1!$A$1:$A$29),"N/A") -> 14 | AU57: =AT57-AO57-AR57 -> 14 | AV57: Computrabajo | AW57: Medplus | AX57: Estudio de seguridad
A58: 15433 | B58: COOMEVA | C58: USC | D58: 45996 | E58: 45996 | F58: Cali | G58: CALI | H58: EMPRESA ENVIA EL CANDIDATO | I58: NEGOCIADOR/A | J58: ANALISTA/PROFESIONAL/COORDINADOR | K58: Susan Bermeo Saenz | L58: 1 | M58: Finalizado - Llego hasta contratacion | N58: 0000-00-00 | O58: 0 | Q58: 0000-00-00 | R58: 0000-00-00 | S58: 0 | T58: 0000-00-00 | U58: 0000-00-00 | V58: 0000-00-00 | W58: 0000-00-00 | X58: 0000-00-00 | Y58: 0000-00-00 | Z58: 0000-00-00 | AA58: 1 | AB58: 1 | AC58: 0 | AD58: 46009 | AE58: 46010 | AF58: 46010 | AG58: 46022 | AH58: 46027 | AI58: =MONTH(AH58) -> 1 | AJ58: Cindy Lorena Lopez Cespedes | AK58: 20251205: Llegó proceso y se le pregunto al cliente como se realizara este proceso si sera reclutamiento o enviaran a evaluar a una persona. 20251209:El cliente aun no responde. (4) 20251211:El cliente envio a evaluar a Cindy. se enviaron pruebas. se cito a entrevista para el Martes 15. 20251215:No se pudo entrevistar ya que se tuvo que ir, se reprogramo para el Miercoles 17. (1) 20251218:Se subio informe y se le informo al cliente. 20251219:El cliente solicito contratar a Cindy. Se envio a contratacion con FI 5 Enero. | AL58: =IFERROR(S58/O58,"N/A") -> N/A | AM58: =IFERROR(NETWORKDAYS(D58,Q58,Hoja1!$A$1:$A$29),"N/A") -> N/A | AN58: =IFERROR(NETWORKDAYS(D58,AE58,Hoja1!$A$1:$A$29),"N/A") -> 10 | AO58: 0 | AP58: =AN58-AO58 -> 10 | AQ58: =IFERROR(NETWORKDAYS(AF58,AG58,Hoja1!$A$1:$A$29),"N/A") -> 8 | AR58: 3 | AS58: =AQ58-AR58 -> 5 | AT58: =IFERROR(NETWORKDAYS(D58,AG58,Hoja1!$A$1:$A$29),"N/A") -> 17 | AU58: =AT58-AO58-AR58 -> 14 | AV58: Movimiento Interno | AW58: Coomeva Cooperativa
A59: 15434 | B59: MP | C59: MP | D59: 45994 | E59: 45994 | F59: Eje Cafetero | G59: MANIZALES | H59: VACANTE DESDE RECLUTAMIENTO | I59: EJECUTIVO/A AFILIACION | J59: CARGO COMERCIAL | K59: Natalia Aristizabal Tabares | L59: 1 | M59: Finalizado - Llego hasta contratacion | N59: 0000-00-00 | O59: 5 | P59: Si | Q59: 45996 | R59: 46001 | S59: 5 | T59: 0000-00-00 | U59: 0000-00-00 | V59: 0000-00-00 | W59: 0000-00-00 | X59: 0000-00-00 | Y59: 0000-00-00 | Z59: 0000-00-00 | AA59: 1 | AB59: 1 | AC59: 0 | AD59: 46009 | AE59: 46008 | AF59: 46009 | AG59: 46021 | AH59: 46027 | AI59: =MONTH(AH59) -> 1 | AJ59: Lady Viviana Ramos Montoya | AK59: 20251205: Se envian 5 HV: Fredy Alvaran, Luz Angela Vasquez, Lady Viviana Ramos, Mile Natalia Vasquez, Valentina Meza. 20251210: Se solicita aplicar prueba de servicio e integridad a Lady Viviana Ramos y Fredy Alvaran. 20251216: Pendiente definir candidato que avanza a contratación. 20251217: Se solicita avanzar con Lady Viviana Ramos para ingreo el 5 de enero. 20251218: Se envia informe, se solicita contratación. 20251230: La candidata firma contrato. *Descontar 4 dias en proces de contratación, por demora en completar documentos por parte de la candidata y finalizar contratación ya que la auxiliar estaba en vacaciones. | AL59: =IFERROR(S59/O59,"N/A") -> 1 | AM59: =IFERROR(NETWORKDAYS(D59,Q59,Hoja1!$A$1:$A$29),"N/A") -> 3 | AN59: =IFERROR(NETWORKDAYS(D59,AE59,Hoja1!$A$1:$A$29),"N/A") -> 10 | AO59: 0 | AP59: =AN59-AO59 -> 10 | AQ59: =IFERROR(NETWORKDAYS(AF59,AG59,Hoja1!$A$1:$A$29),"N/A") -> 8 | AR59: 3 | AS59: =AQ59-AR59 -> 5 | AT59: =IFERROR(NETWORKDAYS(D59,AG59,Hoja1!$A$1:$A$29),"N/A") -> 18 | AU59: =AT59-AO59-AR59 -> 15 | AV59: Otras redes | AW59: Seguros Bolivar
A60: 15436 | B60: COOMEVA | C60: UCO | D60: 45996 | E60: 45995 | F60: Cali | G60: DIRECCION NACIONAL | H60: VACANTE DESDE RECLUTAMIENTO | I60: APRENDIZ SENA | J60: ESTUDIANTE/APRENDIZ | K60: Alba Lucy Alape | L60: 1 | M60: Finalizado - Llego hasta contratacion | N60: 0000-00-00 | O60: 4 | P60: Si | Q60: 46007 | R60: 46028 | S60: 4 | T60: 0000-00-00 | U60: 0000-00-00 | V60: 0000-00-00 | W60: 0000-00-00 | X60: 0000-00-00 | Y60: 0000-00-00 | Z60: 0000-00-00 | AA60: 1 | AB60: 1 | AC60: 0 | AD60: 46030 | AE60: 46030 | AF60: 46031 | AG60: 46043 | AH60: 46044 | AI60: =MONTH(AH60) -> 1 | AJ60: Nikolle Palechor Acosta | AK60: 20251205: Se activa reclutamiento de Tecnologia en Mercadeo y Negocios Internacionales de Antonio Jose Camacho. 20251209: se envia reporte de la institucion camacho donde indica que no hay estudiantes disponibles. gh solicita validar con otras instituciones. 20251216: se envia 1 hv y se continua en reclutamiento. 20251219: Se envian 4 hv. Pte retro por gh.(3) 20251222: gh solicita el pensum de los aprendices. 20251223: Se envia informacion. Pte retro por gh.(4) 20260106:gh solicita evaluar a Nikole y Valery Palechor y solicita activar mas reclutamiento. 20260108: gh solicita avanzar contratacion con Nikole Palechor. 20250109: Se envia OC FI 22 Enero | AL60: =IFERROR(S60/O60,"N/A") -> 1 | AM60: =IFERROR(NETWORKDAYS(D60,Q60,Hoja1!$A$1:$A$29),"N/A") -> 7 | AN60: =IFERROR(NETWORKDAYS(D60,AE60,Hoja1!$A$1:$A$29),"N/A") -> 22 | AO60: 7 | AP60: =AN60-AO60 -> 15 | AQ60: =IFERROR(NETWORKDAYS(AF60,AG60,Hoja1!$A$1:$A$29),"N/A") -> 8 | AR60: 3 | AS60: =AQ60-AR60 -> 5 | AT60: =IFERROR(NETWORKDAYS(D60,AG60,Hoja1!$A$1:$A$29),"N/A") -> 30 | AU60: =AT60-AO60-AR60 -> 20 | AV60: Bolsa de empleo Ins. Educativa | AW60: NA
A61: 15441 | B61: COOMEVA | C61: USC | D61: 46006 | E61: 46000 | F61: Cali | G61: CALI | H61: VACANTE DESDE RECLUTAMIENTO | I61: TÉCNICO/A SEGURIDAD Y SALUD EN EL TRABAJO | J61: AUXILIAR/OPERATIVO | K61: Susan Bermeo Saenz | L61: 1 | M61: Finalizado - Llego hasta contratacion | N61: 0000-00-00 | O61: 3 | P61: Si | Q61: 46009 | R61: 46013 | S61: 3 | T61: 0000-00-00 | U61: 0000-00-00 | V61: 0000-00-00 | W61: 0000-00-00 | X61: 0000-00-00 | Y61: 0000-00-00 | Z61: 0000-00-00 | AA61: 3 | AB61: 2 | AC61: 0 | AD61: 46027 | AE61: 46029 | AF61: 46029 | AG61: 46044 | AH61: 46044 | AI61: =MONTH(AH61) -> 1 | AJ61: Yamileny Nañez Muñoz | AK61: 20251209: Se activa reclutamiento 20251211:El cliente envio a evaluar a Jenny Garces. 20251212:La candidata no paso prueba de integridad. 20251215:Se le pregunto al cliente como proceder, si tienen otra persona para evaluar o activamos reclutamiento. Sin Embargo se activa reclutamiento. (3) 20251218:Se enviaron 3 hojas de vida Yamileny Nañez, Daniela Garces, Juan Jose Castro. 20251218:El cliente envio a evaluar a un candidato Kevin Cordoba se enviaron pruebas. 20251224:Se solicito retroalimentacion. (2) 20251226: El cliente envio a evaluar a Yamileny, se enviaron pruebas y se cito a entrevista. 20260102: El candidato Kevin aun no ha terminado pruebas blue site por tal razon no se ha podido subir el informe. 20260105:Se subio informe de Kevin y se le informo al cliente. 20260106:Se subio informe de Yamileny y se le informo al cliente. 20260107:El cliente envio a contratar a Yamileni. Se envio a contratacion con FI 22 Ene. | AL61: =IFERROR(S61/O61,"N/A") -> 1 | AM61: =IFERROR(NETWORKDAYS(D61,Q61,Hoja1!$A$1:$A$29),"N/A") -> 4 | AN61: =IFERROR(NETWORKDAYS(D61,AE61,Hoja1!$A$1:$A$29),"N/A") -> 16 | AO61: 5 | AP61: =AN61-AO61 -> 11 | AQ61: =IFERROR(NETWORKDAYS(AF61,AG61,Hoja1!$A$1:$A$29),"N/A") -> 11 | AR61: 6 | AS61: =AQ61-AR61 -> 5 | AT61: =IFERROR(NETWORKDAYS(D61,AG61,Hoja1!$A$1:$A$29),"N/A") -> 26 | AU61: =AT61-AO61-AR61 -> 15 | AV61: Computrabajo | AW61: Proinsa | AX61: Prueba de Integridad
A62: 15443 | B62: COOMEVA | C62: UCO | D62: 45996 | E62: 45996 | F62: Cali | G62: DIRECCION NACIONAL | H62: SOLO CONTRATACION | I62: AUDITOR/A | J62: ANALISTA/PROFESIONAL/COORDINADOR | K62: Alba Lucy Alape | L62: 1 | M62: Finalizado - Llego hasta contratacion | N62: 0000-00-00 | O62: 0 | Q62: 0000-00-00 | R62: 0000-00-00 | S62: 0 | T62: 0000-00-00 | U62: 0000-00-00 | V62: 0000-00-00 | W62: 0000-00-00 | X62: 0000-00-00 | Y62: 0000-00-00 | Z62: 0000-00-00 | AA62: 1 | AB62: 1 | AC62: 0 | AD62: 0000-00-00 | AE62: 0000-00-00 | AF62: 46007 | AG62: 46024 | AH62: 46027 | AI62: =MONTH(AH62) -> 1 | AJ62: Paulin Tatiana Mesa Cardona | AK62: 20251205: gh solicita avanzar contratacion con Paulin Mesa quien fue evaluada en la requi 14634. Se solicitan documentos. 20251215: Paulin envia documentos. 20251216: Se envia OC FI 05 Enero. | AL62: =IFERROR(S62/O62,"N/A") -> N/A | AM62: =IFERROR(NETWORKDAYS(D62,Q62,Hoja1!$A$1:$A$29),"N/A") -> N/A | AN62: =IFERROR(NETWORKDAYS(D62,AE62,Hoja1!$A$1:$A$29),"N/A") -> N/A | AO62: 0 | AP62: N/A | AQ62: =IFERROR(NETWORKDAYS(AF62,AG62,Hoja1!$A$1:$A$29),"N/A") -> 12 | AR62: 7 | AS62: =AQ62-AR62 -> 5 | AT62: =IFERROR(NETWORKDAYS(D62,AG62,Hoja1!$A$1:$A$29),"N/A") -> 18 | AU62: =AT62-AO62-AR62 -> 11 | AV62: Movimiento Interno | AW62: Coomeva
A63: 15446 | B63: BANCOOMEVA | C63: BANCOOMEVA | D63: 45996 | E63: 45996 | F63: Cali | G63: BUGA | H63: EMPRESA ENVIA EL CANDIDATO | I63: ASESOR/A VENTAS | J63: CARGO COMERCIAL | K63: Carolina Cordoba Betancourt | L63: 1 | M63: Finalizado - Llego hasta contratacion | N63: 0000-00-00 | O63: 1 | Q63: 0000-00-00 | R63: 0000-00-00 | S63: 0 | T63: 0000-00-00 | U63: 0000-00-00 | V63: 0000-00-00 | W63: 0000-00-00 | X63: 0000-00-00 | Y63: 0000-00-00 | Z63: 0000-00-00 | AA63: 1 | AB63: 1 | AC63: 0 | AD63: 46007 | AE63: 46007 | AF63: 46008 | AG63: 46045 | AH63: 46048 | AI63: =MONTH(AH63) -> 1 | AJ63: Gina Paola Arias Corral | AK63: 20251205: GH solicita aplicar prueba de integridad. Gina. 20251210: GH solicita evaluar referida. 20251215: Evaluada candidata, GH solicita enviarla a contratacion.20251216: se carga evaluacion en SF. 20251217: Se envia O.C con F.I 22 Enero, fecha de ingreso se define de acuerdo a solicutd del cliente.20251231: rq detenido por instruccion del corporativo.20260121: uco autorizar activar contrataciones, se define F.I 26 Enero por solicitud de GH. | AL63: =IFERROR(S63/O63,"N/A") -> 0 | AM63: =IFERROR(NETWORKDAYS(D63,Q63,Hoja1!$A$1:$A$29),"N/A") -> N/A | AN63: =IFERROR(NETWORKDAYS(D63,AE63,Hoja1!$A$1:$A$29),"N/A") -> 7 | AO63: 0 | AP63: =AN63-AO63 -> 7 | AQ63: =IFERROR(NETWORKDAYS(AF63,AG63,Hoja1!$A$1:$A$29),"N/A") -> 25 | AR63: 20 | AS63: =AQ63-AR63 -> 5 | AT63: =IFERROR(NETWORKDAYS(D63,AG63,Hoja1!$A$1:$A$29),"N/A") -> 32 | AU63: =AT63-AO63-AR63 -> 12 | AV63: Referido cliente | AW63: Bancoomeva- Accion Plus
A64: 15451 | B64: MP | C64: MP | D64: 45994 | E64: 46000 | F64: Cali | G64: DIRECCION NACIONAL | H64: VACANTE DESDE RECLUTAMIENTO | I64: ESTUDIANTE EN PRACTICA | J64: ESTUDIANTE/APRENDIZ | K64: Alba Lucy Alape | L64: 1 | M64: Finalizado - Llego hasta contratacion | N64: 0000-00-00 | O64: 3 | P64: Si | Q64: 45996 | R64: 45999 | S64: 3 | T64: 0000-00-00 | U64: 0000-00-00 | V64: 0000-00-00 | W64: 0000-00-00 | X64: 0000-00-00 | Y64: 0000-00-00 | Z64: 0000-00-00 | AA64: 1 | AB64: 1 | AC64: 0 | AD64: 46001 | AE64: 46013 | AF64: 46013 | AG64: 46024 | AH64: 46027 | AI64: =MONTH(AH64) -> 1 | AJ64: Santiago Carabali Juanillo | AK64: 20251210: gh solicita evaluar a jefferson malpud y santiago carabali enviados el 13 de Nov en la requi 15240. Se programan pruebas. 20251212: se informa que Jeferson no pasa veritas y Santiago no ha realizado pruebas. 20251215: pte que santiago termine pruebas para avanzar proceso. 20251216: termina pruebas y se avanzar a evaluar. 20251222: Se confirma informe y se envia OC FI 05 ENE. | AL64: =IFERROR(S64/O64,"N/A") -> 1 | AM64: =IFERROR(NETWORKDAYS(D64,Q64,Hoja1!$A$1:$A$29),"N/A") -> 3 | AN64: =IFERROR(NETWORKDAYS(D64,AE64,Hoja1!$A$1:$A$29),"N/A") -> 13 | AO64: 0 | AP64: =AN64-AO64 -> 13 | AQ64: =IFERROR(NETWORKDAYS(AF64,AG64,Hoja1!$A$1:$A$29),"N/A") -> 8 | AR64: 3 | AS64: =AQ64-AR64 -> 5 | AT64: =IFERROR(NETWORKDAYS(D64,AG64,Hoja1!$A$1:$A$29),"N/A") -> 20 | AU64: =AT64-AO64-AR64 -> 17 | AV64: Bolsa de empleo Ins. Educativa | AW64: NA
A65: 15454 | B65: MP | C65: MP | D65: 46000 | E65: 46000 | F65: Medellin | G65: MEDELLIN | H65: VACANTE DESDE RECLUTAMIENTO | I65: EJECUTIVO/A AFILIACION CEM MP | J65: CARGO COMERCIAL | K65: Francy Giraldo Santos | L65: 1 | M65: Finalizado - Llego hasta contratacion | N65: 0000-00-00 | O65: 6 | P65: Si | Q65: 46002 | R65: 46002 | S65: 6 | T65: 0000-00-00 | U65: 0000-00-00 | V65: 0000-00-00 | W65: 0000-00-00 | X65: 0000-00-00 | Y65: 0000-00-00 | Z65: 0000-00-00 | AA65: 3 | AB65: 2 | AC65: 0 | AD65: 46007 | AE65: 46007 | AF65: 46008 | AG65: 46021 | AH65: 46027 | AI65: =MONTH(AH65) -> 1 | AJ65: Mariana Agudelo Tobon | AK65: 20251210: Se activa reclutamiento . 20251211:Se tiene AS 20251212: El candidato Sebastian Gil, se retira del proceso de seleccion. Y se procede a evaluar a Vanesa Suarez y Mariana Agudelo. 20251215: El proceso de entrevista de ambas candidatas es satisfactorio, pendiente de toma de decision del cliente . 20251216: El cliente solicita avanzar con Mariana Agudelo, si todo sale satisfactorio su ingreso seria el 5 de enero . 20251222: La candidata se encuentra en EM . 20251229: La candidata esta en apertura de cuenta. 20251230: La candidata firma contrato | AL65: =IFERROR(S65/O65,"N/A") -> 1 | AM65: =IFERROR(NETWORKDAYS(D65,Q65,Hoja1!$A$1:$A$29),"N/A") -> 3 | AN65: =IFERROR(NETWORKDAYS(D65,AE65,Hoja1!$A$1:$A$29),"N/A") -> 6 | AO65: 0 | AP65: =AN65-AO65 -> 6 | AQ65: =IFERROR(NETWORKDAYS(AF65,AG65,Hoja1!$A$1:$A$29),"N/A") -> 9 | AR65: 0 | AS65: =AQ65-AR65 -> 9 | AT65: =IFERROR(NETWORKDAYS(D65,AG65,Hoja1!$A$1:$A$29),"N/A") -> 15 | AU65: =AT65-AO65-AR65 -> 15 | AV65: Busqueda directa | AW65: EMI
A66: 15455 | B66: MP | C66: MP | D66: 46000 | E66: 46000 | F66: Medellin | G66: MEDELLIN | H66: VACANTE DESDE RECLUTAMIENTO | I66: EJECUTIVO/A AFILIACION CEM MP | J66: CARGO COMERCIAL | K66: Francy Giraldo Santos | L66: 1 | M66: Finalizado - Llego hasta contratacion | N66: 0000-00-00 | O66: 6 | P66: Si | Q66: 46007 | R66: 46007 | S66: 6 | T66: 0000-00-00 | U66: 0000-00-00 | V66: 0000-00-00 | W66: 0000-00-00 | X66: 0000-00-00 | Y66: 0000-00-00 | Z66: 0000-00-00 | AA66: 1 | AB66: 1 | AC66: 0 | AD66: 46008 | AE66: 46009 | AF66: 46009 | AG66: 46024 | AH66: 46027 | AI66: =MONTH(AH66) -> 1 | AJ66: Cindy Vanessa Gonzalez Perez | AK66: 20251215. Se tiene programado AS para el 16 de diciembre . 20251216: El cliente solicita avanzar con Vanesa Gonzalez. La cual sera evaluada de forma individual el dia 18 de diciembre . 20251222: Se envia concepto al cliente y es favorable a la espera del aval . 20251224: Se envia a contratacion a Vanessa Gonzalez con fecha de contratacion del 13 de enero. 20251229: La candidata esta en EM. 20260102: La candidata firma contrato | AL66: =IFERROR(S66/O66,"N/A") -> 1 | AM66: =IFERROR(NETWORKDAYS(D66,Q66,Hoja1!$A$1:$A$29),"N/A") -> 6 | AN66: =IFERROR(NETWORKDAYS(D66,AE66,Hoja1!$A$1:$A$29),"N/A") -> 8 | AO66: 0 | AP66: =AN66-AO66 -> 8 | AQ66: =IFERROR(NETWORKDAYS(AF66,AG66,Hoja1!$A$1:$A$29),"N/A") -> 10 | AR66: 5 | AS66: =AQ66-AR66 -> 5 | AT66: =IFERROR(NETWORKDAYS(D66,AG66,Hoja1!$A$1:$A$29),"N/A") -> 17 | AU66: =AT66-AO66-AR66 -> 12 | AV66: Computrabajo | AW66: Banco Union
A67: 15458 | B67: MP | C67: MP | D67: 46000 | E67: 46000 | F67: Medellin | G67: MEDELLIN | H67: VACANTE DESDE RECLUTAMIENTO | I67: EJECUTIVO/A AFILIACION CEM MP | J67: CARGO COMERCIAL | K67: Francy Giraldo Santos | L67: 1 | M67: Finalizado - Llego hasta contratacion | N67: 0000-00-00 | O67: 7 | P67: Si | Q67: 46014 | R67: 46014 | S67: 7 | T67: 0000-00-00 | U67: 0000-00-00 | V67: 0000-00-00 | W67: 0000-00-00 | X67: 0000-00-00 | Y67: 0000-00-00 | Z67: 0000-00-00 | AA67: 1 | AB67: 1 | AC67: 0 | AD67: 46017 | AE67: 46017 | AF67: 46017 | AG67: 46031 | AH67: 46035 | AI67: 1 | AJ67: Vanessa Mejia Lopez | AK67: 20251215. Se tiene programado AS para el 16 de diciembre 20251210: Se activa reclutamiento. 20251215. Se tiene programado AS para el 16 de diciembre .20251222: El AS pasado se selecciono una candidata la cual fue evaluada para otra RQ. Se tiene programado AS para el 23 de diciembre . 20251223: Se realiza AS y se selecciona para esta vacante Vanesa Mejia 20251224: Se program a proceso evaluativo con la candidata y es satisfactorio. 20251226: Se envia a proceso de contratacion con fecha del 13 de enero. 20251229. La candidata se encuentra en EM 20260107: candidata aprueba EM y se encuentra a la espera de autorizacion por parte de la nacional para apertura de cuenta y asociatividad. 20260109: La candidata firma contrat | AL67: =IFERROR(S67/O67,"N/A") -> 1 | AM67: =IFERROR(NETWORKDAYS(D67,Q67,Hoja1!$A$1:$A$29),"N/A") -> 11 | AN67: =IFERROR(NETWORKDAYS(D67,AE67,Hoja1!$A$1:$A$29),"N/A") -> 13 | AO67: 0 | AP67: =AN67-AO67 -> 13 | AQ67: =IFERROR(NETWORKDAYS(AF67,AG67,Hoja1!$A$1:$A$29),"N/A") -> 10 | AR67: 5 | AS67: =AQ67-AR67 -> 5 | AT67: =IFERROR(NETWORKDAYS(D67,AG67,Hoja1!$A$1:$A$29),"N/A") -> 22 | AU67: =AT67-AO67-AR67 -> 17 | AV67: Computrabajo | AW67: Emermedica
A68: 15463 | B68: COOMEVA | C68: GCGIA | D68: 45978 | E68: 46001 | F68: Bogota | G68: BOGOTA | H68: VACANTE DESDE RECLUTAMIENTO | I68: ASESOR/A EN LOGISTICA | J68: AUXILIAR/OPERATIVO | K68: Paola Andrea Molano Malaver | L68: 1 | M68: Finalizado - Llego hasta contratacion | N68: 0000-00-00 | O68: 8 | P68: Si | Q68: 45988 | R68: 45988 | S68: 8 | T68: 0000-00-00 | U68: 0000-00-00 | V68: 0000-00-00 | W68: 0000-00-00 | X68: 0000-00-00 | Y68: 0000-00-00 | Z68: 0000-00-00 | AA68: 4 | AB68: 1 | AC68: 0 | AD68: 46007 | AE68: 46007 | AF68: 46007 | AG68: 46024 | AH68: 46027 | AI68: =MONTH(AH68) -> 1 | AJ68: Edwar Estivens Murcia Valbuena | AK68: 20251212: Se inicia reclutamiento, 20251215: El cliente solicita dar continuidad con el candidato que había quedado en back up de otro proceso previo, Edwar Estivens Murcia Valbuena. 20251216: Se solicita continuar con la OC para ingreso el 05 De enero | AL68: =IFERROR(S68/O68,"N/A") -> 1 | AM68: =IFERROR(NETWORKDAYS(D68,Q68,Hoja1!$A$1:$A$29),"N/A") -> 8 | AN68: =IFERROR(NETWORKDAYS(D68,AE68,Hoja1!$A$1:$A$29),"N/A") -> 20 | AO68: 0 | AP68: =AN68-AO68 -> 20 | AQ68: =IFERROR(NETWORKDAYS(AF68,AG68,Hoja1!$A$1:$A$29),"N/A") -> 12 | AR68: 6 | AS68: =AQ68-AR68 -> 6 | AT68: =IFERROR(NETWORKDAYS(D68,AG68,Hoja1!$A$1:$A$29),"N/A") -> 31 | AU68: =AT68-AO68-AR68 -> 25 | AV68: Computrabajo | AW68: Adistec Colombia
A69: 15464 | B69: MP | C69: MP | D69: 46001 | E69: 46001 | F69: Bogota | G69: BOGOTA | H69: VACANTE DESDE RECLUTAMIENTO | I69: EJECUTIVO/A AFILIACION CEM MP | J69: CARGO COMERCIAL | K69: Andrea Katherine Angel Moreno | L69: 1 | M69: Finalizado - Llego hasta contratacion | N69: 0000-00-00 | O69: 7 | P69: Si | Q69: 46006 | R69: 46006 | S69: 7 | T69: 0000-00-00 | U69: 0000-00-00 | V69: 0000-00-00 | W69: 0000-00-00 | X69: 0000-00-00 | Y69: 0000-00-00 | Z69: 0000-00-00 | AA69: 7 | AB69: 3 | AC69: 0 | AD69: 46009 | AE69: 46009 | AF69: 46009 | AG69: 46024 | AH69: 46027 | AI69: =MONTH(AH69) -> 1 | AJ69: Juan Carlos Santana Poveda | AK69: 20251211: Se activa reclutamiento. 20251215: Se realizan entrevistas con JI candidato seleccionado Juan Carlos Santana Poveda se solicitan documentos. 20251218: Se solicita ES candidato seleccionado fecha tentativa de ingreso 05Ene. | AL69: =IFERROR(S69/O69,"N/A") -> 1 | AM69: =IFERROR(NETWORKDAYS(D69,Q69,Hoja1!$A$1:$A$29),"N/A") -> 4 | AN69: =IFERROR(NETWORKDAYS(D69,AE69,Hoja1!$A$1:$A$29),"N/A") -> 7 | AO69: 0 | AP69: =AN69-AO69 -> 7 | AQ69: =IFERROR(NETWORKDAYS(AF69,AG69,Hoja1!$A$1:$A$29),"N/A") -> 10 | AR69: 5 | AS69: =AQ69-AR69 -> 5 | AT69: =IFERROR(NETWORKDAYS(D69,AG69,Hoja1!$A$1:$A$29),"N/A") -> 16 | AU69: =AT69-AO69-AR69 -> 11 | AV69: Computrabajo | AW69: Salud Total
A70: 15466 | B70: MP | C70: MP | D70: 46001 | E70: 46001 | F70: Bogota | G70: BOGOTA | H70: VACANTE DESDE RECLUTAMIENTO | I70: EJECUTIVO/A AFILIACION CEM MP | J70: CARGO COMERCIAL | K70: Andrea Katherine Angel Moreno | L70: 1 | M70: Finalizado - Llego hasta contratacion | N70: 0000-00-00 | O70: 7 | P70: Si | Q70: 46006 | R70: 46006 | S70: 7 | T70: 0000-00-00 | U70: 0000-00-00 | V70: 0000-00-00 | W70: 0000-00-00 | X70: 0000-00-00 | Y70: 0000-00-00 | Z70: 0000-00-00 | AA70: 7 | AB70: 3 | AC70: 0 | AD70: 46027 | AE70: 46027 | AF70: 46027 | AG70: 46031 | AH70: 46035 | AI70: =MONTH(AH70) -> 1 | AJ70: Geraldine Yareli Galiano Contreras | AK70: 20251211: Se activa reclutamiento. 20251215: Se realizan entrevistas con JI candidata seleccionada GERALDINE YARELI GALIANO CONTRERAS se solicitan documentos. 20251218: Se le indica a candidata documentos pendientes. 20251222: Candidata indica se le ha dificultado encontrar el diploma. Informa en horas de la tarde lo envia. 20251226: Candidata no ha podido conseguir el diploma indica ya lo solicito en la institución tiempo de entrega aproximado de 3 a 5 días habiles. 20260105: Se solicita ES candidata seleccionada GERALDINE YARELI GALIANO CONTRERAS fecha tentativa de ingreso 13Ene. ** Se descuentan 10 dias al proceso de selección por demora en entrega de documentos por parte de la candidata** | AL70: =IFERROR(S70/O70,"N/A") -> 1 | AM70: =IFERROR(NETWORKDAYS(D70,Q70,Hoja1!$A$1:$A$29),"N/A") -> 4 | AN70: =IFERROR(NETWORKDAYS(D70,AE70,Hoja1!$A$1:$A$29),"N/A") -> 17 | AO70: 10 | AP70: =AN70-AO70 -> 7 | AQ70: =IFERROR(NETWORKDAYS(AF70,AG70,Hoja1!$A$1:$A$29),"N/A") -> 5 | AR70: 0 | AS70: =AQ70-AR70 -> 5 | AT70: =IFERROR(NETWORKDAYS(D70,AG70,Hoja1!$A$1:$A$29),"N/A") -> 21 | AU70: =AT70-AO70-AR70 -> 11 | AV70: Computrabajo | AW70: SIES SALUD
A71: 15467 | B71: MP | C71: MP | D71: 46001 | E71: 46001 | F71: Bogota | G71: BOGOTA | H71: VACANTE DESDE RECLUTAMIENTO | I71: EJECUTIVO/A AFILIACION CEM MP | J71: CARGO COMERCIAL | K71: Andrea Katherine Angel Moreno | L71: 1 | M71: Finalizado - Llego hasta contratacion | N71: 0000-00-00 | O71: 7 | P71: Si | Q71: 46006 | R71: 46006 | S71: 7 | T71: 0000-00-00 | U71: 0000-00-00 | V71: 0000-00-00 | W71: 0000-00-00 | X71: 0000-00-00 | Y71: 0000-00-00 | Z71: 0000-00-00 | AA71: 7 | AB71: 3 | AC71: 0 | AD71: 46009 | AE71: 46009 | AF71: 46009 | AG71: 46031 | AH71: 46035 | AI71: =MONTH(AH71) -> 1 | AJ71: Sandra Yineth Ruiz Montealegre | AK71: 20251211: Se activa reclutamiento. 20251215: Se realizan entrevistas con JI candidata seleccionada SANDRA RUIZ. Se solicitan documentos. 20251218: Se solicita ES candidata seleccionada fecha tentativa de ingreso 05Ene. 20251231: Se congela contratación por directriz nacional. 20260105: Se recibe autorización de ingreso fecha tentativa 13Ene. | AL71: =IFERROR(S71/O71,"N/A") -> 1 | AM71: =IFERROR(NETWORKDAYS(D71,Q71,Hoja1!$A$1:$A$29),"N/A") -> 4 | AN71: =IFERROR(NETWORKDAYS(D71,AE71,Hoja1!$A$1:$A$29),"N/A") -> 7 | AO71: 0 | AP71: =AN71-AO71 -> 7 | AQ71: =IFERROR(NETWORKDAYS(AF71,AG71,Hoja1!$A$1:$A$29),"N/A") -> 15 | AR71: 10 | AS71: =AQ71-AR71 -> 5 | AT71: =IFERROR(NETWORKDAYS(D71,AG71,Hoja1!$A$1:$A$29),"N/A") -> 21 | AU71: =AT71-AO71-AR71 -> 11 | AV71: Computrabajo | AW71: DACA TECNOLOGÍ
A72: 15471 | B72: MP | C72: MP | D72: 45996 | E72: 45973 | F72: Caribe | G72: BARRANQUILLA | H72: VACANTE DESDE RECLUTAMIENTO | I72: EJECUTIVO/A AFILIACION CEM MP | J72: CARGO COMERCIAL | K72: Norma Elena Achkar Mansour | L72: 1 | M72: Finalizado - Llego hasta contratacion | N72: 0000-00-00 | O72: 1 | P72: Si | Q72: 46000 | R72: 46000 | S72: 1 | T72: 0000-00-00 | U72: 0000-00-00 | V72: 0000-00-00 | W72: 0000-00-00 | X72: 0000-00-00 | Y72: 0000-00-00 | Z72: 0000-00-00 | AA72: 1 | AB72: 1 | AC72: 0 | AD72: 46010 | AE72: 46010 | AF72: 46010 | AG72: 46017 | AH72: 46027 | AI72: =MONTH(AH72) -> 1 | AJ72: Zarina Paola Diaz Cabarcas | AK72: 20251211: Crean Rq. y piden evaluar a Zaria Díaz, quien viene en BackUP desde el 13/Nov. 20251212: Se comparte registo evaluativo y se avanza EDS con Zarina. 20250126: Se confirma contratación de la colaboradora Zarina Paola Díaz Cabarcas, con FI. 05/01/2026. | AL72: =IFERROR(S72/O72,"N/A") -> 1 | AM72: =IFERROR(NETWORKDAYS(D72,Q72,Hoja1!$A$1:$A$29),"N/A") -> 2 | AN72: =IFERROR(NETWORKDAYS(D72,AE72,Hoja1!$A$1:$A$29),"N/A") -> 10 | AO72: 0 | AP72: =AN72-AO72 -> 10 | AQ72: =IFERROR(NETWORKDAYS(AF72,AG72,Hoja1!$A$1:$A$29),"N/A") -> 5 | AR72: 0 | AS72: =AQ72-AR72 -> 5 | AT72: =IFERROR(NETWORKDAYS(D72,AG72,Hoja1!$A$1:$A$29),"N/A") -> 14 | AU72: =AT72-AO72-AR72 -> 14 | AV72: Computrabajo | AW72: GRUPO RECORDAR
A73: 15472 | B73: MP | C73: MP | D73: 45996 | E73: 45973 | F73: Caribe | G73: BARRANQUILLA | H73: VACANTE DESDE RECLUTAMIENTO | I73: EJECUTIVO/A AFILIACION CEM MP | J73: CARGO COMERCIAL | K73: Norma Elena Achkar Mansour | L73: 1 | M73: Finalizado - Llego hasta contratacion | N73: 0000-00-00 | O73: 1 | P73: Si | Q73: 46000 | R73: 46000 | S73: 1 | T73: 0000-00-00 | U73: 0000-00-00 | V73: 0000-00-00 | W73: 0000-00-00 | X73: 0000-00-00 | Y73: 0000-00-00 | Z73: 0000-00-00 | AA73: 1 | AB73: 1 | AC73: 0 | AD73: 46010 | AE73: 46010 | AF73: 46010 | AG73: 46024 | AH73: 46027 | AI73: =MONTH(AH73) -> 1 | AJ73: Astrid Carolina Fontalvo Gutierrez | AK73: 20251211: Crean RQ. 20251216: Solicitan evaluar a la candidata Astrid Fontalvo, quien viene del reclutamiento en la RQ 15432 desde el 05/Dic. 20251219: Se comparte proceso evaluativo y se avanza con EDS. 20251226: Candidata en apertura de cuenta, 20260102: Se confirma contratación de la colaboradora Astrid Carolina Fontalvo Gutierrez, con FI. 05/01/2026. | AL73: =IFERROR(S73/O73,"N/A") -> 1 | AM73: =IFERROR(NETWORKDAYS(D73,Q73,Hoja1!$A$1:$A$29),"N/A") -> 2 | AN73: =IFERROR(NETWORKDAYS(D73,AE73,Hoja1!$A$1:$A$29),"N/A") -> 10 | AO73: 0 | AP73: =AN73-AO73 -> 10 | AQ73: =IFERROR(NETWORKDAYS(AF73,AG73,Hoja1!$A$1:$A$29),"N/A") -> 9 | AR73: 5 | AS73: =AQ73-AR73 -> 4 | AT73: =IFERROR(NETWORKDAYS(D73,AG73,Hoja1!$A$1:$A$29),"N/A") -> 18 | AU73: =AT73-AO73-AR73 -> 13 | AV73: Computrabajo | AW73: PROTECCION
A74: 15475 | B74: BANCOOMEVA | C74: BANCOOMEVA | D74: 46002 | E74: 46002 | F74: Cali | G74: DIRECCION NACIONAL | H74: EMPRESA ENVIA EL CANDIDATO | I74: ANALISTA MTTO CUENTAS | J74: ANALISTA/PROFESIONAL/COORDINADOR | K74: Carolina Cordoba Betancourt | L74: 1 | M74: Finalizado - Llego hasta contratacion | N74: 0000-00-00 | O74: 0 | Q74: 0000-00-00 | R74: 0000-00-00 | S74: 0 | T74: 0000-00-00 | U74: 0000-00-00 | V74: 0000-00-00 | W74: 0000-00-00 | X74: 0000-00-00 | Y74: 0000-00-00 | Z74: 0000-00-00 | AA74: 1 | AB74: 1 | AC74: 0 | AD74: 46008 | AE74: 46013 | AF74: 46013 | AG74: 46044 | AH74: 46045 | AI74: =MONTH(AH74) -> 1 | AJ74: Miguel Antonio Villarraga Rico | AK74: 20251212: GH envia cv para evaluacion Miguel Villarraga.20251217: Se carga evaluación en SF. 20251222: GH solicita contratación. se envia O.C con F.I 05 Enero.20251231: rq detenido por instruccion del corporativo.20260121: uco autorizar activar contrataciones, se define F.I 23 Enero. | AL74: =IFERROR(S74/O74,"N/A") -> N/A | AM74: =IFERROR(NETWORKDAYS(D74,Q74,Hoja1!$A$1:$A$29),"N/A") -> N/A | AN74: =IFERROR(NETWORKDAYS(D74,AE74,Hoja1!$A$1:$A$29),"N/A") -> 8 | AO74: 0 | AP74: =AN74-AO74 -> 8 | AQ74: =IFERROR(NETWORKDAYS(AF74,AG74,Hoja1!$A$1:$A$29),"N/A") -> 21 | AR74: 16 | AS74: =AQ74-AR74 -> 5 | AT74: =IFERROR(NETWORKDAYS(D74,AG74,Hoja1!$A$1:$A$29),"N/A") -> 28 | AU74: =AT74-AO74-AR74 -> 12 | AV74: Referido cliente | AW74: Corficolombiana
A75: 15480 | B75: MP | C75: MP | D75: 46000 | E75: 46003 | F75: Bogota | G75: BOGOTA | H75: VACANTE DESDE RECLUTAMIENTO | I75: EJECUTIVO/A AFILIACION | J75: CARGO COMERCIAL | K75: Andrea Katherine Angel Moreno | L75: 1 | M75: Finalizado - Llego hasta contratacion | N75: 0000-00-00 | O75: 3 | P75: Si | Q75: 46007 | R75: 46007 | S75: 3 | T75: 0000-00-00 | U75: 0000-00-00 | V75: 0000-00-00 | W75: 0000-00-00 | X75: 0000-00-00 | Y75: 0000-00-00 | Z75: 0000-00-00 | AA75: 3 | AB75: 1 | AC75: 0 | AD75: 46010 | AE75: 46010 | AF75: 46010 | AG75: 46031 | AH75: 46035 | AI75: =MONTH(AH75) -> 1 | AJ75: Sergio Andres Diaz Llanos | AK75: 0251209: Se activa reclutamiento. 20251216: Se activa backup Sergio Andres Diaz. Se solicitan documentos. 20251218: Candidato indica se le ha dificultado conseguir el diploma pero esta en tramite. 20251219: Se solicita ES candidato seleccionado Sergio Andres Diaz. Fecha tentativa de ingreso 05Ene. 20251231: Se congela contratación por directriz nacional. 20260105: Se recibe autorización de ingreso fecha tentativa 13Ene. | AL75: =IFERROR(S75/O75,"N/A") -> 1 | AM75: =IFERROR(NETWORKDAYS(D75,Q75,Hoja1!$A$1:$A$29),"N/A") -> 6 | AN75: =IFERROR(NETWORKDAYS(D75,AE75,Hoja1!$A$1:$A$29),"N/A") -> 9 | AO75: 0 | AP75: =AN75-AO75 -> 9 | AQ75: =IFERROR(NETWORKDAYS(AF75,AG75,Hoja1!$A$1:$A$29),"N/A") -> 14 | AR75: 9 | AS75: =AQ75-AR75 -> 5 | AT75: =IFERROR(NETWORKDAYS(D75,AG75,Hoja1!$A$1:$A$29),"N/A") -> 22 | AU75: =AT75-AO75-AR75 -> 13 | AV75: Computrabajo | AW75: Salud Total
A76: 15484 | B76: COOMEVA EXPERIENCIA MEDICA | C76: COOMEVA EXPERIENCIA MEDICA | D76: 46006 | E76: 46006 | F76: Cali | G76: DIRECCION NACIONAL | H76: VACANTE DESDE RECLUTAMIENTO | I76: APRENDIZ SENA | J76: ESTUDIANTE/APRENDIZ | K76: Carolina Cordoba Betancourt | L76: 1 | M76: Finalizado - Llego hasta contratacion | N76: 0000-00-00 | O76: 6 | P76: No | Q76: 46031 | R76: 46031 | S76: 6 | T76: 0000-00-00 | U76: 0000-00-00 | V76: 0000-00-00 | W76: 0000-00-00 | X76: 0000-00-00 | Y76: 0000-00-00 | Z76: 0000-00-00 | AA76: 1 | AB76: 1 | AC76: 0 | AD76: 46036 | AE76: 46036 | AF76: 46036 | AG76: 46043 | AH76: 46044 | AI76: =MONTH(AH76) -> 1 | AJ76: Andrea Lorena Tautas Eraso | AK76: 20251215: GH crea RQ. 20251215: GH solicita continuar con Valentina, pdt que termine pruebas psico y envie documentos.20251215: solicita reclutamiento preventivo.20251223: se envian 3cv.20261229: No aprobaron proceso se activa reclutamiento. 20261229: GH solicita evaluar Jonathan David.20260106: No aprobo proceso Joonathan veritas R3, Se activa reclutamiento.20260109: se envian 1cv.20260114: GH informa evaluar a adnrea Tautas y hacer proceso simultaneo con contratación, se carga evaluacion en sf. 20260115 se envia OC con F.I 22Enero. | AL76: =IFERROR(S76/O76,"N/A") -> 1 | AM76: =IFERROR(NETWORKDAYS(D76,Q76,Hoja1!$A$1:$A$29),"N/A") -> 18 | AN76: =IFERROR(NETWORKDAYS(D76,AE76,Hoja1!$A$1:$A$29),"N/A") -> 20 | AO76: 5 | AP76: =AN76-AO76 -> 15 | AQ76: =IFERROR(NETWORKDAYS(AF76,AG76,Hoja1!$A$1:$A$29),"N/A") -> 6 | AR76: 1 | AS76: =AQ76-AR76 -> 5 | AT76: =IFERROR(NETWORKDAYS(D76,AG76,Hoja1!$A$1:$A$29),"N/A") -> 25 | AU76: =AT76-AO76-AR76 -> 19 | AV76: Bolsa de empleo Ins. Educativa | AW76: No aplica
A77: 15488 | B77: COOMEVA | C77: GCGIA | D77: 46015 | E77: 46006 | F77: Cali | G77: IBAGUE | H77: EMPRESA ENVIA EL CANDIDATO | I77: ASESOR/A INTEGRAL | J77: CARGO COMERCIAL | K77: Susan Bermeo Saenz | L77: 1 | M77: Finalizado - Llego hasta contratacion | N77: 0000-00-00 | O77: 3 | P77: No | Q77: 46013 | R77: 46013 | S77: 3 | T77: 0000-00-00 | U77: 0000-00-00 | V77: 0000-00-00 | W77: 0000-00-00 | X77: 0000-00-00 | Y77: 0000-00-00 | Z77: 0000-00-00 | AA77: 1 | AB77: 1 | AC77: 0 | AD77: 46027 | AE77: 46028 | AF77: 46028 | AG77: 46044 | AH77: 46045 | AI77: =MONTH(AH77) -> 1 | AJ77: Daniela Andrea Perez Sanchez | AK77: 20251215:Se activo reclutamiento. 20251222:Se enviaron 3 hv Ana Maria Gonzalez, Edinson Guillen y Vanessa Reyes. Se citaron a entrevista para el miercoles 24, tambien se cito a canddiata enviada por el lide. Daniela Perez. (8) 20251224: Ana Maria y Vanessa no se conectaron a entrevista. Edison no paso entrevista y se enviaron pruebas a Daniela. 20260102: Daniela aun no ha terminado pruebas, por tal razon no se ha podido subir el informe. (3) 20260105:Se subio informe y se le informo al cliente. 20260106:El cliente envio a contratar a Daniela. Se envio a contratacion con FI 22 de Ene. | AL77: =IFERROR(S77/O77,"N/A") -> 1 | AM77: =IFERROR(NETWORKDAYS(D77,Q77,Hoja1!$A$1:$A$29),"N/A") -> -3 | AN77: =IFERROR(NETWORKDAYS(D77,AE77,Hoja1!$A$1:$A$29),"N/A") -> 8 | AO77: 0 | AP77: =AN77-AO77 -> 8 | AQ77: =IFERROR(NETWORKDAYS(AF77,AG77,Hoja1!$A$1:$A$29),"N/A") -> 12 | AR77: 7 | AS77: =AQ77-AR77 -> 5 | AT77: =IFERROR(NETWORKDAYS(D77,AG77,Hoja1!$A$1:$A$29),"N/A") -> 19 | AU77: =AT77-AO77-AR77 -> 12 | AV77: Movimiento Interno | AW77: Coomeva Cooperativa
A78: 15493 | B78: BANCOOMEVA | C78: BANCOOMEVA | D78: 46006 | E78: 46006 | F78: Cali | G78: DIRECCION NACIONAL | H78: EMPRESA ENVIA EL CANDIDATO | I78: INGENIERO/A TREN SOLUCIONES I | J78: ANALISTA/PROFESIONAL/COORDINADOR | K78: Carolina Cordoba Betancourt | L78: 1 | M78: Finalizado - Llego hasta contratacion | N78: 0000-00-00 | O78: 0 | Q78: 0000-00-00 | R78: 0000-00-00 | S78: 0 | T78: 0000-00-00 | U78: 0000-00-00 | V78: 0000-00-00 | W78: 0000-00-00 | X78: 0000-00-00 | Y78: 0000-00-00 | Z78: 0000-00-00 | AA78: 1 | AB78: 1 | AC78: 0 | AD78: 46009 | AE78: 46010 | AF78: 46013 | AG78: 46024 | AH78: 46027 | AI78: =MONTH(AH78) -> 1 | AJ78: Willington Diaz Diaz | AK78: 20251215: GH envia a evalucion y contratación de Willington Diaz.20251218: se carga evaluacion en SF. 20251219: Enviar a contratacion. 20251222: se envia OC con F.I 05 Enero. | AL78: =IFERROR(S78/O78,"N/A") -> N/A | AM78: =IFERROR(NETWORKDAYS(D78,Q78,Hoja1!$A$1:$A$29),"N/A") -> N/A | AN78: =IFERROR(NETWORKDAYS(D78,AE78,Hoja1!$A$1:$A$29),"N/A") -> 5 | AO78: 0 | AP78: =AN78-AO78 -> 5 | AQ78: =IFERROR(NETWORKDAYS(AF78,AG78,Hoja1!$A$1:$A$29),"N/A") -> 8 | AR78: 3 | AS78: =AQ78-AR78 -> 5 | AT78: =IFERROR(NETWORKDAYS(D78,AG78,Hoja1!$A$1:$A$29),"N/A") -> 13 | AU78: =AT78-AO78-AR78 -> 10 | AV78: Referido cliente | AW78: KATA SOFTWARE
A79: 15500 | B79: MP | C79: MP | D79: 45992 | E79: 46007 | F79: Medellin | G79: BUCARAMANGA | H79: VACANTE DESDE RECLUTAMIENTO | I79: EJECUTIVO/A AFILIACION | J79: CARGO COMERCIAL | K79: Francy Giraldo Santos | L79: 1 | M79: Finalizado - Llego hasta contratacion | N79: 0000-00-00 | O79: 1 | P79: Si | Q79: 46007 | R79: 46007 | S79: 1 | T79: 0000-00-00 | U79: 0000-00-00 | V79: 0000-00-00 | W79: 0000-00-00 | X79: 0000-00-00 | Y79: 0000-00-00 | Z79: 0000-00-00 | AA79: 1 | AB79: 1 | AC79: 0 | AD79: 46009 | AE79: 46009 | AF79: 46009 | AG79: 46024 | AH79: 46027 | AI79: =MONTH(AH79) -> 1 | AJ79: Daira Nayary Davila Suarez | AK79: 20251216: Se activa proceso. Se tenia una persona en back-up de una proceso en el mes de Octubre. Se avanza proceso evaluativo Daira Nayari Suarez. 20251218: Se envia a la candidata a contratación | AL79: =IFERROR(S79/O79,"N/A") -> 1 | AM79: =IFERROR(NETWORKDAYS(D79,Q79,Hoja1!$A$1:$A$29),"N/A") -> 11 | AN79: =IFERROR(NETWORKDAYS(D79,AE79,Hoja1!$A$1:$A$29),"N/A") -> 13 | AO79: 0 | AP79: =AN79-AO79 -> 13 | AQ79: =IFERROR(NETWORKDAYS(AF79,AG79,Hoja1!$A$1:$A$29),"N/A") -> 10 | AR79: 4 | AS79: =AQ79-AR79 -> 6 | AT79: =IFERROR(NETWORKDAYS(D79,AG79,Hoja1!$A$1:$A$29),"N/A") -> 22 | AU79: =AT79-AO79-AR79 -> 18 | AV79: Computrabajo | AW79: Seguros Bolivar
A80: 15506 | B80: MP | C80: MP | D80: 46007 | E80: 46007 | F80: Cali | G80: CALI | H80: EMPRESA ENVIA EL CANDIDATO | I80: EJECUTIVO/A ATENCION INTEGRAL | J80: AUXILIAR/OPERATIVO | K80: Alba Lucy Alape | L80: 1 | M80: Finalizado - Llego hasta contratacion | N80: 0000-00-00 | O80: 0 | Q80: 0000-00-00 | R80: 0000-00-00 | S80: 0 | T80: 0000-00-00 | U80: 0000-00-00 | V80: 0000-00-00 | W80: 0000-00-00 | X80: 0000-00-00 | Y80: 0000-00-00 | Z80: 0000-00-00 | AA80: 1 | AB80: 1 | AC80: 0 | AD80: 46013 | AE80: 46013 | AF80: 46013 | AG80: 46024 | AH80: 46027 | AI80: =MONTH(AH80) -> 1 | AJ80: Lina Marcela Pava Mercado | AK80: 20251216: GH solicita evaluar y contratar a Lina Marcela Pava Mercado. Se programan pruebas. 20251222: se confirma informe y se envia OC FI 05 ENE. | AL80: =IFERROR(S80/O80,"N/A") -> N/A | AM80: =IFERROR(NETWORKDAYS(D80,Q80,Hoja1!$A$1:$A$29),"N/A") -> N/A | AN80: =IFERROR(NETWORKDAYS(D80,AE80,Hoja1!$A$1:$A$29),"N/A") -> 5 | AO80: 0 | AP80: =AN80-AO80 -> 5 | AQ80: =IFERROR(NETWORKDAYS(AF80,AG80,Hoja1!$A$1:$A$29),"N/A") -> 8 | AR80: 3 | AS80: =AQ80-AR80 -> 5 | AT80: =IFERROR(NETWORKDAYS(D80,AG80,Hoja1!$A$1:$A$29),"N/A") -> 12 | AU80: =AT80-AO80-AR80 -> 9 | AV80: Referido cliente | AW80: ASMET SALUD
A81: 15507 | B81: MP | C81: MP | D81: 46010 | E81: 46015 | F81: Caribe | G81: BARRANQUILLA | H81: VACANTE DESDE RECLUTAMIENTO | I81: EJECUTIVO/A AFILIACION CEM MP | J81: CARGO COMERCIAL | K81: Sheylin Florez Saenz | L81: 1 | M81: Finalizado - Llego hasta contratacion | N81: 0000-00-00 | O81: 1 | P81: Si | Q81: 46013 | R81: 46013 | S81: 1 | T81: 0000-00-00 | U81: 0000-00-00 | V81: 0000-00-00 | W81: 0000-00-00 | X81: 0000-00-00 | Y81: 0000-00-00 | Z81: 0000-00-00 | AA81: 1 | AB81: 1 | AC81: 0 | AD81: 45959 | AE81: 46027 | AF81: 46027 | AG81: 46031 | AH81: 46035 | AI81: =MONTH(AH81) -> 1 | AJ81: Lizeth Valencia Romero | AK81: 20251224: Asignan RQ. Se inicia reclutamiento.20251029: Solicitan EDS para la candidata Lizeth Valencia Romero, quien viene de la RQ 15473. 20260105: Congelena contrataciones - Se avanza con EDS para la candidata porque GH pide aval para contratar al 13/Ene. 20260109: Se confirma contratación de la colaboradora Lizeth Valencia Romero, con FI. 13/01/2026. | AL81: =IFERROR(S81/O81,"N/A") -> 1 | AM81: =IFERROR(NETWORKDAYS(D81,Q81,Hoja1!$A$1:$A$29),"N/A") -> 2 | AN81: =IFERROR(NETWORKDAYS(D81,AE81,Hoja1!$A$1:$A$29),"N/A") -> 10 | AO81: 0 | AP81: =AN81-AO81 -> 10 | AQ81: =IFERROR(NETWORKDAYS(AF81,AG81,Hoja1!$A$1:$A$29),"N/A") -> 5 | AR81: 1 | AS81: =AQ81-AR81 -> 4 | AT81: =IFERROR(NETWORKDAYS(D81,AG81,Hoja1!$A$1:$A$29),"N/A") -> 14 | AU81: =AT81-AO81-AR81 -> 13 | AV81: Computrabajo | AW81: POSTOBON SA
A82: 15513 | B82: MP | C82: MP | D82: 46007 | E82: 46007 | F82: Cali | G82: CALI | H82: EMPRESA ENVIA EL CANDIDATO | I82: EJECUTIVO/A ATENCION INTEGRAL | J82: AUXILIAR/OPERATIVO | K82: Alba Lucy Alape | L82: 1 | M82: Finalizado - Llego hasta contratacion | N82: 0000-00-00 | O82: 0 | Q82: 0000-00-00 | R82: 0000-00-00 | S82: 0 | T82: 0000-00-00 | U82: 0000-00-00 | V82: 0000-00-00 | W82: 0000-00-00 | X82: 0000-00-00 | Y82: 0000-00-00 | Z82: 0000-00-00 | AA82: 1 | AB82: 1 | AC82: 0 | AD82: 46013 | AE82: 46013 | AF82: 46013 | AG82: 46024 | AH82: 46027 | AI82: =MONTH(AH82) -> 1 | AJ82: Laura Estefania Romero Rosas | AK82: 20251216: GH solicita evaluar y contratar a Laura Estefania Romero Rosas. Se programan pruebas. 20251222: se confirma informe y se envia OC FI 05 ENE. | AL82: =IFERROR(S82/O82,"N/A") -> N/A | AM82: =IFERROR(NETWORKDAYS(D82,Q82,Hoja1!$A$1:$A$29),"N/A") -> N/A | AN82: =IFERROR(NETWORKDAYS(D82,AE82,Hoja1!$A$1:$A$29),"N/A") -> 5 | AO82: 0 | AP82: =AN82-AO82 -> 5 | AQ82: =IFERROR(NETWORKDAYS(AF82,AG82,Hoja1!$A$1:$A$29),"N/A") -> 8 | AR82: 3 | AS82: =AQ82-AR82 -> 5 | AT82: =IFERROR(NETWORKDAYS(D82,AG82,Hoja1!$A$1:$A$29),"N/A") -> 12 | AU82: =AT82-AO82-AR82 -> 9 | AV82: Referido cliente | AW82: COOSEGURIDAD
A83: 15514 | B83: MP | C83: MP | D83: 46008 | E83: 46007 | F83: Cali | G83: CALI | H83: EMPRESA ENVIA EL CANDIDATO | I83: EJECUTIVO/A ATENCION INTEGRAL | J83: AUXILIAR/OPERATIVO | K83: Alba Lucy Alape | L83: 1 | M83: Finalizado - Llego hasta contratacion | N83: 0000-00-00 | O83: 0 | Q83: 0000-00-00 | R83: 0000-00-00 | S83: 0 | T83: 0000-00-00 | U83: 0000-00-00 | V83: 0000-00-00 | W83: 0000-00-00 | X83: 0000-00-00 | Y83: 0000-00-00 | Z83: 0000-00-00 | AA83: 1 | AB83: 1 | AC83: 0 | AD83: 46013 | AE83: 46013 | AF83: 46013 | AG83: 46031 | AH83: 46035 | AI83: =MONTH(AH83) -> 1 | AJ83: Roosvelt Andres Cisco Epe | AK83: 20251217: GH solicita evaluar y contratar a Roosvelth Cisco Epe. Se programan pruebas. 20251222: se confirma informe y se envia OC FI 05 ENE. 20251231: Se informa a gh que candidato tiene producto en mora con la cooperativa. pte aval para avanzar contrata/. DESCONTAR 8 DIAS por que el candidato tenia un producto en mora con la cooperativa y por ello se corrio la contratacion hasta tener el aval para contratacion | AL83: =IFERROR(S83/O83,"N/A") -> N/A | AM83: =IFERROR(NETWORKDAYS(D83,Q83,Hoja1!$A$1:$A$29),"N/A") -> N/A | AN83: =IFERROR(NETWORKDAYS(D83,AE83,Hoja1!$A$1:$A$29),"N/A") -> 4 | AO83: 0 | AP83: =AN83-AO83 -> 4 | AQ83: =IFERROR(NETWORKDAYS(AF83,AG83,Hoja1!$A$1:$A$29),"N/A") -> 13 | AR83: 8 | AS83: =AQ83-AR83 -> 5 | AT83: =IFERROR(NETWORKDAYS(D83,AG83,Hoja1!$A$1:$A$29),"N/A") -> 16 | AU83: =AT83-AO83-AR83 -> 8 | AV83: Referido cliente | AW83: ANGIOGRAFIA DE OCCIDENTE
A84: 15524 | B84: MP | C84: MP | D84: 46001 | E84: 46008 | F84: Bogota | G84: BOGOTA | H84: VACANTE DESDE RECLUTAMIENTO | I84: EJECUTIVO/A ATENCION INTEGRAL | J84: AUXILIAR/OPERATIVO | K84: Andrea Katherine Angel Moreno | L84: 1 | M84: Finalizado - Llego hasta contratacion | N84: 0000-00-00 | O84: 5 | P84: Si | Q84: 46008 | R84: 46008 | S84: 5 | T84: 0000-00-00 | U84: 0000-00-00 | V84: 0000-00-00 | W84: 0000-00-00 | X84: 0000-00-00 | Y84: 0000-00-00 | Z84: 0000-00-00 | AA84: 5 | AB84: 2 | AC84: 0 | AD84: 46009 | AE84: 46009 | AF84: 46009 | AG84: 46031 | AH84: 46035 | AI84: =MONTH(AH84) -> 1 | AJ84: Aura Maria Urrutia Saavedra | AK84: 20251217: Se activa reclutamiento, se reactiva backup AURA MARIA URRUTIA SAAVEDRA se solicitan documentos. 20251218: Se solicita ES candidato seleccionado fecha tentativa de ingreso 05Ene. 20251231: Se congela contratación por directriz nacional. 20260105: Se recibe autorizaciónd e ingreso fecha tentativa de ingreso 13Ene. | AL84: =IFERROR(S84/O84,"N/A") -> 1 | AM84: =IFERROR(NETWORKDAYS(D84,Q84,Hoja1!$A$1:$A$29),"N/A") -> 6 | AN84: =IFERROR(NETWORKDAYS(D84,AE84,Hoja1!$A$1:$A$29),"N/A") -> 7 | AO84: 0 | AP84: =AN84-AO84 -> 7 | AQ84: =IFERROR(NETWORKDAYS(AF84,AG84,Hoja1!$A$1:$A$29),"N/A") -> 15 | AR84: 10 | AS84: =AQ84-AR84 -> 5 | AT84: =IFERROR(NETWORKDAYS(D84,AG84,Hoja1!$A$1:$A$29),"N/A") -> 21 | AU84: =AT84-AO84-AR84 -> 11 | AV84: Computrabajo | AW84: Colmédica
A85: 15528 | B85: MP | C85: MP | D85: 46001 | E85: 46008 | F85: Cali | G85: CALI | H85: EMPRESA ENVIA EL CANDIDATO | I85: AUXILIAR ADMISIONES | J85: AUXILIAR/OPERATIVO | K85: Alba Lucy Alape | L85: 1 | M85: Finalizado - Llego hasta contratacion | N85: 0000-00-00 | O85: 0 | Q85: 0000-00-00 | R85: 0000-00-00 | S85: 0 | T85: 0000-00-00 | U85: 0000-00-00 | V85: 0000-00-00 | W85: 0000-00-00 | X85: 0000-00-00 | Y85: 0000-00-00 | Z85: 0000-00-00 | AA85: 1 | AB85: 1 | AC85: 0 | AD85: 46009 | AE85: 46009 | AF85: 46013 | AG85: 46024 | AH85: 46027 | AI85: =MONTH(AH85) -> 1 | AJ85: Valentina Cruz Ceron | AK85: 20251204: se activa reclutamiento sin requi. 20251209: Se envian 10 hv. 20251210: gh solicita evaluar a Valentina Cruz (referida). Se programan pruebas. 20251217: se envia requi. 20251218: se envia informe y gh solicita avanzar. 20251222: Se envia OC FI 05 ENE. | AL85: =IFERROR(S85/O85,"N/A") -> N/A | AM85: =IFERROR(NETWORKDAYS(D85,Q85,Hoja1!$A$1:$A$29),"N/A") -> N/A | AN85: =IFERROR(NETWORKDAYS(D85,AE85,Hoja1!$A$1:$A$29),"N/A") -> 7 | AO85: 0 | AP85: =AN85-AO85 -> 7 | AQ85: =IFERROR(NETWORKDAYS(AF85,AG85,Hoja1!$A$1:$A$29),"N/A") -> 8 | AR85: 3 | AS85: =AQ85-AR85 -> 5 | AT85: =IFERROR(NETWORKDAYS(D85,AG85,Hoja1!$A$1:$A$29),"N/A") -> 16 | AU85: =AT85-AO85-AR85 -> 13 | AV85: Movimiento Interno | AW85: Coomeva
A86: 15529 | B86: MP | C86: MP | D86: 45995 | E86: 46008 | F86: Cali | G86: CALI | H86: VACANTE DESDE RECLUTAMIENTO | I86: AUXILIAR ADMISIONES | J86: AUXILIAR/OPERATIVO | K86: Alba Lucy Alape | L86: 1 | M86: Finalizado - Llego hasta contratacion | N86: 0000-00-00 | O86: 4 | P86: Si | Q86: 46000 | R86: 46002 | S86: 4 | T86: 0000-00-00 | U86: 0000-00-00 | V86: 0000-00-00 | W86: 0000-00-00 | X86: 0000-00-00 | Y86: 0000-00-00 | Z86: 0000-00-00 | AA86: 1 | AB86: 1 | AC86: 0 | AD86: 46009 | AE86: 46009 | AF86: 46013 | AG86: 46024 | AH86: 46027 | AI86: =MONTH(AH86) -> 1 | AJ86: Valentina Burbano Machin | AK86: 20251204: se activa reclutamiento sin requi. 20251209: Se envian 10 hv. 20251211: gh solicita evaluar a Valentina Burbano. Se programan pruebas. 20251217: se envia requi. 20251218: se envia informe y gh solicita avanzar. 20251222: Se envia OC FI 05 ENE. | AL86: =IFERROR(S86/O86,"N/A") -> 1 | AM86: =IFERROR(NETWORKDAYS(D86,Q86,Hoja1!$A$1:$A$29),"N/A") -> 3 | AN86: =IFERROR(NETWORKDAYS(D86,AE86,Hoja1!$A$1:$A$29),"N/A") -> 10 | AO86: 0 | AP86: =AN86-AO86 -> 10 | AQ86: =IFERROR(NETWORKDAYS(AF86,AG86,Hoja1!$A$1:$A$29),"N/A") -> 8 | AR86: 3 | AS86: =AQ86-AR86 -> 5 | AT86: =IFERROR(NETWORKDAYS(D86,AG86,Hoja1!$A$1:$A$29),"N/A") -> 19 | AU86: =AT86-AO86-AR86 -> 16 | AV86: Computrabajo | AW86: IPS HORISOES
A87: 15530 | B87: MP | C87: MP | D87: 45995 | E87: 46008 | F87: Cali | G87: CALI | H87: VACANTE DESDE RECLUTAMIENTO | I87: AUXILIAR ADMISIONES | J87: AUXILIAR/OPERATIVO | K87: Alba Lucy Alape | L87: 1 | M87: Finalizado - Llego hasta contratacion | N87: 0000-00-00 | O87: 4 | P87: Si | Q87: 46000 | R87: 46002 | S87: 4 | T87: 0000-00-00 | U87: 0000-00-00 | V87: 0000-00-00 | W87: 0000-00-00 | X87: 0000-00-00 | Y87: 0000-00-00 | Z87: 0000-00-00 | AA87: 1 | AB87: 1 | AC87: 0 | AD87: 46009 | AE87: 46009 | AF87: 46013 | AG87: 46024 | AH87: 46027 | AI87: =MONTH(AH87) -> 1 | AJ87: Maycol Fernando Cordoba Lozada | AK87: 20251204: se activa reclutamiento sin requi. 20251209: Se envian 10 hv. 20251211: gh solicita evaluar a Michael Cordoba. Se programan pruebas. 20251217: se envia requi. 20251218: se envia informe y gh solicita avanzar. 20251222: Se envia OC FI 05 ENE. | AL87: =IFERROR(S87/O87,"N/A") -> 1 | AM87: =IFERROR(NETWORKDAYS(D87,Q87,Hoja1!$A$1:$A$29),"N/A") -> 3 | AN87: =IFERROR(NETWORKDAYS(D87,AE87,Hoja1!$A$1:$A$29),"N/A") -> 10 | AO87: 0 | AP87: =AN87-AO87 -> 10 | AQ87: =IFERROR(NETWORKDAYS(AF87,AG87,Hoja1!$A$1:$A$29),"N/A") -> 8 | AR87: 3 | AS87: =AQ87-AR87 -> 5 | AT87: =IFERROR(NETWORKDAYS(D87,AG87,Hoja1!$A$1:$A$29),"N/A") -> 19 | AU87: =AT87-AO87-AR87 -> 16 | AV87: Computrabajo | AW87: HOSPITAL UNIVERSITARIO DEL VALLE
A88: 15533 | B88: MP | C88: MP | D88: 46008 | E88: 46008 | F88: Cali | G88: CALI | H88: EMPRESA ENVIA EL CANDIDATO | I88: AUXILIAR IMAGENES DIAGNOSTICAS | J88: SALUD/ASISTENCIAL | K88: Alba Lucy Alape | L88: 1 | M88: Finalizado - Llego hasta contratacion | N88: 0000-00-00 | O88: 0 | Q88: 0000-00-00 | R88: 0000-00-00 | S88: 0 | T88: 0000-00-00 | U88: 0000-00-00 | V88: 0000-00-00 | W88: 0000-00-00 | X88: 0000-00-00 | Y88: 0000-00-00 | Z88: 0000-00-00 | AA88: 1 | AB88: 1 | AC88: 0 | AD88: 46010 | AE88: 46010 | AF88: 46013 | AG88: 46024 | AH88: 46027 | AI88: =MONTH(AH88) -> 1 | AJ88: Daniela Salazar Mosquera | AK88: 20251204: se activa solicitud, pte envio de perfil para activar reclutamiento. 20251211: se envia perfil y se activa reclutamiento. 20251217: se envian 2 hv. pte retro por gh. Ese mismo dia gh solicita evaluar y contratar a Daniela Salazar (referida). Se programan pruebas. 20251219: Se confirma informe y gh solicita avanzar contratacion. 20251222: Se envia OC FI 05 ENE. | AL88: =IFERROR(S88/O88,"N/A") -> N/A | AM88: =IFERROR(NETWORKDAYS(D88,Q88,Hoja1!$A$1:$A$29),"N/A") -> N/A | AN88: =IFERROR(NETWORKDAYS(D88,AE88,Hoja1!$A$1:$A$29),"N/A") -> 3 | AO88: 0 | AP88: =AN88-AO88 -> 3 | AQ88: =IFERROR(NETWORKDAYS(AF88,AG88,Hoja1!$A$1:$A$29),"N/A") -> 8 | AR88: 3 | AS88: =AQ88-AR88 -> 5 | AT88: =IFERROR(NETWORKDAYS(D88,AG88,Hoja1!$A$1:$A$29),"N/A") -> 11 | AU88: =AT88-AO88-AR88 -> 8 | AV88: Referido cliente | AW88: KAFURY Y ZULUAGA SAS
A89: 15535 | B89: MP | C89: MP | D89: 46003 | E89: 46008 | F89: Cali | G89: CALI | H89: EMPRESA ENVIA EL CANDIDATO | I89: AUXILIAR ENFERMERIA | J89: SALUD/ASISTENCIAL | K89: Johana Fuentes Ardila | L89: 1 | M89: Finalizado - Llego hasta contratacion | N89: 0000-00-00 | O89: 0 | Q89: 0000-00-00 | R89: 0000-00-00 | S89: 0 | T89: 0000-00-00 | U89: 0000-00-00 | V89: 0000-00-00 | W89: 0000-00-00 | X89: 0000-00-00 | Y89: 0000-00-00 | Z89: 0000-00-00 | AA89: 1 | AB89: 1 | AC89: 0 | AD89: 46009 | AE89: 46010 | AF89: 46010 | AG89: 46027 | AH89: 46027 | AI89: =MONTH(AH89) -> 1 | AJ89: Sthephany Millan Torres | AK89: 20251212: GH solicita evaluar y contratar a Sthephany Millan. 20251218: se confirma concepto favorable. 20251219: se envia OC con F.I 5 ene. | AL89: =IFERROR(S89/O89,"N/A") -> N/A | AM89: =IFERROR(NETWORKDAYS(D89,Q89,Hoja1!$A$1:$A$29),"N/A") -> N/A | AN89: =IFERROR(NETWORKDAYS(D89,AE89,Hoja1!$A$1:$A$29),"N/A") -> 6 | AO89: 0 | AP89: =AN89-AO89 -> 6 | AQ89: =IFERROR(NETWORKDAYS(AF89,AG89,Hoja1!$A$1:$A$29),"N/A") -> 10 | AR89: 5 | AS89: =AQ89-AR89 -> 5 | AT89: =IFERROR(NETWORKDAYS(D89,AG89,Hoja1!$A$1:$A$29),"N/A") -> 15 | AU89: =AT89-AO89-AR89 -> 10 | AV89: Referido cliente | AW89: Fundación Valle del Lili
A90: 15536 | B90: MP | C90: MP | D90: 45995 | E90: 46008 | F90: Cali | G90: CALI | H90: VACANTE DESDE RECLUTAMIENTO | I90: AUXILIAR ENFERMERIA | J90: SALUD/ASISTENCIAL | K90: Johana Fuentes Ardila | L90: 1 | M90: Finalizado - Llego hasta contratacion | N90: 0000-00-00 | O90: 3 | P90: Si | Q90: 46001 | R90: 46003 | S90: 3 | T90: 0000-00-00 | U90: 0000-00-00 | V90: 0000-00-00 | W90: 0000-00-00 | X90: 0000-00-00 | Y90: 0000-00-00 | Z90: 0000-00-00 | AA90: 1 | AB90: 1 | AC90: 0 | AD90: 46009 | AE90: 46010 | AF90: 46010 | AG90: 46027 | AH90: 46027 | AI90: =MONTH(AH90) -> 1 | AJ90: Michel Steven Figueroa Castro | AK90: 20251204: se activa reclutamiento sin requi. 20251210: se envian 3 hv. 20251212: GH solicita evaluar a Michel Figueroa. 20251218: se confirma concepto favorable. 20251219: se envia OC con F.I 5 ene. | AL90: =IFERROR(S90/O90,"N/A") -> 1 | AM90: =IFERROR(NETWORKDAYS(D90,Q90,Hoja1!$A$1:$A$29),"N/A") -> 4 | AN90: =IFERROR(NETWORKDAYS(D90,AE90,Hoja1!$A$1:$A$29),"N/A") -> 11 | AO90: 0 | AP90: =AN90-AO90 -> 11 | AQ90: =IFERROR(NETWORKDAYS(AF90,AG90,Hoja1!$A$1:$A$29),"N/A") -> 10 | AR90: 5 | AS90: =AQ90-AR90 -> 5 | AT90: =IFERROR(NETWORKDAYS(D90,AG90,Hoja1!$A$1:$A$29),"N/A") -> 20 | AU90: =AT90-AO90-AR90 -> 15 | AV90: Computrabajo | AW90: Clínica Imbanaco
A91: 15537 | B91: MP | C91: MP | D91: 46003 | E91: 46008 | F91: Cali | G91: CALI | H91: EMPRESA ENVIA EL CANDIDATO | I91: AUXILIAR ENFERMERIA | J91: SALUD/ASISTENCIAL | K91: Johana Fuentes Ardila | L91: 1 | M91: Finalizado - Llego hasta contratacion | N91: 0000-00-00 | O91: 0 | Q91: 0000-00-00 | R91: 0000-00-00 | S91: 0 | T91: 0000-00-00 | U91: 0000-00-00 | V91: 0000-00-00 | W91: 0000-00-00 | X91: 0000-00-00 | Y91: 0000-00-00 | Z91: 0000-00-00 | AA91: 1 | AB91: 1 | AC91: 0 | AD91: 46009 | AE91: 46010 | AF91: 46010 | AG91: 46027 | AH91: 46027 | AI91: =MONTH(AH91) -> 1 | AJ91: Angela Maria Piamba Rengifo | AK91: 20251212: GH solicita evaluar a Angela Piamba. 20251218: se informa concepto favorable. 20251219: se envia OC con F.I 05 ene. | AL91: =IFERROR(S91/O91,"N/A") -> N/A | AM91: =IFERROR(NETWORKDAYS(D91,Q91,Hoja1!$A$1:$A$29),"N/A") -> N/A | AN91: =IFERROR(NETWORKDAYS(D91,AE91,Hoja1!$A$1:$A$29),"N/A") -> 6 | AO91: 0 | AP91: =AN91-AO91 -> 6 | AQ91: =IFERROR(NETWORKDAYS(AF91,AG91,Hoja1!$A$1:$A$29),"N/A") -> 10 | AR91: 5 | AS91: =AQ91-AR91 -> 5 | AT91: =IFERROR(NETWORKDAYS(D91,AG91,Hoja1!$A$1:$A$29),"N/A") -> 15 | AU91: =AT91-AO91-AR91 -> 10 | AV91: Referido cliente | AW91: IDC Hematoncólogos
A92: 15539 | B92: MP | C92: MP | D92: 46003 | E92: 46008 | F92: Cali | G92: CALI | H92: EMPRESA ENVIA EL CANDIDATO | I92: AUXILIAR ENFERMERIA | J92: SALUD/ASISTENCIAL | K92: Johana Fuentes Ardila | L92: 1 | M92: Finalizado - Llego hasta contratacion | N92: 0000-00-00 | O92: 0 | Q92: 0000-00-00 | R92: 0000-00-00 | S92: 0 | T92: 0000-00-00 | U92: 0000-00-00 | V92: 0000-00-00 | W92: 0000-00-00 | X92: 0000-00-00 | Y92: 0000-00-00 | Z92: 0000-00-00 | AA92: 2 | AB92: 1 | AC92: 0 | AD92: 46014 | AE92: 46014 | AF92: 46014 | AG92: 46030 | AH92: 46035 | AI92: =MONTH(AH92) -> 1 | AJ92: Victoria Eugenia Plaza Zuñiga | AK92: 20251212: Gh solicita evaluar a Yesenia Vallecilla. 20251217: se informa a GH que la candidata no pasa prueba integridad. 20251219: Gh solicita evaluar y contratar a Victoria Plaza. 20251223: Se carga informe y se envia OC con F.I 5 ene. 20251231: se solicita excepcion de Victoria de vacunas y rcp. gh informa que decide esperar a completar los documentos pte. Se modifica FI para 13 ENE. | AL92: =IFERROR(S92/O92,"N/A") -> N/A | AM92: =IFERROR(NETWORKDAYS(D92,Q92,Hoja1!$A$1:$A$29),"N/A") -> N/A | AN92: =IFERROR(NETWORKDAYS(D92,AE92,Hoja1!$A$1:$A$29),"N/A") -> 8 | AO92: 0 | AP92: =AN92-AO92 -> 8 | AQ92: =IFERROR(NETWORKDAYS(AF92,AG92,Hoja1!$A$1:$A$29),"N/A") -> 11 | AR92: 6 | AS92: =AQ92-AR92 -> 5 | AT92: =IFERROR(NETWORKDAYS(D92,AG92,Hoja1!$A$1:$A$29),"N/A") -> 18 | AU92: =AT92-AO92-AR92 -> 12 | AV92: Referido cliente | AW92: Hospital San Roque | AX92: Prueba de Integridad
A93: 15540 | B93: MP | C93: MP | D93: 46003 | E93: 46008 | F93: Cali | G93: CALI | H93: EMPRESA ENVIA EL CANDIDATO | I93: AUXILIAR ENFERMERIA | J93: SALUD/ASISTENCIAL | K93: Johana Fuentes Ardila | L93: 1 | M93: Finalizado - Llego hasta contratacion | N93: 0000-00-00 | O93: 0 | Q93: 0000-00-00 | R93: 0000-00-00 | S93: 0 | T93: 0000-00-00 | U93: 0000-00-00 | V93: 0000-00-00 | W93: 0000-00-00 | X93: 0000-00-00 | Y93: 0000-00-00 | Z93: 0000-00-00 | AA93: 1 | AB93: 1 | AC93: 0 | AD93: 46009 | AE93: 46010 | AF93: 46010 | AG93: 46027 | AH93: 46027 | AI93: =MONTH(AH93) -> 1 | AJ93: Santiago Bedoya Muñoz | AK93: 20251212: GH solicita evaluar a Santiago Bedoya. 20251218: se confirma concepto favorable. 20251219: se envia OC con F.I 5 ene. | AL93: =IFERROR(S93/O93,"N/A") -> N/A | AM93: =IFERROR(NETWORKDAYS(D93,Q93,Hoja1!$A$1:$A$29),"N/A") -> N/A | AN93: =IFERROR(NETWORKDAYS(D93,AE93,Hoja1!$A$1:$A$29),"N/A") -> 6 | AO93: 0 | AP93: =AN93-AO93 -> 6 | AQ93: =IFERROR(NETWORKDAYS(AF93,AG93,Hoja1!$A$1:$A$29),"N/A") -> 10 | AR93: 5 | AS93: =AQ93-AR93 -> 5 | AT93: =IFERROR(NETWORKDAYS(D93,AG93,Hoja1!$A$1:$A$29),"N/A") -> 15 | AU93: =AT93-AO93-AR93 -> 10 | AV93: Referido cliente | AW93: Clínica Colombia
A94: 15543 | B94: MP | C94: MP | D94: 46010 | E94: 46008 | F94: Cali | G94: CALI | H94: VACANTE DESDE RECLUTAMIENTO | I94: ENFERMERO(A) CM | J94: SALUD/ASISTENCIAL | K94: Alba Lucy Alape | L94: 1 | M94: Finalizado - Llego hasta contratacion | N94: 0000-00-00 | O94: 3 | P94: No | Q94: 46014 | R94: 46020 | S94: 3 | T94: 0000-00-00 | U94: 0000-00-00 | V94: 0000-00-00 | W94: 0000-00-00 | X94: 0000-00-00 | Y94: 0000-00-00 | Z94: 0000-00-00 | AA94: 2 | AB94: 1 | AC94: 0 | AD94: 46027 | AE94: 46027 | AF94: 46027 | AG94: 46031 | AH94: 46035 | AI94: =MONTH(AH94) -> 1 | AJ94: Jennifer Carolina Conde Cardozo | AK94: 20251204: se activa reclutamiento sin requi. 20251212: Se envian 5 hv. 20251217: gh solicita evaluar a Alison Marulanda y Juan Satizabal. Se programan pruebas. Ese mismo dia se envia requi. 20251219: Se decide no avanzar con los 2 candidatos. Se activa reclutamiento. 20251223: Se envian 5 hv. Pte retro por gh. 20251229: gh solicita evaluar a Jennifer Conde. Se programan pruebas. 20260105: se confirma informe y se envia OC FI 13 ENE. | AL94: =IFERROR(S94/O94,"N/A") -> 1 | AM94: =IFERROR(NETWORKDAYS(D94,Q94,Hoja1!$A$1:$A$29),"N/A") -> 3 | AN94: =IFERROR(NETWORKDAYS(D94,AE94,Hoja1!$A$1:$A$29),"N/A") -> 10 | AO94: 0 | AP94: =AN94-AO94 -> 10 | AQ94: =IFERROR(NETWORKDAYS(AF94,AG94,Hoja1!$A$1:$A$29),"N/A") -> 5 | AR94: 0 | AS94: =AQ94-AR94 -> 5 | AT94: =IFERROR(NETWORKDAYS(D94,AG94,Hoja1!$A$1:$A$29),"N/A") -> 14 | AU94: =AT94-AO94-AR94 -> 14 | AV94: Computrabajo | AW94: HOSPITAL UNIVERSITARIO DEL VALLE
A95: 15544 | B95: MP | C95: MP | D95: 46010 | E95: 46008 | F95: Cali | G95: CALI | H95: VACANTE DESDE RECLUTAMIENTO | I95: ENFERMERO(A) CM | J95: SALUD/ASISTENCIAL | K95: Alba Lucy Alape | L95: 1 | M95: Finalizado - Llego hasta contratacion | N95: 0000-00-00 | O95: 3 | P95: No | Q95: 46014 | R95: 46020 | S95: 3 | T95: 0000-00-00 | U95: 0000-00-00 | V95: 0000-00-00 | W95: 0000-00-00 | X95: 0000-00-00 | Y95: 0000-00-00 | Z95: 0000-00-00 | AA95: 2 | AB95: 1 | AC95: 0 | AD95: 46027 | AE95: 46027 | AF95: 46027 | AG95: 46031 | AH95: 46035 | AI95: =MONTH(AH95) -> 1 | AJ95: Luisa Fernanda Granada Bueno | AK95: 20251204: se activa reclutamiento sin requi. 20251212: Se envian 5 hv. 20251217: gh solicita evaluar a Alison Marulanda y Juan Satizabal. Se programan pruebas. Ese mismo dia se envia requi. 20251219: Se decide no avanzar con los 2 candidatos. Se activa reclutamiento. 20251223: Se envian 5 hv. Pte retro por gh. 20251229: gh solicita evaluar a Luisa Granada. Se programan pruebas. 20260105: se confirma informe y se envia OC FI 13 ENE. | AL95: =IFERROR(S95/O95,"N/A") -> 1 | AM95: =IFERROR(NETWORKDAYS(D95,Q95,Hoja1!$A$1:$A$29),"N/A") -> 3 | AN95: =IFERROR(NETWORKDAYS(D95,AE95,Hoja1!$A$1:$A$29),"N/A") -> 10 | AO95: 0 | AP95: =AN95-AO95 -> 10 | AQ95: =IFERROR(NETWORKDAYS(AF95,AG95,Hoja1!$A$1:$A$29),"N/A") -> 5 | AR95: 0 | AS95: =AQ95-AR95 -> 5 | AT95: =IFERROR(NETWORKDAYS(D95,AG95,Hoja1!$A$1:$A$29),"N/A") -> 14 | AU95: =AT95-AO95-AR95 -> 14 | AV95: Computrabajo | AW95: PLASTIKOS CIRIJANOS
A96: 15547 | B96: MP | C96: MP | D96: 45992 | E96: 45992 | F96: Cali | G96: CALI | H96: VACANTE DESDE RECLUTAMIENTO | I96: APRENDIZ SENA | J96: ESTUDIANTE/APRENDIZ | K96: Susan Bermeo Saenz | L96: 1 | M96: Finalizado - Llego hasta contratacion | N96: 0000-00-00 | O96: 5 | P96: Si | Q96: 45993 | R96: 45993 | S96: 5 | T96: 0000-00-00 | U96: 0000-00-00 | V96: 0000-00-00 | W96: 0000-00-00 | X96: 0000-00-00 | Y96: 0000-00-00 | Z96: 0000-00-00 | AA96: 1 | AB96: 1 | AC96: 0 | AD96: 46010 | AE96: 46013 | AF96: 46013 | AG96: 46024 | AH96: 46027 | AI96: =MONTH(AH96) -> 1 | AJ96: Leidy Rossana Marquez Campo | AK96: 20251201:Se activo reclutamiento. 202515:El cliente envio a evaluar a Leidy Marquez. 20251222:El cliente envio a contratar a Leidy. Se enviaro a contratacion con FI 5 Enero. | AL96: =IFERROR(S96/O96,"N/A") -> 1 | AM96: =IFERROR(NETWORKDAYS(D96,Q96,Hoja1!$A$1:$A$29),"N/A") -> 2 | AN96: =IFERROR(NETWORKDAYS(D96,AE96,Hoja1!$A$1:$A$29),"N/A") -> 15 | AO96: 0 | AP96: =AN96-AO96 -> 15 | AQ96: =IFERROR(NETWORKDAYS(AF96,AG96,Hoja1!$A$1:$A$29),"N/A") -> 8 | AR96: 3 | AS96: =AQ96-AR96 -> 5 | AT96: =IFERROR(NETWORKDAYS(D96,AG96,Hoja1!$A$1:$A$29),"N/A") -> 22 | AU96: =AT96-AO96-AR96 -> 19 | AV96: Bolsa de empleo Ins. Educativa | AW96: N/A
A97: 15554 | B97: MP | C97: MP | D97: 46009 | E97: 46009 | F97: Cali | G97: DIRECCION NACIONAL | H97: VACANTE DESDE RECLUTAMIENTO | I97: APRENDIZ SENA | J97: ESTUDIANTE/APRENDIZ | K97: Alba Lucy Alape | L97: 1 | M97: Finalizado - Llego hasta contratacion | N97: 0000-00-00 | O97: 4 | P97: Si | Q97: 46010 | R97: 46013 | S97: 4 | T97: 0000-00-00 | U97: 0000-00-00 | V97: 0000-00-00 | W97: 0000-00-00 | X97: 0000-00-00 | Y97: 0000-00-00 | Z97: 0000-00-00 | AA97: 1 | AB97: 1 | AC97: 0 | AD97: 46021 | AE97: 46030 | AF97: 46031 | AG97: 46042 | AH97: 46044 | AI97: =MONTH(AH97) -> 1 | AJ97: Valeria Villegas Muñoz | AK97: 20251218: Se activa reclutamiento. 20251219: se envian 4 hv. pte retro por gh. 20251222: gh solicita evaluar a Valeria Villegas. Se programan pruebas.20251230: se envia informe. pte retro por gh. 20260108; gh solicita avanzar contratacion con Valeria. 20260109: se envia OC FI 22 Enero. | AL97: =IFERROR(S97/O97,"N/A") -> 1 | AM97: =IFERROR(NETWORKDAYS(D97,Q97,Hoja1!$A$1:$A$29),"N/A") -> 2 | AN97: =IFERROR(NETWORKDAYS(D97,AE97,Hoja1!$A$1:$A$29),"N/A") -> 14 | AO97: 0 | AP97: =AN97-AO97 -> 14 | AQ97: =IFERROR(NETWORKDAYS(AF97,AG97,Hoja1!$A$1:$A$29),"N/A") -> 7 | AR97: 2 | AS97: =AQ97-AR97 -> 5 | AT97: =IFERROR(NETWORKDAYS(D97,AG97,Hoja1!$A$1:$A$29),"N/A") -> 21 | AU97: =AT97-AO97-AR97 -> 19 | AV97: Bolsa de empleo Ins. Educativa | AW97: NA
A98: 15564 | B98: BANCOOMEVA | C98: BANCOOMEVA | D98: 46013 | E98: 46013 | F98: Cali | G98: POPAYAN | H98: VACANTE DESDE RECLUTAMIENTO | I98: SUPERNUMERARIO/A | J98: CARGO COMERCIAL | K98: Carolina Cordoba Betancourt | L98: 1 | M98: Finalizado - Llego hasta contratacion | N98: 0000-00-00 | O98: 3 | P98: Si | Q98: 46021 | R98: 46021 | S98: 3 | T98: 0000-00-00 | U98: 0000-00-00 | V98: 0000-00-00 | W98: 0000-00-00 | X98: 0000-00-00 | Y98: 0000-00-00 | Z98: 0000-00-00 | AA98: 1 | AB98: 1 | AC98: 0 | AD98: 46034 | AE98: 46034 | AF98: 46034 | AG98: 46044 | AH98: 46045 | AI98: =MONTH(AH98) -> 1 | AJ98: Yurani Andrea Muñoz Bolaños | AK98: 20251222: se envia a reclutamiento.20251230: se envian 3cv a GH.20260107: se realiza seguimiento.20260108: GH solicita evaluar a Yurani Muñoz.20260112: se carga evaluacion en sf,GH solicita enviar O.C de yurani. 20260114: Se envia O.C con F.I 22 Enero. | AL98: =IFERROR(S98/O98,"N/A") -> 1 | AM98: =IFERROR(NETWORKDAYS(D98,Q98,Hoja1!$A$1:$A$29),"N/A") -> 6 | AN98: =IFERROR(NETWORKDAYS(D98,AE98,Hoja1!$A$1:$A$29),"N/A") -> 13 | AO98: 0 | AP98: =AN98-AO98 -> 13 | AQ98: =IFERROR(NETWORKDAYS(AF98,AG98,Hoja1!$A$1:$A$29),"N/A") -> 8 | AR98: 3 | AS98: =AQ98-AR98 -> 5 | AT98: =IFERROR(NETWORKDAYS(D98,AG98,Hoja1!$A$1:$A$29),"N/A") -> 21 | AU98: =AT98-AO98-AR98 -> 18 | AV98: Computrabajo | AW98: Banco Finandina
A99: 15566 | B99: COOMEVA | C99: USC | D99: 46021 | E99: 46013 | F99: Cali | G99: CALI | H99: EMPRESA ENVIA EL CANDIDATO | I99: AUXILIAR MAESTRAS | J99: AUXILIAR/OPERATIVO | K99: Susan Bermeo Saenz | L99: 1 | M99: Finalizado - Llego hasta contratacion | N99: 0000-00-00 | O99: 0 | Q99: 0000-00-00 | R99: 0000-00-00 | T99: 0000-00-00 | U99: 0000-00-00 | V99: 0000-00-00 | W99: 0000-00-00 | X99: 0000-00-00 | Y99: 0000-00-00 | Z99: 0000-00-00 | AA99: 1 | AB99: 1 | AC99: 0 | AD99: 46030 | AE99: 46035 | AF99: 46035 | AG99: 46044 | AH99: 46045 | AI99: =MONTH(AH99) -> 1 | AJ99: Luisa Maria Cabrera Calapsu | AK99: 20251223: Se activo reclutamiento. (6) 20251230: gh solicito suspender reclutamiento y envio a evaluar a Luisa Cabrera. Se enviaron pruebas y se cito a entrevista para el 6 de Enero. 20260108:Se subio informe y se le informo al cliente. (1) 20260113:El cliente envio a contratar a Luisa. Se envio a contratacion con FI 22 ENE. | AL99: =IFERROR(S99/O99,"N/A") -> N/A | AM99: =IFERROR(NETWORKDAYS(D99,Q99,Hoja1!$A$1:$A$29),"N/A") -> N/A | AN99: =IFERROR(NETWORKDAYS(D99,AE99,Hoja1!$A$1:$A$29),"N/A") -> 9 | AO99: 0 | AP99: =AN99-AO99 -> 9 | AQ99: =IFERROR(NETWORKDAYS(AF99,AG99,Hoja1!$A$1:$A$29),"N/A") -> 8 | AR99: 3 | AS99: =AQ99-AR99 -> 5 | AT99: =IFERROR(NETWORKDAYS(D99,AG99,Hoja1!$A$1:$A$29),"N/A") -> 16 | AU99: =AT99-AO99-AR99 -> 13 | AV99: Movimiento Interno | AW99: Coomeva Cooperativa
A100: 15578 | B100: FUNDACION COOMEVA | C100: FUNDACION COOMEVA | D100: 46017 | E100: 46017 | F100: Cali | G100: PALMIRA | H100: EMPRESA ENVIA EL CANDIDATO | I100: ANALISTA REG MICROCREDITO ADMINISTRATIVO | J100: ANALISTA/PROFESIONAL/COORDINADOR | K100: Carolina Cordoba Betancourt | L100: 1 | M100: Finalizado - Llego hasta contratacion | N100: 0000-00-00 | O100: 0 | Q100: 0000-00-00 | R100: 0000-00-00 | S100: 0 | T100: 0000-00-00 | U100: 0000-00-00 | V100: 0000-00-00 | W100: 0000-00-00 | X100: 0000-00-00 | Y100: 0000-00-00 | Z100: 0000-00-00 | AA100: 1 | AB100: 1 | AC100: 0 | AD100: 46035 | AE100: 46035 | AF100: 46036 | AG100: 46042 | AH100: 46044 | AI100: =MONTH(AH100) -> 1 | AJ100: Paula Andrea Rojas Gonzalez | AK100: 20260106: GH solicita programar prueba tecnica paula interna y Luisa Maria externa. 20260108: se confirma prueba tecnica de Paula, laura desiste del proceso, GH solicita evaluar a Paula. 20260113: se carga evaluacion, GH solicita enviar a contratacion. 20260114: se envia O.C con F.I 22 Enero, se adjunta aprobacion del Sr Manuel Issa. | AL100: =IFERROR(S100/O100,"N/A") -> N/A | AM100: =IFERROR(NETWORKDAYS(D100,Q100,Hoja1!$A$1:$A$29),"N/A") -> N/A | AN100: =IFERROR(NETWORKDAYS(D100,AE100,Hoja1!$A$1:$A$29),"N/A") -> 11 | AO100: 0 | AP100: =AN100-AO100 -> 11 | AQ100: =IFERROR(NETWORKDAYS(AF100,AG100,Hoja1!$A$1:$A$29),"N/A") -> 5 | AR100: 0 | AS100: =AQ100-AR100 -> 5 | AT100: =IFERROR(NETWORKDAYS(D100,AG100,Hoja1!$A$1:$A$29),"N/A") -> 16 | AU100: =AT100-AO100-AR100 -> 16 | AV100: Referido cliente | AW100: Fundación coomeva
...

Sheet Hoja1
A1: 45778 | D1: Bolsa de empleo Ins. Educativa
A2: 45810 | D2: Busqueda directa
A3: 45831 | D3: Busqueda booleana
A4: 45838 | D4: Computrabajo
A5: 45876 | D5: Coonectados
A6: 45887 | D6: Facebook
A7: 45943 | D7: Ferias laborales
A8: 45964 | D8: Ferias Universitarias
A9: 45978 | D9: Instagram
A10: 45999 | D10: Linkedin
A11: 46016 | D11: Magneto
A12: 46023 | D12: Movimiento Interno
... A16: 46115 | D16: Whatsapp
A17: 46143
A18: 46160
A19: 46181
A20: 46188
A21: 46202
A22: 46223
A23: 46241
A24: 46251
A25: 46307
A26: 46328
A27: 46342
A28: 46364
A29: 46381

Sheet Requis
A1: Número Requisicion | B1: Fecha Recepción | C1: Fecha de aprobación Requisición | D1: # Personas Solicitadas | E1: Estado Requisición | F1: Fecha Afinamiento Perfil | G1: # hojas de vida presentadas al cliente | H1: ¿Pertenece a la Primera Terna? | I1: Fecha entrega hoja de vida al cliente | J1: Fecha de aprobación de HV por el cliente | K1: Número de hojas de vida aprobadas por el cliente | L1: Fecha de envio del perfil | M1: Fecha Publicación de Concurso | N1: Fecha entrega matriz de inscritos | O1: Fecha Notificación quienes continúan a prueba técnica | P1: Fecha aplicación Prueba técnica | Q1: Fecha envío prueba técnica al cliente | R1: Fecha Notificación quienes continúan a proceso de selección | S1: Número de personas evaluadas | T1: Número de informes entregados | U1: Número de referencias | V1: Fecha de entrega de informe al cliente | W1: Fecha de notificación del cliente persona seleccionada | X1: Fecha de solicitud contratacion | Y1: Fecha Firma Contrato o Cierre de requisición | Z1: Fecha de Ingreso | AA1: Mes | AB1: Candidato(s) contratado(s): | AC1: Observacion | AD1: Efectividad reclutamiento | AE1: Oportunidad en el proceso de reclutamiento | AF1: Oportunidad en proceso de Selección | AG1: Dias a Descontar Selección | AH1: Oportunidad Selección | AI1: Oportunidad en proceso de Contratación | AJ1: Dias a Descontar Contratación | AK1: Oportunidad Contratacion | AL1: Tiempo Total Proceso | AM1: Oportunidad SyC | AN1: Candidato 1 | AO1: Candidato 2 | AP1: Candidato 3 | AQ1: Candidato 4 | AR1: Candidato 5 | AS1: FK_Empresa | AT1: FK_Cargo | AU1: FK_Psicologo | AV1: FK_Fuente | AW1: FK_Calendario
A2: 14104 | B2: 45909 | C2: 45797 | D2: 1 | E2: Finalizado - Llego hasta contratacion | F2: 0000-00-00 | G2: 18 | H2: No | I2: 46027 | J2: 46027 | K2: 15 | L2: 0000-00-00 | M2: 0000-00-00 | N2: 0000-00-00 | O2: 0000-00-00 | P2: 0000-00-00 | Q2: 0000-00-00 | R2: 0000-00-00 | S2: 5 | T2: 5 | U2: 0 | V2: 46031 | W2: 46037 | X2: 46037 | Y2: 46048 | Z2: 46048 | AA2: =MONTH(Z2) -> 1 | AB2: Juan Camilo Cuartas Echeverri | AC2: 20250520: GH solicita reclutamiento, se le solicita a GH el aval del corporativo para continuar. 20250521: Se detiene vacante hasta tener aval del corporativo. 20250618: Se reanuda proceso por cargo en estructura de la empresa, pdte enviar reclutamiento. 20250624: Se envian 3 HV (Tatiana, Isabella, Cristian), pdte retro GH. 20250701: gh solicita realizar prueba tecnica de Isabella Gonzales y Cristian Amaguaña. 20250702: se adjunta prueba tecnica. pte retro por gh. 20250704: solicitan evaluar a isabella para Analista Reg Microcredito FUN y Cristian no avanza prueba tecnica. Se activa reclutamiento. 20250707: Se envia 2 hv. pte retro por gh. 20250715: gh envia retro y solicita avanzar a prueba tecnica con Juan Carlos Roman. 20250717: se envia prueba tecnica de Juan Roman. Pte retro por gh. 20250724: gh solicita reasignar requi a la Ciudad de Medellin por cambio de la pocision. 20250724: GH notifica el cambio de RQ para la ciudad de Medellin, se informa que se tendrá en cuenta los candidatos en back de la vacante como Analista de Microcredito. 20250728: se hace el ofrecimiento a la candidata Luby Dayana Guisao quien acepta, sin embargo, se hace validacion con JI para valorar la disponibilidad de viajar. 20250801: candidata se presenta a entrevista, sin embargo, por solicitud de JI se solicita buscar nuevos candidatos considerando que la candidata podría no cumplir con los requisitos para la disponibilidad de viaje. 20250805: se comparte 1 HV a la espera de disponibilidad para entrevista. 20250806: se programa entrevista para el viernes 8 de ago. 20250811: Gh indica que no fue posible conectarse al espacio. 20250812: JI solicita programar la entrevista para el miércoles 13 y se comparten 2 HV (Marlon Pacheco) adicionales. 20250813: se presenta el candidato Marlon Pacheco y continua proceso para aplicar PS. 20250819: se comparte retroliamentacion con concepto aprobado de Marlon Pacheco 20250822: se solicita retroalimentacion a GH y JI. 20250825: JI manfiesta la intención de que el candidato sea contratado en la RQ 14772 para Analista Regional. 20250826: se continua reclutamiento. 20250827: JI mangiiesta que el candidato Marlon Pacheco desea continuar el proceso para supernumerario, sin embargo, el candidato no responde los mensajes 20250829: se comparten 2 HV para entrevista el 2 de sep. 20250902: se presetan dos candidatos, pero no aprueban proceso de entrevista. 20250908: se envían 3 HV para entrevista el 9 de sep. 20250909: se presentan dos candidatos, uno aprueba el proceso pero será tenido en cuenta para la RQ 14772 Ana de Microcrédito. 20250911: se comparte 1 HV adicional (Felipe Guerra) 20250916: se comparte otra HV (Brayan Baron) y se programa entrevista para el día de hoy. Se presentan los dos candidatos, sin embargo, no aprueban proceso de entrevista iniguno de los dos. 20250922: se comparte 1 HV para considerar y se continua reclutamiento. 20250930: se programa entrevista para el 1 de oct solo con GH por falta de disponibilidad de JI y se comparte 1 HV más 20251001: se presenta 1 candidato, pero no aprueba proceso, se programa otra entrevista para el 2 de octubre y se comparte 1 Hv adicional. 20251002: se presenta 1 candidato y no aprueba proceso 20251006: se continua con reclutamiento. 20251014: se continua proceso reclutamiento ya que no hay candidatos que cumplan con el perfil.20251020: se comparte 1 HV, sin embargo, se hace validación previa ya que requiere excepción en el perfil académico y GH informa que debe cumplir con el perfil requerido 20251023: se comparte 1 HV y se programa entrevista para el 24 de oct. 20251024: se presenta el candidato pero no aprueba entrevista. 20251028: se continua reclutamiento 20251030: se continua reclutamiento 20251104: se comparte 1 HV. 20251107: candidata de la HV pendiente indica que no tiene aún disponibilidad para iniciar el proceso 20251111: candidata inidica que cuenta con disponibilidad para el 12 de nov 20251112: se presenta la candidata, pero no aprueba proceso de entrevista 20251118: se continua reclutamiento 20251124: continua reclutamiento. 20251127: se comparte 1 HV adicional para entrevista el 1 de dic. 20251201: el candidato programado no se conecta al espacio de entrevista. 20251209: se continua reclutamiento 20251212: se comparte 1 HV para ser tenida en cuenta. 20251229: Se compartio una hoja de vida pendiente de la retroalimentacion de GH 20260105: se comparte 1 HV para entrevista el 6 de enero. 20260106: se presenta Juan Camilo Cuartas y aprueba entrevista con GH, solicita programar evaluacion.20260109: se comparte retroalimentacion con concepto aprobado 20250114: se valida con GH e indican que están aun a la espera de confirmar la posibilidad de dar continuidad al candidato 20250115: GH solicita el envio a contratacion de Juan Camilo Cuartas. Se envia OC 20260119: candidato registra con novedad en ES, sin embargo, se gestiona excepcion con GH. 20260121: candidato se encuentra en apertura de cuenta y EM 20260122: candidato presenta novedad con apertura de cuenta y GH brinda autorizacion para el pago por cheque 20260123: contratacion confirma ingreso de Juan Camilo Cuartas con fecha de inicio 26 de ene | AD2: =IFERROR(K2/G2,"N/A") -> 0.83333333 | AE2: =IFERROR(NETWORKDAYS(B2,I2,Hoja1!$A$1:$A$29),"N/A") -> 79 | AF2: =IFERROR(NETWORKDAYS(B2,W2,Hoja1!$A$1:$A$29),"N/A") -> 86 | AG2: 10 | AH2: =AF2-AG2 -> 76 | AI2: =IFERROR(NETWORKDAYS(X2,Y2,Hoja1!$A$1:$A$29),"N/A") -> 8 | AJ2: 3 | AK2: =AI2-AJ2 -> 5 | AL2: =IFERROR(NETWORKDAYS(B2,Y2,Hoja1!$A$1:$A$29),"N/A") -> 93 | AM2: =AL2-AG2-AJ2 -> 80 | AN2: Desiste | AS2: FUNDACION COOMEVAMedellinMEDELLINFUNDACION COOMEVA | AT2: SUPERNUMERARIO/ACARGO COMERCIALVACANTE DESDE RECLUTAMIENTO | AU2: Fredy Alej | AV2: ComputrabajoCooperativa Afroamericano | AW2: 45909457970000-00-0046027460270000-00-000000-00-000000-00-000000-00-000000-00-000000-00-000000-00-0046031460374603746048460481
A3: 14454 | B3: 45953 | C3: 45847 | D3: 1 | E3: Finalizado - Llego hasta contratacion | F3: 0000-00-00 | G3: 6 | H3: No | I3: 45968 | J3: 45968 | K3: 6 | L3: 0000-00-00 | M3: 0000-00-00 | N3: 0000-00-00 | O3: 0000-00-00 | P3: 0000-00-00 | Q3: 0000-00-00 | R3: 0000-00-00 | S3: 6 | T3: 3 | U3: 0 | V3: 46010 | W3: 46036 | X3: 46036 | Y3: 46042 | Z3: 46044 | AA3: =MONTH(Z3) -> 1 | AB3: Ricardo Carrillo Higuita | AC3: 20250709: GH solicita evaluacion de Anny Stephany Moreno Ruiz. 20250711: Anny ha realizado unicamente una prueba, solicita tiempo adicional para culminar las demas. 20250714: Se informa que la candidata tiene pendiente 2 pruebas. Se compromete a realizarlas ese mismo dia. Se agenda entrevistas para el 15 de julio. (3) 20250717: se informa a GH que la candidata no cumple perfil academico. 20250718: GH solicita no continuar y activar reclutamiento. 20250728: se envian 5 hv. 20250813: Se solicito retroaliementación del proceso. 20250815:El cliente informa que aún se encuentran revisando los perfiles. 20250820:Se solicito nuevamente retroalimentacion del proceso. 20250821:EL cliente informa que estan a la espera de la aprobacion del jefe para continuar con el proceso.(19) 20250827:El cliente envio a contratar a Anny candidata que ya estaba evaluada por Leidy Checa. Se envio a la candidata a contratación con excepción por formación academica. 20250902: La candidata no paso ES y se solicito mas hojas de vida. 20250903:Se solicita retroalimentación de las 5 hojas de vida enviadas el 28 de Julio. (22) 20250904: El cliente informa que ya reviso las HV, sin embargo pidio mas reclutamiento. (10) 20250910: Se enviaron 6 hojas de vida mas sin filtro tefonico. 20250919: Se solito retroalimentación de las hojas de vida enviadas. 20250926: Se volvio a solicitar retroalimentacion. El cliente informa que esta en entrevistas y el Lunes me da avances. (12) 20250930:El cliente envio a evaluar a Andres Tovar y David Barreros, se enviaron pruebas y se citaran a entrevista para 1 de Octubre. Andres Felipe Tovar no contesta. 20251003:Se cito a entrevista a Andres para el dia 6 de Octubre y se enviaron pruebas. (4) 20251008:David Barrios aun no ha terminado las pruebas Bluesite. (3)20251010:Se subio informe y se le informo al cliente. 20251016:El cliente entrevistara por ultima vez a David para tomar una decision. (4) 20251017:El cliente envio a contratar a David. 20251020: El candidato no ha enviado los documentos. (3) 20251022:Se envio a contratacion con FI Nov 4 20251023: El candidato salio con anotaciones y no se continuara proceso de contratacion. 20251027: Se le solicito al cliente retroalimentacion del proceso. (8) 20251031: GH solicita reclutamiento.20251107: Se enviaron 3 hojas de vida (Lili Nieto, Jessica Armero y Sandra Angulo) (19) 20251209:El cliente envio a evaluar a 3 personas (Leidy Pedrosa, Ricardo Carrillo, Luis Medallo). 20251210:Se enviaron 3 hojas de vida(Jose Fernando Villaquiran, Yesika Robles y Alvaro Solarte) 20251211:GH solicito pruebas para Leidy Pedrosa, Ricardo Carrillo y Luis Medolla. 20251212:Los candidatos aun no han realizado pruebas y tampoco han enviado documentos para enviarlos a estudios de seguridad. 20251215:Los candidato enviaron los documentos y fueron enviados a ES. Pendiente resultados. 20251217:El cliente envio a evlauar a los 3 candidatos. 20251219:Se envio novedad al cliente de resultados de ES. 20251222:Se reunio con el cliente para retroalimentacion de dos de los 3 canddiatos. Lady no se ha podido presentar a entrevista y se volvio a reprogramar para el 23. (6) 20251224: Se evaluo a la candidata y se le dio retroalimentación al cliente. 20251230:Se solicito retroalimentacion. 20260107: Se solicito retroaimentacion y el cliente informa que el dia de mañana tomara una decision. 20260109:El envio evaluar Jose Fernando Villaquiran. 20260114:El cliente envio a contratar a Ricardo con FI 22 Ene. | AD3: =IFERROR(K3/G3,"N/A") -> 1 | AE3: =IFERROR(NETWORKDAYS(B3,I3,Hoja1!$A$1:$A$29),"N/A") -> 11 | AF3: =IFERROR(NETWORKDAYS(B3,W3,Hoja1!$A$1:$A$29),"N/A") -> 54 | AG3: 30 | AH3: =AF3-AG3 -> 24 | AI3: =IFERROR(NETWORKDAYS(X3,Y3,Hoja1!$A$1:$A$29),"N/A") -> 5 | AJ3: 0 | AK3: =AI3-AJ3 -> 5 | AL3: =IFERROR(NETWORKDAYS(B3,Y3,Hoja1!$A$1:$A$29),"N/A") -> 58 | AM3: =AL3-AG3-AJ3 -> 28 | AN3: Estudio de seguridad | AO3: Estudio de seguridad | AS3: CLUB LOS ANDESCaliSANTANDER DE QUILICHAOCLUB LOS ANDES | AT3: JEFE COMERCIALJEFE/DIRECTOR/GERENTEVACANTE DESDE RECLUTAMIENTO | AU3: Susan Berm | AV3: ComputrabajoGI Group (INSSA) | AW3: 45953458470000-00-0045968459680000-00-000000-00-000000-00-000000-00-000000-00-000000-00-000000-00-0046010460364603646042460441
A4: 14619 | B4: 45972 | C4: 45873 | D4: 1 | E4: Finalizado - Llego hasta contratacion | F4: 0000-00-00 | G4: 10 | H4: No | I4: 45996 | J4: 46006 | K4: 10 | L4: 0000-00-00 | M4: 0000-00-00 | N4: 0000-00-00 | O4: 0000-00-00 | P4: 0000-00-00 | Q4: 0000-00-00 | R4: 0000-00-00 | S4: 2 | T4: 2 | U4: 0 | V4: 46030 | W4: 46030 | X4: 46031 | Y4: 46043 | Z4: 46044 | AA4: =MONTH(Z4) -> 1 | AB4: Valery Palechor Acosta | AC4: 20250808: El cliente solicito reclutamiento. 20250813: Se enviaron 2 hojas de vida (Jhohan y Jhon Sebastian). 20250820:Se solicito retroalimentación 20250821:El cliente informa que realizaran entrevistas el dia Martes 26 de Agosto. 20250827:El cliente informo que el candidato citado no se presento a entrevista por tal razón solicito mas hojas de vida. 20250827:Se enviaron 2 hojas de vida (Jaider y Daniela) 20250902:Se solicito retroalimentación al cliente. 20250903: El cliente informo que esta solicitando espacio para entrevista. 20250915: Pte retro por gh. 20250924: gh envia retro, los candidatos ya no estan disponibles. Se activa reclutamiento. 20251006: Se envian 2 hv. Pte retro por gh. 20251015: gh envia retro, se solicita activar reclutamiento. 20251023: Se envian 2 hv. Pte retro por gh. 20251030: gh envia retro de hv y refiere que se programa a franci para entrevista y se solicita activar reclutamiento. 20251106: Gh solicita evaluar a franci, sin embargo solicita mas reclutamiento. 20251111: se informa a gh que la candidata Franci desiste del proceso. 20251114: Se envian 3 hv. Pte retro por gh. 20251121: gh envia retro y se activa reclutamiento. 20251124: se envian 2 hv. pte retro por gh. 20251125: gh solicita evaluar a contratar a Angela Natalia Ruales . Se programan pruebas. 20251128: Se envia OC FI 10 Dic. 20251204: se notifica a gh que se cancela proceso ya que la institucion no nos envia carta de presentacion. Se activa reclutamiento. 20251205: se envian 3 hv. Pte retro por gh. 20251215: pte retro por gh. 20251226: Pte retro por gh. 20250106: Pte retro por gh. (8) 20260106:gh solicita evaluar a Valery Palechor y solicita activar mas reclutamiento. 20260108: gh solicita avanzar contratacion con Valery Palechor. 20250109: Se envia OC FI 22 Enero. | AD4: =IFERROR(K4/G4,"N/A") -> 1 | AE4: =IFERROR(NETWORKDAYS(B4,I4,Hoja1!$A$1:$A$29),"N/A") -> 18 | AF4: =IFERROR(NETWORKDAYS(B4,W4,Hoja1!$A$1:$A$29),"N/A") -> 39 | AG4: 12 | AH4: =AF4-AG4 -> 27 | AI4: =IFERROR(NETWORKDAYS(X4,Y4,Hoja1!$A$1:$A$29),"N/A") -> 8 | AJ4: 3 | AK4: =AI4-AJ4 -> 5 | AL4: =IFERROR(NETWORKDAYS(B4,Y4,Hoja1!$A$1:$A$29),"N/A") -> 47 | AM4: =AL4-AG4-AJ4 -> 32 | AN4: Candidato desiste | AO4: Candidato desiste | AS4: COOMEVACaliDIRECCION NACIONALEYD | AT4: APRENDIZ SENAESTUDIANTE/APRENDIZVACANTE DESDE RECLUTAMIENTO | AU4: Alba Lucy | AV4: Bolsa de empleo Ins. EducativaNA | AW4: 45972458730000-00-0045996460060000-00-000000-00-000000-00-000000-00-000000-00-000000-00-000000-00-0046030460304603146043460441
